Workbook

Sheet 1.1_各事業 TA 預算規劃_人力時間配置
A1: 子公司 | B1: 事業單位 | C1: Si 編號 | D1: TA 編號 | E1: 價值鏈專案預算代號 | F1: 費用單位 | G1: 費用類型 | H1: 姓名 | I1: 備註 | J1: 46023 | K1: 46054 | L1: 46082 | M1: 46113 | N1: 46143 | O1: 46174 | P1: 46204 | Q1: 46235 | R1: 46266 | S1: 46296 | T1: 46327 | U1: 46357 | V1: 2026 year
A3: TW | B3: POS | C3: ENTSi1 | D3: ENT26TA1 | E3: NA | F3: 執行長室 : 客戶價值中心 : 客戶成功管理部 : 客戶成功團隊 | G3: 人事費用 | H3: 陳馨如 | J3: 0.2 | K3: 0.2 | L3: 0.2 | M3: 0.2 | N3: 0.2 | O3: 0.2 | P3: 0.2 | Q3: 0.2 | R3: 0.2 | S3: 0.2 | T3: 0.2 | U3: 0.2 | V3: =SUM(J3:U3) -> 2.4
A4: TW | B4: OMO | C4: OrderingSi1 | D4: Ordering26TA2 | E4: NA | F4: 執行長室 : 客戶價值中心 : 客戶成功管理部 : 客戶成功團隊 | G4: 人事費用 | H4: 陳馨如 | J4: 0.4 | K4: 0.4 | L4: 0.4 | M4: 0.4 | N4: 0.4 | O4: 0.4 | P4: 0.4 | Q4: 0.4 | R4: 0.4 | S4: 0.4 | T4: 0.4 | U4: 0.4 | V4: =SUM(J4:U4) -> 4.8
A5: TW | B5: OMO | C5: ReservationSi1 | D5: Reservation26TA1 | E5: NA | F5: 執行長室 : 客戶價值中心 : 客戶成功管理部 : 客戶成功團隊 | G5: 人事費用 | H5: 陳馨如 | J5: 0.4 | K5: 0.4 | L5: 0.4 | M5: 0.4 | N5: 0.4 | O5: 0.4 | P5: 0.4 | Q5: 0.4 | R5: 0.4 | S5: 0.4 | T5: 0.4 | U5: 0.4 | V5: =SUM(J5:U5) -> 4.8
A6: TW | B6: POS | C6: ENTSi1 | D6: ENT26TA1 | E6: NA | F6: 執行長室 : 客戶價值中心 : 客戶成功管理部 : 客戶成功團隊 | G6: 人事費用 | H6: 楊麗涵 | J6: 0.2 | K6: 0.2 | L6: 0.2 | M6: 0.2 | N6: 0.2 | O6: 0.2 | P6: 0.2 | Q6: 0.2 | R6: 0.2 | S6: 0.2 | T6: 0.2 | U6: 0.2 | V6: =SUM(J6:U6) -> 2.4
A7: TW | B7: OMO | C7: OrderingSi1 | D7: Ordering26TA2 | E7: NA | F7: 執行長室 : 客戶價值中心 : 客戶成功管理部 : 客戶成功團隊 | G7: 人事費用 | H7: 楊麗涵 | J7: 0.4 | K7: 0.4 | L7: 0.4 | M7: 0.4 | N7: 0.4 | O7: 0.4 | P7: 0.4 | Q7: 0.4 | R7: 0.4 | S7: 0.4 | T7: 0.4 | U7: 0.4 | V7: =SUM(B3:U3) -> 2.4
A8: TW | B8: OMO | C8: ReservationSi1 | D8: Reservation26TA1 | E8: NA | F8: 執行長室 : 客戶價值中心 : 客戶成功管理部 : 客戶成功團隊 | G8: 人事費用 | H8: 楊麗涵 | J8: 0.4 | K8: 0.4 | L8: 0.4 | M8: 0.4 | N8: 0.4 | O8: 0.4 | P8: 0.4 | Q8: 0.4 | R8: 0.4 | S8: 0.4 | T8: 0.4 | U8: 0.4 | V8: =SUM(B4:U4) -> 4.8
A9: TW | B9: POS | C9: ENTSi1 | D9: ENT26TA1 | E9: NA | F9: 執行長室 : 客戶價值中心 : 客戶成功管理部 : 客戶成功團隊 | G9: 人事費用 | H9: 新人 3 | I9: MS 2025 已招募 、預計 2025 年 11 月到職 | J9: 0.2 | K9: 0.2 | L9: 0.2 | M9: 0.2 | N9: 0.2 | O9: 0.2 | P9: 0.2 | Q9: 0.2 | R9: 0.2 | S9: 0.2 | T9: 0.2 | U9: 0.2 | V9: =SUM(B5:U5) -> 4.8
A10: TW | B10: OMO | C10: OrderingSi1 | D10: Ordering26TA2 | E10: NA | F10: 執行長室 : 客戶價值中心 : 客戶成功管理部 : 客戶成功團隊 | G10: 人事費用 | H10: 新人 3 | I10: MS 2025 已招募 、預計 2025 年 11 月到職 | J10: 0.4 | K10: 0.4 | L10: 0.4 | M10: 0.4 | N10: 0.4 | O10: 0.4 | P10: 0.4 | Q10: 0.4 | R10: 0.4 | S10: 0.4 | T10: 0.4 | U10: 0.4 | V10: =SUM(B6:U6) -> 2.4
A11: TW | B11: OMO | C11: ReservationSi1 | D11: Reservation26TA1 | E11: NA | F11: 執行長室 : 客戶價值中心 : 客戶成功管理部 : 客戶成功團隊 | G11: 人事費用 | H11: 新人 3 | I11: MS 2025 已招募 、預計 2025 年 11 月到職 | J11: 0.4 | K11: 0.4 | L11: 0.4 | M11: 0.4 | N11: 0.4 | O11: 0.4 | P11: 0.4 | Q11: 0.4 | R11: 0.4 | S11: 0.4 | T11: 0.4 | U11: 0.4 | V11: =SUM(B7:U7) -> 4.8
A12: TW | B12: POS | C12: ENTSi1 | D12: ENT26TA1 | E12: NA | F12: 執行長室 : 客戶價值中心 : 客戶關係管理部 : 客戶經理團隊 | G12: 人事費用 | H12: 蔡佳玲 | I12: 總部 AM | J12: 0.6 | K12: 0.6 | L12: 0.6 | M12: 0.6 | N12: 0.6 | O12: 0.9 | P12: 0.9 | Q12: 0.9 | R12: 0.9 | S12: 0.9 | T12: 0.9 | U12: 0.9 | V12: =SUM(B8:U8) -> 4.8
A13: TW | B13: POS | C13: SMBSi1 | D13: SMB26TA1 | E13: NA | F13: 執行長室 : 客戶價值中心 : 客戶關係管理部 : 客戶經理團隊 | G13: 人事費用 | H13: 莊媁晨 | I13: OMO+POS AM | J13: 0.5 | K13: 0.5 | L13: 0.5 | M13: 0.5 | N13: 0.5 | O13: 0.5 | P13: 0.5 | Q13: 0.5 | R13: 0.5 | S13: 0.5 | T13: 0.5 | U13: 0.5 | V13: =SUM(B9:U9) -> 2.4
A14: TW | B14: OMO | C14: OrderingSi1 | D14: Ordering26TA3 | E14: NA | F14: 執行長室 : 客戶價值中心 : 客戶關係管理部 : 客戶經理團隊 | G14: 人事費用 | H14: 莊媁晨 | I14: OMO+POS AM | J14: 0.3 | K14: 0.3 | L14: 0.3 | M14: 0.3 | N14: 0.3 | O14: 0.3 | P14: 0.3 | Q14: 0.3 | R14: 0.3 | S14: 0.3 | T14: 0.3 | U14: 0.3 | V14: =SUM(B10:U10) -> 4.8
A15: TW | B15: OMO | C15: ReservationSi1 | D15: Reservation26TA2 | E15: NA | F15: 執行長室 : 客戶價值中心 : 客戶關係管理部 : 客戶經理團隊 | G15: 人事費用 | H15: 莊媁晨 | I15: OMO+POS AM | J15: 0.2 | K15: 0.2 | L15: 0.2 | M15: 0.2 | N15: 0.2 | O15: 0.2 | P15: 0.2 | Q15: 0.2 | R15: 0.2 | S15: 0.2 | T15: 0.2 | U15: 0.2 | V15: =SUM(B11:U11) -> 4.8
A16: TW | B16: POS | C16: ENTSi2 | D16: ENT26TA1 | E16: VC05P1 | F16: 執行長室 : 客戶價值中心 : 客戶價值中心 | G16: 人事費用 | H16: 李菩綾 | I16: 三級主管 | J16: 0.1 | K16: 0.1 | L16: 0.1 | M16: 0.1 | N16: 0.1 | O16: 0.2 | P16: 0.2 | Q16: 0.1 | R16: 0.1 | S16: 0.1 | T16: 0.1 | U16: 0.1 | V16: =SUM(B16:U16) -> 1.4
V17: =SUM(B13:U13) -> 6
V18: =SUM(B14:U14) -> 3.6
V19: =SUM(B15:U15) -> 2.4
V20: =SUM(B20:U20) -> 0
V21: =SUM(B21:U21) -> 0
V22: =SUM(B22:U22) -> 0
V23: =SUM(B23:U23) -> 0
V24: =SUM(B24:U24) -> 0
V25: =SUM(B25:U25) -> 0
V26: =SUM(B26:U26) -> 0
V27: =SUM(B27:U27) -> 0
V28: =SUM(B28:U28) -> 0
V29: =SUM(B29:U29) -> 0
V30: =SUM(B30:U30) -> 0
V31: =SUM(B31:U31) -> 0
... V1000: =SUM(B1000:U1000) -> 0

Sheet 1.2_各事業 TA 預算規劃_$
A1: 子公司 | B1: 事業單位 | C1: Si 編號 | D1: TA 編號 | E1: 價值鏈專案預算代號 | F1: 費用單位 | G1: 費用類型 | H1: 費用項目 | I1: 備註 | J1: 46023 | K1: 46054 | L1: 46082 | M1: 46113 | N1: 46143 | O1: 46174 | P1: 46204 | Q1: 46235 | R1: 46266 | S1: 46296 | T1: 46327 | U1: 46357 | V1: 2026 year
A2: TW | B2: OMO | C2: OrderingSi1 | D2: Ordering26TA2 | E2: VC05P4 | F2: 執行長室 : 客戶價值中心 : 客戶成功管理部 : 客戶成功團隊 | G2: 非人事費用 | H2: MS 公務機津貼_點餐 | I2: 每人每月 $1,000 | J2: =1000*2 -> 2000 | K2: =1000*2 -> 2000 | L2: =1000*2 -> 2000 | M2: =1000*2 -> 2000 | N2: =1000*2 -> 2000 | O2: =1000*2 -> 2000 | P2: =1000*2 -> 2000 | Q2: =1000*2 -> 2000 | ... U2: =1000*2 -> 2000 | V2: =SUM(#REF!) -> #REF!
A3: TW | B3: OMO | C3: OrderingSi1 | D3: Ordering26TA2 | E3: VC05P4 | F3: 執行長室 : 客戶價值中心 : 客戶成功管理部 : 客戶成功團隊 | G3: 非人事費用 | H3: MS 交通差旅費_點餐 | I3: 每人每月 $10,000 | J3: =10000*2 -> 20000 | K3: =10000*2 -> 20000 | L3: =10000*2 -> 20000 | M3: =10000*2 -> 20000 | N3: =10000*2 -> 20000 | O3: =10000*2 -> 20000 | P3: =10000*2 -> 20000 | Q3: =10000*2 -> 20000 | ... U3: =10000*2 -> 20000 | V3: =SUM(#REF!) -> #REF!
A4: TW | B4: OMO | C4: ReservationSi1 | D4: Reservation26TA1 | E4: VC05P4 | F4: 執行長室 : 客戶價值中心 : 客戶成功管理部 : 客戶成功團隊 | G4: 非人事費用 | H4: MS 公務機津貼_訂位 | I4: 每人每月 $1,000 | J4: =1000 -> 1000 | K4: =1000 -> 1000 | L4: =1000 -> 1000 | M4: =1000 -> 1000 | N4: =1000 -> 1000 | O4: =1000 -> 1000 | P4: =1000 -> 1000 | Q4: =1000 -> 1000 | ... U4: =1000 -> 1000 | V4: =SUM(B2:U2) -> 24000
A5: TW | B5: OMO | C5: ReservationSi1 | D5: Reservation26TA1 | E5: VC05P4 | F5: 執行長室 : 客戶價值中心 : 客戶成功管理部 : 客戶成功團隊 | G5: 非人事費用 | H5: MS 交通差旅費_訂位 | I5: 每人每月 $10,000 | J5: =10000 -> 10000 | K5: =10000 -> 10000 | L5: =10000 -> 10000 | M5: =10000 -> 10000 | N5: =10000 -> 10000 | O5: =10000 -> 10000 | P5: =10000 -> 10000 | Q5: =10000 -> 10000 | ... U5: =10000 -> 10000 | V5: =SUM(B3:U3) -> 240000
A6: TW | B6: OMO | C6: OrderingSi1 | D6: Ordering26TA2 | E6: VC05P4 | F6: 執行長室 : 客戶價值中心 : 客戶成功管理部 : 客戶成功團隊 | G6: 人事費用 | H6: OMO 業績達標獎金_點餐 | I6: $2000／間（暫時延續 2025 年預算單價） | J6: =2000*14 -> 28000 | K6: =2000*14 -> 28000 | L6: =2000*14 -> 28000 | M6: =2000*14 -> 28000 | N6: =2000*14 -> 28000 | O6: =2000*14 -> 28000 | P6: =2000*14 -> 28000 | Q6: =2000*14 -> 28000 | ... U6: =2000*14 -> 28000 | V6: =SUM(B6:U6) -> 336000
A7: TW | B7: OMO | C7: ReservationSi1 | D7: Reservation26TA1 | E7: VC05P4 | F7: 執行長室 : 客戶價值中心 : 客戶成功管理部 : 客戶成功團隊 | G7: 人事費用 | H7: OMO 業績達標獎金_訂位 | I7: $2000／間（暫時延續 2025 年預算單價） | J7: =2000*10 -> 20000 | K7: =2000*10 -> 20000 | L7: =2000*10 -> 20000 | M7: =2000*10 -> 20000 | N7: =2000*10 -> 20000 | O7: =2000*10 -> 20000 | P7: =2000*10 -> 20000 | Q7: =2000*10 -> 20000 | ... U7: =2000*10 -> 20000 | V7: =SUM(B8:U8) -> 720000
A8: TW | B8: POS | C8: ENTSi1 | D8: ENT26TA1 | E8: VC01P1 | F8: 執行長室 : 客戶價值中心 : 客戶成功管理部 : 客戶成功團隊 | G8: 人事費用 | H8: ENT 業績達標獎金 | I8: $30000／品牌 | J8: =30000*24/12 -> 60000 | K8: =30000*24/12 -> 60000 | L8: =30000*24/12 -> 60000 | M8: =30000*24/12 -> 60000 | N8: =30000*24/12 -> 60000 | O8: =30000*24/12 -> 60000 | P8: =30000*24/12 -> 60000 | Q8: =30000*24/12 -> 60000 | ... U8: =30000*24/12 -> 60000 | V8: =SUM(B9:U9) -> 72000
A9: TW | B9: POS | C9: ENTSi1 | D9: ENT26TA1 | E9: VC01P1 | F9: 執行長室 : 客戶價值中心 : 客戶成功管理部 : 客戶成功團隊 | G9: 人事費用 | H9: ENT 派發導入業務工單 | I9: $1500／單張 | J9: =1500*48/12 -> 6000 | K9: =1500*48/12 -> 6000 | L9: =1500*48/12 -> 6000 | M9: =1500*48/12 -> 6000 | N9: =1500*48/12 -> 6000 | O9: =1500*48/12 -> 6000 | P9: =1500*48/12 -> 6000 | Q9: =1500*48/12 -> 6000 | ... U9: =1500*48/12 -> 6000 | V9: =SUM(#REF!) -> #REF!
A10: TW | B10: POS | C10: SMBSi1 | D10: SMB26TA1 | E10: VC05P2 | F10: 執行長室 : 客戶價值中心 : 客戶關係管理部 : 客戶經理團隊 | G10: 非人事費用 | H10: 轉介回饋金 | I10: $ 2000/組 | J10: =2000*10 -> 20000 | K10: =2000*10 -> 20000 | L10: =2000*10 -> 20000 | M10: =2000*10 -> 20000 | N10: =2000*10 -> 20000 | O10: =2000*10 -> 20000 | P10: =2000*10 -> 20000 | Q10: =2000*10 -> 20000 | ... U10: =2000*10 -> 20000 | V10: =SUM(#REF!) -> #REF!
A11: TW | B11: OMO | C11: OrderingSi1 | D11: Ordering26TA3 | E11: VC06P1 | F11: 執行長室 : 客戶價值中心 : 客戶關係管理部 : 客戶經理團隊 | G11: 非人事費用 | H11: mailchimp | I11: USD 45 /月 | J11: 1376 | K11: 1376 | L11: 1376 | M11: 1376 | N11: 1376 | O11: 1376 | P11: 1376 | Q11: 1376 | R11: 1376 | S11: 1376 | T11: 1376 | U11: 1376 | V11: =SUM(B10:U10) -> 240000
A12: TW | B12: POS | C12: ENTSi1 | D12: ENT26TA1 | E12: VC05P2 | F12: 執行長室 : 客戶價值中心 : 客戶關係管理部 : 客戶經理團隊 | G12: 非人事費用 | H12: 總部 AM 公務機津貼 | I12: 每人每月 $1,000 | J12: 1000 | K12: 1000 | L12: 1000 | M12: 1000 | N12: 1000 | O12: 1000 | P12: 1000 | Q12: 1000 | R12: 1000 | S12: 1000 | T12: 1000 | U12: 1000 | V12: =SUM(B11:U11) -> 16512
A13: TW | B13: POS | C13: ENTSi1 | D13: ENT26TA1 | E13: VC05P2 | F13: 執行長室 : 客戶價值中心 : 客戶關係管理部 : 客戶經理團隊 | G13: 非人事費用 | H13: 總部 AM 交通差旅費 | I13: 每人每月 $10,000 | J13: 10000 | K13: 10000 | L13: 10000 | M13: 10000 | N13: 10000 | O13: 10000 | P13: 10000 | Q13: 10000 | R13: 10000 | S13: 10000 | T13: 10000 | U13: 10000 | V13: =SUM(B12:U12) -> 12000
A14: TW | B14: POS | C14: ENTSi1 | D14: ENT26TA1 | F14: 執行長室 : 客戶價值中心 : 客戶成功管理部 : 客戶成功團隊 | G14: 人事費用 | H14: 加總 | J14: 55080 | K14: 55080 | L14: 55080 | M14: 55080 | N14: 55080 | O14: 55080 | P14: 55080 | Q14: 55080 | R14: 55080 | S14: 55080 | T14: 55080 | U14: 55080 | V14: 660960
A15: TW | B15: OMO | C15: OrderingSi1 | D15: Ordering26TA2 | F15: 執行長室 : 客戶價值中心 : 客戶成功管理部 : 客戶成功團隊 | G15: 人事費用 | H15: 加總 | J15: 110160 | K15: 110160 | L15: 110160 | M15: 110160 | N15: 110160 | O15: 110160 | P15: 110160 | Q15: 110160 | R15: 110160 | S15: 110160 | T15: 110160 | U15: 110160 | V15: 1321920
A16: TW | B16: OMO | C16: ReservationSi1 | D16: Reservation26TA1 | F16: 執行長室 : 客戶價值中心 : 客戶成功管理部 : 客戶成功團隊 | G16: 人事費用 | H16: 加總 | J16: 110160 | K16: 110160 | L16: 110160 | M16: 110160 | N16: 110160 | O16: 110160 | P16: 110160 | Q16: 110160 | R16: 110160 | S16: 110160 | T16: 110160 | U16: 110160 | V16: 1321920
A17: TW | B17: POS | C17: ENTSi1 | D17: ENT26TA1 | V17: =SUM(B17:U17) -> 0
A18: TW | B18: POS | C18: ENTSi1 | D18: ENT26TA1 | V18: =SUM(B18:U18) -> 0
A19: TW | B19: POS | C19: ENTSi1 | D19: ENT26TA1 | V19: =SUM(B19:U19) -> 0
V20: =SUM(B20:U20) -> 0
V21: =SUM(B21:U21) -> 0
V22: =SUM(B22:U22) -> 0
V25: =SUM(B25:U25) -> 0
V26: =SUM(B26:U26) -> 0
V27: =SUM(B27:U27) -> 0
V28: =SUM(B28:U28) -> 0
V29: =SUM(B29:U29) -> 0
V30: =SUM(B30:U30) -> 0
V31: =SUM(B31:U31) -> 0
V32: =SUM(B32:U32) -> 0
V33: =SUM(B33:U33) -> 0
... V1000: =SUM(B1000:U1000) -> 0

Sheet 2.1_事業維運費用_人力時間配置
A1: 子公司 | B1: 事業單位 | C1: Si 編號 | D1: TA 編號 | E1: 價值鏈專案預算代號 | F1: 費用單位 | G1: 費用類型 | H1: 姓名 | I1: 備註 | J1: 46023 | K1: 46054 | L1: 46082 | M1: 46113 | N1: 46143 | O1: 46174 | P1: 46204 | Q1: 46235 | R1: 46266 | S1: 46296 | T1: 46327 | U1: 46357 | V1: 2026 year
A2: TW | B2: POS | C2: Maintenance | D2: Baseline | E2: NA | F2: 執行長室 : 客戶價值中心 : 客戶成功管理部 : 產品教育團隊 | G2: 人事費用 | H2: 周玟萱 | J2: 0.5 | K2: 0.5 | L2: 0.5 | M2: 0.5 | N2: 0.5 | O2: 0.5 | P2: 0.5 | Q2: 0.5 | R2: 0.5 | S2: 0.5 | T2: 0.5 | U2: 0.5 | V2: =SUM(B2:U2) -> 6
A3: TW | B3: OMO | C3: Maintenance | D3: Baseline | E3: NA | F3: 執行長室 : 客戶價值中心 : 客戶成功管理部 : 產品教育團隊 | G3: 人事費用 | H3: 周玟萱 | J3: 0.5 | K3: 0.5 | L3: 0.5 | M3: 0.5 | N3: 0.5 | O3: 0.5 | P3: 0.5 | Q3: 0.5 | R3: 0.5 | S3: 0.5 | T3: 0.5 | U3: 0.5 | V3: =SUM(B3:U3) -> 6
A4: TW | B4: POS | C4: Maintenance | D4: Baseline | E4: NA | F4: 執行長室 : 客戶價值中心 : 客戶成功管理部 : 產品教育團隊 | G4: 人事費用 | H4: 朱肇平 | J4: 0.5 | K4: 0.5 | L4: 0.5 | M4: 0.5 | N4: 0.5 | O4: 0.5 | P4: 0.5 | Q4: 0.5 | R4: 0.5 | S4: 0.5 | T4: 0.5 | U4: 0.5 | V4: =SUM(B4:U4) -> 6
A5: TW | B5: OMO | C5: Maintenance | D5: Baseline | E5: NA | F5: 執行長室 : 客戶價值中心 : 客戶成功管理部 : 產品教育團隊 | G5: 人事費用 | H5: 朱肇平 | J5: 0.5 | K5: 0.5 | L5: 0.5 | M5: 0.5 | N5: 0.5 | O5: 0.5 | P5: 0.5 | Q5: 0.5 | R5: 0.5 | S5: 0.5 | T5: 0.5 | U5: 0.5 | V5: =SUM(B5:U5) -> 6
A6: TW | B6: POS | C6: Maintenance | D6: Baseline | E6: NA | F6: 執行長室 : 客戶價值中心 : 客戶關係管理部 : TSE 團隊 | G6: 人事費用 | H6: 丁伊柔 | J6: 0.7 | K6: 0.7 | L6: 0.7 | M6: 0.7 | N6: 0.7 | O6: 0.7 | P6: 0.7 | Q6: 0.7 | R6: 0.7 | S6: 0.7 | T6: 0.7 | U6: 0.7 | V6: =SUM(B6:U6) -> 8.4
A7: TW | B7: OMO | C7: Maintenance | D7: Baseline | E7: NA | F7: 執行長室 : 客戶價值中心 : 客戶關係管理部 : TSE 團隊 | G7: 人事費用 | H7: 丁伊柔 | J7: 0.3 | K7: 0.3 | L7: 0.3 | M7: 0.3 | N7: 0.3 | O7: 0.3 | P7: 0.3 | Q7: 0.3 | R7: 0.3 | S7: 0.3 | T7: 0.3 | U7: 0.3 | V7: =SUM(B7:U7) -> 3.6
A8: TW | B8: POS | C8: Maintenance | D8: Baseline | E8: NA | F8: 執行長室 : 客戶價值中心 : 客戶關係管理部 : TSE 團隊 | G8: 人事費用 | H8: 林展甫 | J8: 0.7 | K8: 0.7 | L8: 0.7 | M8: 0.7 | N8: 0.7 | O8: 0.7 | P8: 0.7 | Q8: 0.7 | R8: 0.7 | S8: 0.7 | T8: 0.7 | U8: 0.7 | V8: =SUM(B8:U8) -> 8.4
A9: TW | B9: OMO | C9: Maintenance | D9: Baseline | E9: NA | F9: 執行長室 : 客戶價值中心 : 客戶關係管理部 : TSE 團隊 | G9: 人事費用 | H9: 林展甫 | J9: 0.3 | K9: 0.3 | L9: 0.3 | M9: 0.3 | N9: 0.3 | O9: 0.3 | P9: 0.3 | Q9: 0.3 | R9: 0.3 | S9: 0.3 | T9: 0.3 | U9: 0.3 | V9: =SUM(B9:U9) -> 3.6
A10: TW | B10: POS | C10: Maintenance | D10: Baseline | E10: NA | F10: 執行長室 : 客戶價值中心 : 客戶關係管理部 : 客服團隊 | G10: 人事費用 | H10: 吳芯儀 | J10: 0.8 | K10: 0.8 | L10: 0.8 | M10: 0.8 | N10: 0.8 | O10: 0.8 | P10: 0.8 | Q10: 0.8 | R10: 0.8 | S10: 0.8 | T10: 0.8 | U10: 0.8 | V10: =SUM(B10:U10) -> 9.6
A11: TW | B11: OMO | C11: Maintenance | D11: Baseline | E11: NA | F11: 執行長室 : 客戶價值中心 : 客戶關係管理部 : 客服團隊 | G11: 人事費用 | H11: 吳芯儀 | J11: 0.2 | K11: 0.2 | L11: 0.2 | M11: 0.2 | N11: 0.2 | O11: 0.2 | P11: 0.2 | Q11: 0.2 | R11: 0.2 | S11: 0.2 | T11: 0.2 | U11: 0.2 | V11: =SUM(B11:U11) -> 2.4
A12: TW | B12: POS | C12: Maintenance | D12: Baseline | E12: NA | F12: 執行長室 : 客戶價值中心 : 客戶關係管理部 : 客服團隊 | G12: 人事費用 | H12: 戴馨妤 | J12: 0.8 | K12: 0.8 | L12: 0.8 | M12: 0.8 | N12: 0.8 | O12: 0.8 | P12: 0.8 | Q12: 0.8 | R12: 0.8 | S12: 0.8 | T12: 0.8 | U12: 0.8 | V12: =SUM(B12:U12) -> 9.6
A13: TW | B13: OMO | C13: Maintenance | D13: Baseline | E13: NA | F13: 執行長室 : 客戶價值中心 : 客戶關係管理部 : 客服團隊 | G13: 人事費用 | H13: 戴馨妤 | J13: 0.2 | K13: 0.2 | L13: 0.2 | M13: 0.2 | N13: 0.2 | O13: 0.2 | P13: 0.2 | Q13: 0.2 | R13: 0.2 | S13: 0.2 | T13: 0.2 | U13: 0.2 | V13: =SUM(B13:U13) -> 2.4
... A25: TW | B25: OMO | C25: Maintenance | D25: Baseline | E25: NA | F25: 執行長室 : 客戶價值中心 : 客戶關係管理部 : 客服團隊 | G25: 人事費用 | H25: 周思吟 | J25: 0.2 | K25: 0.2 | L25: 0.2 | M25: 0.2 | N25: 0.2 | O25: 0.2 | P25: 0.2 | Q25: 0.2 | R25: 0.2 | S25: 0.2 | T25: 0.2 | U25: 0.2 | V25: =SUM(B25:U25) -> 2.4
A26: TW | B26: POS | C26: Maintenance | D26: Baseline | E26: NA | F26: 執行長室 : 客戶價值中心 : 客戶關係管理部 : 客服團隊 | G26: 人事費用 | H26: 劉晏廷 | I26: TW-CS 工讀生 | J26: 1 | K26: 1 | L26: 1 | M26: 1 | N26: 1 | O26: 1 | P26: 1 | Q26: 1 | R26: 1 | S26: 1 | T26: 1 | U26: 1 | V26: =SUM(B26:U26) -> 12
A27: TW | B27: POS | C27: Maintenance | D27: Baseline | E27: NA | F27: 執行長室 : 客戶價值中心 : 客戶關係管理部 : 客服團隊 | G27: 人事費用 | H27: 盧欣妤 | I27: TW-CS 工讀生 | J27: 1 | K27: 1 | L27: 1 | M27: 1 | N27: 1 | O27: 1 | P27: 1 | Q27: 1 | R27: 1 | S27: 1 | T27: 1 | U27: 1 | V27: =SUM(B27:U27) -> 12
A28: SG | B28: POS | C28: Maintenance | D28: Baseline | E28: NA | F28: 執行長室 : 客戶價值中心 : 客戶關係管理部 : 客服團隊 | G28: 人事費用 | H28: 陳怡婷 | I28: SG-CS 工讀生 | J28: 1 | K28: 1 | L28: 1 | M28: 1 | N28: 1 | O28: 1 | P28: 1 | Q28: 1 | R28: 1 | S28: 1 | T28: 1 | U28: 1 | V28: =SUM(B28:U28) -> 12
A29: TW | B29: POS | C29: Maintenance | D29: Baseline | E29: NA | F29: 執行長室 : 客戶價值中心 : 客戶關係管理部 : 客戶經理團隊 | G29: 人事費用 | H29: 陳嘉汶 | I29: 總部 AM ( 育嬰留停） | J29: NA | K29: NA | L29: NA | M29: NA | N29: NA | O29: 1 | P29: 1 | Q29: 1 | R29: 1 | S29: 1 | T29: 1 | U29: 1 | V29: =SUM(B29:U29) -> 7
A30: TW | B30: POS | C30: Maintenance | D30: Baseline | E30: NA | F30: 執行長室 : 客戶價值中心 : 客戶關係管理部 : 客戶經理團隊 | G30: 人事費用 | H30: 蔡佳玲 | I30: 總部 AM | J30: 0.4 | K30: 0.4 | L30: 0.4 | M30: 0.4 | N30: 0.4 | O30: 0.2 | P30: 0.2 | Q30: 0.2 | R30: 0.2 | S30: 0.2 | T30: 0.2 | U30: 0.2 | V30: =SUM(B30:U30) -> 3.4
A31: TW | B31: POS | C31: Maintenance | D31: Baseline | E31: NA | F31: 執行長室 : 客戶價值中心 : 客戶關係管理部 : 客戶經理團隊 | G31: 人事費用 | H31: 許裴宸 | I31: TW-POS-AM | J31: 1 | K31: 1 | L31: 1 | M31: 1 | N31: 1 | O31: 1 | P31: 1 | Q31: 1 | R31: 1 | S31: 1 | T31: 1 | U31: 1 | V31: =SUM(B31:U31) -> 12
A32: TW | B32: OMO | C32: Maintenance | D32: Baseline | E32: NA | F32: 執行長室 : 客戶價值中心 : 客戶關係管理部 : 客戶經理團隊 | G32: 人事費用 | H32: 黃如蘭 | I32: TW-OMO-AM | J32: 1 | K32: 1 | L32: 1 | M32: 1 | N32: 1 | O32: 1 | P32: 1 | Q32: 1 | R32: 1 | S32: 1 | T32: 1 | U32: 1 | V32: =SUM(B32:U32) -> 12
A33: TW | B33: POS | C33: Maintenance | D33: Baseline | E33: NA | F33: 執行長室 : 客戶價值中心 : 客戶關係管理部 : 客服團隊 | G33: 人事費用 | H33: 新人 1 | I33: ( A ) NEW-CS T1 | J33: 0.8 | K33: 0.8 | L33: 0.8 | M33: 0.8 | N33: 0.8 | O33: 0.8 | P33: 0.8 | Q33: 0.8 | R33: 0.8 | S33: 0.8 | T33: 0.8 | U33: 0.8 | V33: =SUM(B33:U33) -> 9.6
A34: TW | B34: OMO | C34: Maintenance | D34: Baseline | E34: NA | F34: 執行長室 : 客戶價值中心 : 客戶關係管理部 : 客服團隊 | G34: 人事費用 | H34: 新人 1 | I34: ( A ) NEW-CS T1 | J34: 0.2 | K34: 0.2 | L34: 0.2 | M34: 0.2 | N34: 0.2 | O34: 0.2 | P34: 0.2 | Q34: 0.2 | R34: 0.2 | S34: 0.2 | T34: 0.2 | U34: 0.2 | V34: =SUM(B34:U34) -> 2.4
A35: TW | B35: POS | C35: Maintenance | D35: Baseline | E35: NA | F35: 執行長室 : 客戶價值中心 : 客戶關係管理部 : 客服團隊 | G35: 人事費用 | H35: 新人 2 | I35: ( B ) NEW-CS T1 | J35: NA | K35: NA | L35: NA | M35: 0.8 | N35: 0.8 | O35: 0.8 | P35: 0.8 | Q35: 0.8 | R35: 0.8 | S35: 0.8 | T35: 0.8 | U35: 0.8 | V35: =SUM(B35:U35) -> 7.2
A36: TW | B36: OMO | C36: Maintenance | D36: Baseline | E36: NA | F36: 執行長室 : 客戶價值中心 : 客戶關係管理部 : 客服團隊 | G36: 人事費用 | H36: 新人 2 | I36: ( B ) NEW-CS T1 | J36: NA | K36: NA | L36: NA | M36: 0.2 | N36: 0.2 | O36: 0.2 | P36: 0.2 | Q36: 0.2 | R36: 0.2 | S36: 0.2 | T36: 0.2 | U36: 0.2 | V36: =SUM(B36:U36) -> 1.8
V37: =SUM(B37:U37) -> 0
V38: =SUM(B38:U38) -> 0
V39: =SUM(B39:U39) -> 0
V41: =SUM(B41:U41) -> 0
V42: =SUM(B42:U42) -> 0
V43: =SUM(B43:U43) -> 0
V44: =SUM(B44:U44) -> 0
V45: =SUM(B45:U45) -> 0
V46: =SUM(B46:U46) -> 0
V47: =SUM(B47:U47) -> 0
V48: =SUM(B48:U48) -> 0
V49: =SUM(B49:U49) -> 0
... V1000: =SUM(B1000:U1000) -> 0

Sheet 2.2_事業維運費用_$
A1: 子公司 | B1: 事業單位 | C1: Si 編號 | D1: TA 編號 | E1: 價值鏈專案預算代號 | F1: 費用單位 | G1: 費用類型 | H1: 費用項目 | I1: 備註 | J1: 46023 | K1: 46054 | L1: 46082 | M1: 46113 | N1: 46143 | O1: 46174 | P1: 46204 | Q1: 46235 | R1: 46266 | S1: 46296 | T1: 46327 | U1: 46357 | V1: 2026 year
A2: TW | B2: Corporation | C2: Maintenance | D2: Baseline | E2: NA | F2: 執行長室 : 客戶價值中心 : 客戶關係管理部 : 客服團隊 | G2: 非人事費用 | H2: @ichefcs 客服 LINE OA 帳號 | I2: 基礎費用＋訊息加購費 | J2: 14429 | K2: 14429 | L2: 14429 | M2: 5429 | N2: 5429 | O2: 5429 | P2: 5429 | Q2: 9429 | R2: 5429 | S2: 9429 | T2: 5429 | U2: 5429 | V2: =SUM(B2:U2) -> 100148
A3: TW | B3: Corporation | C3: Maintenance | D3: Baseline | E3: NA | F3: 執行長室 : 客戶價值中心 : 客戶關係管理部 : 客戶經理團隊 | G3: 非人事費用 | H3: @ichefob 續約 LINE OA 帳號 | I3: 年繳，2026/03/1 請款 ＋ 用量方案 | J3: 168 | K3: 168 | L3: 168 | M3: 168 | N3: 168 | O3: 168 | P3: 168 | Q3: 168 | R3: 168 | S3: 168 | T3: 168 | U3: 168 | V3: =SUM(B3:U3) -> 2016
A4: TW | B4: Corporation | C4: Maintenance | D4: Baseline | E4: NA | F4: 執行長室 : 客戶價值中心 : 客戶成功管理部 : 客戶成功團隊 | G4: 非人事費用 | H4: @ichefms 客戶成功 LINE OA 帳號 | I4: 年繳，2026/10/1 請款 | J4: =756/12 -> 63 | K4: =756/12 -> 63 | L4: =756/12 -> 63 | M4: =756/12 -> 63 | N4: =756/12 -> 63 | O4: =756/12 -> 63 | P4: =756/12 -> 63 | Q4: =756/12 -> 63 | ... U4: =756/12 -> 63 | V4: =SUM(B4:U4) -> 756
A5: TW | B5: Corporation | C5: Maintenance | D5: Baseline | E5: NA | F5: 執行長室 : 客戶價值中心 : 客戶關係管理部 : 客戶經理團隊 | G5: 非人事費用 | H5: @ichefhq 總部客服 LINE OA 帳號 | I5: 年繳，2026/05/1 請款 | J5: =756/12 -> 63 | K5: =756/12 -> 63 | L5: =756/12 -> 63 | M5: =756/12 -> 63 | N5: =756/12 -> 63 | O5: =756/12 -> 63 | P5: =756/12 -> 63 | Q5: =756/12 -> 63 | ... U5: =756/12 -> 63 | V5: =SUM(B5:U5) -> 756
A6: TW | B6: Corporation | C6: Maintenance | D6: Baseline | E6: NA | F6: 執行長室 : 客戶價值中心 : 客戶關係管理部 : 客服團隊 | G6: 非人事費用 | H6: 客服手機 0965186039 (Line OA 號碼） | I6: 固定月費 | J6: 199 | K6: 199 | L6: 199 | M6: 199 | N6: 199 | O6: 199 | P6: 199 | Q6: 199 | R6: 199 | S6: 199 | T6: 199 | U6: 199 | V6: =SUM(B6:U6) -> 2388
A7: TW | B7: Corporation | C7: Maintenance | D7: Baseline | E7: NA | F7: 執行長室 : 客戶價值中心 : 客戶關係管理部 : 客服團隊 | G7: 非人事費用 | H7: 客服 0800-889-055 電話費用 | I7: 已依據大小月及產品 roadmap 預估推播次數。 | J7: 55000 | K7: 40000 | L7: 55000 | M7: 42000 | N7: 42000 | O7: 42000 | P7: 45000 | Q7: 45000 | R7: 45000 | S7: 50000 | T7: 42000 | U7: 42000 | V7: =SUM(B7:U7) -> 545000
A8: TW | B8: Corporation | C8: Maintenance | D8: Baseline | E8: NA | F8: 執行長室 : 客戶價值中心 : 客戶關係管理部 : 客服團隊 | G8: 非人事費用 | H8: 網訊電信費（IVR轉接、電話費、簡訊費） | I8: 網訊電信費（IVR轉接、電話費、簡訊費），已包含 5%稅率 | J8: 5600 | K8: 5600 | L8: 5600 | M8: 5600 | N8: 5600 | O8: 5600 | P8: 5600 | Q8: 5600 | R8: 5600 | S8: 5600 | T8: 5600 | U8: 5600 | V8: =SUM(B8:U8) -> 67200
A9: TW | B9: Corporation | C9: Maintenance | D9: Baseline | E9: NA | F9: 執行長室 : 客戶價值中心 : 客戶關係管理部 : 客服團隊 | G9: 非人事費用 | H9: 網訊 G5 帳號費 | I9: 線上接聽電話（網訊/台中/台北 共用） | J9: 8400 | K9: 8400 | L9: 8400 | M9: 15330 | N9: 15330 | O9: 15330 | P9: 15330 | Q9: 15330 | R9: 15330 | S9: 15330 | T9: 15330 | U9: 15330 | V9: =SUM(B9:U9) -> 163170
A10: TW | B10: Corporation | C10: Maintenance | D10: Baseline | E10: NA | F10: 執行長室 : 客戶價值中心 : 客戶關係管理部 : 客服團隊 | G10: 非人事費用 | H10: 黑貓運費 | I10: 因 Lalamove 費用在同期成長達 16%，自 2025 年 7 月起內部調整配送機制：非急件一律改由黑貓配送，壓低整體運輸成本。整體評估後，2026 年預估黑貓運費將隨件數與用戶數有成長，故增加此條預算金額 | J10: 33000 | K10: 33000 | L10: 33000 | M10: 38000 | N10: 33000 | O10: 33000 | P10: 33000 | Q10: 33000 | R10: 40000 | S10: 40000 | T10: 33000 | U10: 40000 | V10: =SUM(B10:U10) -> 422000
A11: TW | B11: Corporation | C11: Maintenance | D11: Baseline | E11: NA | F11: 執行長室 : 客戶價值中心 : 客戶關係管理部 : 客服團隊 | G11: 非人事費用 | H11: Lalamove運費 | I11: 2026 年建議維持兩個月請購一次，但單次請購金額由 NT$20,000 下調為 NT$14,000。 | J11: 7000 | K11: 7000 | L11: 7000 | M11: 7000 | N11: 7000 | O11: 7000 | P11: 7000 | Q11: 7000 | R11: 7000 | S11: 7000 | T11: 7000 | U11: 7000 | V11: =SUM(B11:U11) -> 84000
A12: TW | B12: Corporation | C12: Maintenance | D12: Baseline | E12: NA | F12: 執行長室 : 客戶價值中心 : 客戶關係管理部 : 客服團隊 | G12: 非人事費用 | H12: 客服購置備用機 | I12: 客服購置備用機 / 季 | J12: 20000 | K12: 20000 | L12: 20000 | M12: 20000 | N12: 10000 | O12: 10000 | P12: 20000 | Q12: 20000 | R12: 20000 | S12: 20000 | T12: 10000 | U12: 20000 | V12: =SUM(B12:U12) -> 210000
A13: TW | B13: Corporation | C13: Maintenance | D13: Baseline | E13: NA | F13: 執行長室 : 客戶價值中心 : 客戶關係管理部 : 客服團隊 | G13: 非人事費用 | H13: 客服備用機維修 | I13: 備用機維修金額難以依月份預估，約每年 $120,000 | J13: 10000 | K13: 10000 | L13: 10000 | M13: 10000 | N13: 10000 | O13: 10000 | P13: 10000 | Q13: 10000 | R13: 10000 | S13: 10000 | T13: 10000 | U13: 10000 | V13: =SUM(B13:U13) -> 120000
A14: TW | B14: Corporation | C14: Maintenance | D14: Baseline | E14: NA | F14: 執行長室 : 客戶價值中心 : 客戶關係管理部 : 客服團隊 | G14: 非人事費用 | H14: Zaiper | I14: USD 2202（匯率約 33）。客服費用占比約 73% | J14: 6056 | K14: 6056 | L14: 6056 | M14: 6056 | N14: 6056 | O14: 6056 | P14: 6056 | Q14: 6056 | R14: 6056 | S14: 6056 | T14: 6056 | U14: 6056 | V14: =SUM(B14:U14) -> 72672
A15: TW | B15: Corporation | C15: Maintenance | D15: Baseline | E15: NA | F15: 執行長室 : 客戶價值中心 : 客戶關係管理部 : 客戶經理團隊 | G15: 非人事費用 | H15: Zapier 費用 | I15: 續約組 | J15: 1000 | K15: 1000 | L15: 1000 | M15: 1000 | N15: 1000 | O15: 1000 | P15: 1000 | Q15: 1000 | R15: 1000 | S15: 1000 | T15: 1000 | U15: 1000 | V15: =SUM(B15:U15) -> 12000
A16: TW | B16: Corporation | C16: Maintenance | D16: Baseline | E16: NA | F16: 執行長室 : 客戶價值中心 : 客戶關係管理部 : 客服團隊 | G16: 非人事費用 | H16: Typeform | I16: 每年 2/15 續約，費用為 USD 350。＄11559/年 | J16: 964 | K16: 964 | L16: 964 | M16: 964 | N16: 964 | O16: 964 | P16: 964 | Q16: 964 | R16: 964 | S16: 964 | T16: 964 | U16: 964 | V16: =SUM(B16:U16) -> 11568
A17: TW | B17: Corporation | C17: Maintenance | D17: Baseline | E17: NA | F17: 執行長室 : 客戶價值中心 : 客戶關係管理部 : 客服團隊 | G17: 非人事費用 | H17: SURVEYSPARROW | I17: NPS 調查軟體 $1188 USD | J17: 3366 | K17: 3366 | L17: 3366 | M17: 3366 | N17: 3366 | O17: 3366 | P17: 3366 | Q17: 3366 | R17: 3366 | S17: 3366 | T17: 3366 | U17: 3366 | V17: =SUM(B17:U17) -> 40392
A18: TW | B18: Corporation | C18: Maintenance | D18: Baseline | E18: NA | F18: 執行長室 : 客戶價值中心 : 客戶關係管理部 : 客戶經理團隊 | G18: 非人事費用 | H18: 點點簽帳號 | I18: 續約跟客戶成功共用，每一個帳號每月是$450元 | J18: 450 | K18: 450 | L18: 450 | M18: 450 | N18: 450 | O18: 450 | P18: 450 | Q18: 450 | R18: 450 | S18: 450 | T18: 450 | U18: 450 | V18: =SUM(B18:U18) -> 5400
A19: TW | B19: Corporation | C19: Maintenance | D19: Baseline | E19: NA | F19: 執行長室 : 客戶價值中心 : 客戶成功管理部 : 產品教育團隊 | G19: 非人事費用 | H19: WordPress 專業版 | I19: 年繳｜2026/03/21 請款｜NTD$5148 | J19: =5148/12 -> 429 | K19: =5148/12 -> 429 | L19: =5148/12 -> 429 | M19: =5148/12 -> 429 | N19: =5148/12 -> 429 | O19: =5148/12 -> 429 | P19: =5148/12 -> 429 | Q19: =5148/12 -> 429 | ... U19: =5148/12 -> 429 | V19: =SUM(B19:U19) -> 5148
A20: TW | B20: Corporation | C20: Maintenance | D20: Baseline | E20: NA | F20: 執行長室 : 客戶價值中心 : 客戶成功管理部 : 產品教育團隊 | G20: 非人事費用 | H20: Elementor | I20: 年繳｜2026/04/20 請款｜USD$49 | J20: =1504/12 -> 125.33333 | K20: =1504/12 -> 125.33333 | L20: =1504/12 -> 125.33333 | M20: =1504/12 -> 125.33333 | N20: =1504/12 -> 125.33333 | O20: =1504/12 -> 125.33333 | P20: =1504/12 -> 125.33333 | Q20: =1504/12 -> 125.33333 | ... U20: =1504/12 -> 125.33333 | V20: =SUM(B20:U20) -> 1504
A21: TW | B21: Corporation | C21: Maintenance | D21: Baseline | E21: NA | F21: 執行長室 : 客戶價值中心 : 客戶成功管理部 : 產品教育團隊 | G21: 非人事費用 | H21: WPML | I21: 年繳｜2026/04/20 請款｜USD$74 | J21: =2272/12 -> 189.33333 | K21: =2272/12 -> 189.33333 | L21: =2272/12 -> 189.33333 | M21: =2272/12 -> 189.33333 | N21: =2272/12 -> 189.33333 | O21: =2272/12 -> 189.33333 | P21: =2272/12 -> 189.33333 | Q21: =2272/12 -> 189.33333 | ... U21: =2272/12 -> 189.33333 | V21: =SUM(B21:U21) -> 2272
A22: TW | B22: Corporation | C22: Maintenance | D22: Baseline | E22: NA | F22: 執行長室 : 客戶價值中心 : 客戶成功管理部 : 產品教育團隊 | G22: 非人事費用 | H22: Frontitude | I22: 年繳｜2026/04/27 請款｜USD$828 | J22: =25417/12 -> 2118.0833 | K22: =25417/12 -> 2118.0833 | L22: =25417/12 -> 2118.0833 | M22: =25417/12 -> 2118.0833 | N22: =25417/12 -> 2118.0833 | O22: =25417/12 -> 2118.0833 | P22: =25417/12 -> 2118.0833 | Q22: =25417/12 -> 2118.0833 | ... U22: =25417/12 -> 2118.0833 | V22: =SUM(B22:U22) -> 25417
A23: TW | B23: Corporation | C23: Maintenance | D23: Baseline | E23: NA | F23: 執行長室 : 客戶價值中心 : 客戶成功管理部 : 產品教育團隊 | G23: 非人事費用 | H23: Figma | I23: USD$16／月 x 3 席 | J23: =491*3 -> 1473 | K23: =491*3 -> 1473 | L23: =491*3 -> 1473 | M23: =491*3 -> 1473 | N23: =491*3 -> 1473 | O23: =491*3 -> 1473 | P23: =491*3 -> 1473 | Q23: =491*3 -> 1473 | ... U23: =491*3 -> 1473 | V23: =SUM(B23:U23) -> 17676
A24: TW | B24: Corporation | C24: Maintenance | D24: Baseline | E24: NA | F24: 執行長室 : 客戶價值中心 : 客戶關係管理部 : 客服團隊 | G24: 非人事費用 | H24: YET ANOTHER MAIL | I24: 年繳｜2026/05 請款｜NTD$ 1205 | J24: 101 | K24: 101 | L24: 101 | M24: 101 | N24: 101 | O24: 101 | P24: 101 | Q24: 101 | R24: 101 | S24: 101 | T24: 101 | U24: 101 | V24: =SUM(B24:U24) -> 1212
A25: TW | B25: Corporation | C25: Maintenance | D25: Baseline | E25: NA | F25: 執行長室 : 客戶價值中心 : 客戶關係管理部 : 客戶經理團隊 | G25: 非人事費用 | H25: FORM-PUBLISHER.COM | I25: 年繳，USD 79，2026/1 請款，用於權責移轉跳轉表單寄給店家 | J25: 204 | K25: 204 | L25: 204 | M25: 204 | N25: 204 | O25: 204 | P25: 204 | Q25: 204 | R25: 204 | S25: 204 | T25: 204 | U25: 204 | V25: =SUM(B25:U25) -> 2448
A26: TW | B26: Corporation | C26: Maintenance | D26: Baseline | E26: NA | F26: 執行長室 : 客戶價值中心 : 客戶關係管理部 : 客戶經理團隊 | G26: 非人事費用 | H26: Flydove 費用 | I26: 用於續約通知 | J26: 2500 | K26: 2500 | L26: 2500 | M26: 2500 | N26: 2500 | O26: 2500 | P26: 2500 | Q26: 2500 | R26: 2500 | S26: 2500 | T26: 2500 | U26: 2500 | V26: =SUM(B26:U26) -> 30000
A27: TW | B27: Corporation | C27: Maintenance | D27: Baseline | E27: NA | F27: 執行長室 : 客戶價值中心 : 客戶關係管理部 : TSE 團隊 | G27: 非人事費用 | H27: GitHub | I27: 研發中心協助請款 | J27: 360 | K27: 360 | L27: 360 | M27: 360 | N27: 360 | O27: 360 | P27: 360 | Q27: 360 | R27: 360 | S27: 360 | T27: 360 | U27: 360 | V27: =SUM(B27:U27) -> 4320
A28: TW | B28: Corporation | C28: Maintenance | D28: Baseline | E28: NA | F28: 執行長室 : 客戶價值中心 : 客戶關係管理部 : 客服團隊 | G28: 非人事費用 | H28: iCHEF 之家費用 /月（台北＋高雄） | I28: 台北 ＆ 高雄各一家 | J28: 4000 | K28: 4000 | L28: 4000 | M28: 4000 | N28: 4000 | O28: 4000 | P28: 4000 | Q28: 4000 | R28: 4000 | S28: 4000 | T28: 4000 | U28: 4000 | V28: =SUM(B28:U28) -> 48000
A29: TW | B29: Corporation | C29: Maintenance | D29: Baseline | E29: NA | F29: 執行長室 : 客戶價值中心 : 客戶關係管理部 : 客服團隊 | G29: 非人事費用 | H29: 業務工單 | I29: 每張工單為 750 元，預估每月 8張。 | J29: 6000 | K29: 6000 | L29: 6000 | M29: 6000 | N29: 6000 | O29: 6000 | P29: 6000 | Q29: 6000 | R29: 6000 | S29: 6000 | T29: 6000 | U29: 6000 | V29: =SUM(B29:U29) -> 72000
A30: TW | B30: Corporation | C30: Maintenance | D30: Baseline | E30: NA | F30: 執行長室 : 客戶價值中心 : 客戶關係管理部 : 客服團隊 | G30: 非人事費用 | H30: 外站差旅費｜每 2個月一次 T2 外地訓練 | I30: 團隊夥伴預計每兩個月出差一次（單日） | J30: 0 | K30: 0 | L30: 2500 | M30: 0 | N30: 2500 | O30: 0 | P30: 2500 | Q30: 0 | R30: 2500 | S30: 0 | T30: 2500 | U30: 0 | V30: =SUM(B30:U30) -> 12500
A31: TW | B31: Corporation | C31: Maintenance | D31: Baseline | E31: NA | F31: 執行長室 : 客戶價值中心 : 客戶關係管理部 : 客服團隊 | G31: 非人事費用 | H31: 外站差旅費｜CS 台中夥伴至台北開會 | I31: 來回車票共 NT$1,400／人，7 人估列 | J31: 0 | K31: 0 | L31: 0 | M31: 0 | N31: 0 | O31: 0 | P31: 0 | Q31: 0 | R31: 0 | S31: 0 | T31: 0 | U31: 10000 | V31: =SUM(B31:U31) -> 10000
A32: TW | B32: Corporation | C32: Maintenance | D32: Baseline | E32: NA | F32: 執行長室 : 客戶價值中心 : 客戶關係管理部 : 客服團隊 | G32: 非人事費用 | H32: 出單機包材 | I32: 小紙箱與包裝泡泡紙，季 /＄5,500 | J32: 5500 | K32: 0 | L32: 0 | M32: 5500 | N32: 0 | O32: 0 | P32: 5500 | Q32: 0 | R32: 0 | S32: 5500 | T32: 0 | U32: 0 | V32: =SUM(B32:U32) -> 22000
A33: TW | B33: Corporation | C33: Maintenance | D33: Baseline | E33: NA | F33: 執行長室 : 客戶價值中心 : 客戶關係管理部 : 客服團隊 | G33: 非人事費用 | H33: 備機封箱貼紙 | I33: 半年 / 3,300 | J33: 0 | K33: 0 | L33: 0 | M33: 3300 | N33: 0 | O33: 0 | P33: 0 | Q33: 0 | R33: 0 | S33: 3300 | T33: 0 | U33: 0 | V33: =SUM(B33:U33) -> 6600
A34: TW | B34: Corporation | C34: Maintenance | D34: Baseline | E34: NA | F34: 執行長室 : 客戶價值中心 : 客戶關係管理部 : 客服團隊 | G34: 非人事費用 | H34: 緊急紙卷&測試紙捲 | I34: 季 /＄4,000 | J34: 0 | K34: 0 | L34: 4000 | M34: 0 | N34: 0 | O34: 4000 | P34: 0 | Q34: 0 | R34: 4000 | S34: 0 | T34: 0 | U34: 4000 | V34: =SUM(B34:U34) -> 16000
A35: TW | B35: Corporation | C35: Maintenance | D35: Baseline | E35: NA | F35: 執行長室 : 客戶價值中心 : 客戶關係管理部 : 客服團隊 | G35: 非人事費用 | H35: TW客訴賠償預算 | I35: 季/9,000 | J35: 0 | K35: 9000 | L35: 0 | M35: 0 | N35: 9000 | O35: 0 | P35: 0 | Q35: 9000 | R35: 0 | S35: 0 | T35: 9000 | U35: 0 | V35: =SUM(B35:U35) -> 36000
... A41: SG | B41: Corporation | C41: Maintenance | D41: Baseline | E41: NA | F41: 執行長室 : 客戶價值中心 : 客戶關係管理部 : 客服團隊 | G41: 非人事費用 | H41: SG - Alice 薪資轉帳手續費 | I41: 月付，每月約 SGD $50 | J41: 1200 | K41: 1200 | L41: 1200 | M41: 1200 | N41: 1200 | O41: 1200 | P41: 1200 | Q41: 0 | R41: 0 | S41: 0 | T41: 0 | U41: 0 | V41: =SUM(B41:U41) -> 8400
V43: =SUM(B43:U43) -> 0
V44: =SUM(B44:U44) -> 0
V45: =SUM(B45:U45) -> 0
V46: =SUM(B46:U46) -> 0
V47: =SUM(B47:U47) -> 0
V48: =SUM(B48:U48) -> 0
V49: =SUM(B49:U49) -> 0
V50: =SUM(B50:U50) -> 0
V51: =SUM(B51:U51) -> 0
V52: =SUM(B52:U52) -> 0
V53: =SUM(B53:U53) -> 0
V54: =SUM(B54:U54) -> 0
... V999: =SUM(B999:U999) -> 0

Sheet 3.1_集團共用資源_人力時間配置
A1: 子公司 | B1: 事業單位 | C1: Si 編號 | D1: TA 編號 | E1: 價值鏈專案預算代號 | F1: 費用單位 | G1: 費用類型 | H1: 姓名 | I1: 備註 | J1: 46023 | K1: 46054 | L1: 46082 | M1: 46113 | N1: 46143 | O1: 46174 | P1: 46204 | Q1: 46235 | R1: 46266 | S1: 46296 | T1: 46327 | U1: 46357 | V1: 2026 year
A3: TW | B3: Corporation | C3: Corporation | D3: Corporation | E3: NA | F3: 執行長室 : 客戶價值中心 : 客戶價值中心 | G3: 人事費用 | H3: 梁方瑜 | I3: 一級主管 | J3: 1 | K3: 1 | L3: 1 | M3: 1 | N3: 1 | O3: 1 | P3: 1 | Q3: 1 | R3: 1 | S3: 1 | T3: 1 | U3: 1 | V3: =SUM(B3:U3) -> 12
A4: TW | B4: POS | C4: Corporation | D4: Corporation | E4: NA | F4: 執行長室 : 客戶價值中心 : 客戶價值中心 | G4: 人事費用 | H4: 謝孟娟 | I4: 二級主管 | J4: 0.2 | K4: 0.2 | L4: 0.2 | M4: 0.2 | N4: 0.2 | O4: 0.2 | P4: 0.2 | Q4: 0.2 | R4: 0.2 | S4: 0.2 | T4: 0.2 | U4: 0.2 | V4: =SUM(B4:U4) -> 2.4
A5: TW | B5: OMO | C5: Corporation | D5: Corporation | E5: NA | F5: 執行長室 : 客戶價值中心 : 客戶價值中心 | G5: 人事費用 | H5: 謝孟娟 | I5: 二級主管 | J5: 0.8 | K5: 0.8 | L5: 0.8 | M5: 0.8 | N5: 0.8 | O5: 0.8 | P5: 0.8 | Q5: 0.8 | R5: 0.8 | S5: 0.8 | T5: 0.8 | U5: 0.8 | V5: =SUM(B5:U5) -> 9.6
A6: TW | B6: POS | C6: Corporation | D6: Corporation | E6: NA | F6: 執行長室 : 客戶價值中心 : 客戶價值中心 | G6: 人事費用 | H6: 陳繼訓 | I6: 二級主管 | J6: 0.6 | K6: 0.6 | L6: 0.6 | M6: 0.6 | N6: 0.6 | O6: 0.6 | P6: 0.6 | Q6: 0.6 | R6: 0.6 | S6: 0.6 | T6: 0.6 | U6: 0.6 | V6: =SUM(B6:U6) -> 7.2
A7: TW | B7: OMO | C7: Corporation | D7: Corporation | E7: NA | F7: 執行長室 : 客戶價值中心 : 客戶價值中心 | G7: 人事費用 | H7: 陳繼訓 | I7: 二級主管 | J7: 0.4 | K7: 0.4 | L7: 0.4 | M7: 0.4 | N7: 0.4 | O7: 0.4 | P7: 0.4 | Q7: 0.4 | R7: 0.4 | S7: 0.4 | T7: 0.4 | U7: 0.4 | V7: =SUM(B7:U7) -> 4.8
A8: TW | B8: POS | C8: Corporation | D8: Corporation | E8: NA | F8: 執行長室 : 客戶價值中心 : 客戶價值中心 | G8: 人事費用 | H8: 林怡儒 | I8: 三級主管 | J8: 0.6 | K8: 0.6 | L8: 0.6 | M8: 0.6 | N8: 0.6 | O8: 0.6 | P8: 0.6 | Q8: 0.6 | R8: 0.6 | S8: 0.6 | T8: 0.6 | U8: 0.6 | V8: =SUM(B8:U8) -> 7.2
A9: TW | B9: OMO | C9: Corporation | D9: Corporation | E9: NA | F9: 執行長室 : 客戶價值中心 : 客戶價值中心 | G9: 人事費用 | H9: 林怡儒 | I9: 三級主管 | J9: 0.5 | K9: 0.5 | L9: 0.5 | M9: 0.5 | N9: 0.4 | O9: 0.4 | P9: 0.4 | Q9: 0.4 | R9: 0.4 | S9: 0.4 | T9: 0.4 | U9: 0.4 | V9: =SUM(B9:U9) -> 5.2
A10: TW | B10: POS | C10: Corporation | D10: Corporation | E10: NA | F10: 執行長室 : 客戶價值中心 : 客戶價值中心 | G10: 人事費用 | H10: 李菩綾 | I10: 三級主管 | J10: 0.3 | K10: 0.3 | L10: 0.3 | M10: 0.3 | N10: 0.3 | O10: 0.3 | P10: 0.3 | Q10: 0.3 | R10: 0.3 | S10: 0.3 | T10: 0.3 | U10: 0.3 | V10: =SUM(B10:U10) -> 3.6
A11: TW | B11: OMO | C11: Corporation | D11: Corporation | E11: NA | F11: 執行長室 : 客戶價值中心 : 客戶價值中心 | G11: 人事費用 | H11: 李菩綾 | I11: 三級主管 | J11: 0.7 | K11: 0.7 | L11: 0.7 | M11: 0.7 | N11: 0.6 | O11: 0.6 | P11: 0.6 | Q11: 0.6 | R11: 0.6 | S11: 0.6 | T11: 0.6 | U11: 0.6 | V11: =SUM(B11:U11) -> 7.6
V12: =SUM(B12:U12) -> 0
V13: =SUM(B13:U13) -> 0
V14: =SUM(B14:U14) -> 0
V15: =SUM(B15:U15) -> 0
V16: =SUM(B16:U16) -> 0
V17: =SUM(B17:U17) -> 0
V18: =SUM(B18:U18) -> 0
V19: =SUM(B19:U19) -> 0
V20: =SUM(B20:U20) -> 0
V21: =SUM(B21:U21) -> 0
V22: =SUM(B22:U22) -> 0
V23: =SUM(B23:U23) -> 0
... V1000: =SUM(B1000:U1000) -> 0

Sheet 3.2_集團共用資源_$
A1: 子公司 | B1: 事業單位 | C1: Si 編號 | D1: TA 編號 | E1: 價值鏈專案預算代號 | F1: 費用單位 | G1: 費用類型 | H1: 費用項目 | I1: 備註 | J1: 46023 | K1: 46054 | L1: 46082 | M1: 46113 | N1: 46143 | O1: 46174 | P1: 46204 | Q1: 46235 | R1: 46266 | S1: 46296 | T1: 46327 | U1: 46357 | V1: 2026 year
A3: TW | B3: Corporation | C3: Corporation | D3: Corporation | F3: 執行長室 : 客戶價值中心 : 客戶價值中心 | G3: 人事費用 | H3: 團隊層級獎金 - IC職 | I3: 1667 | J3: =$I$3*'｜工作區>>>'!C36 -> 38341 | K3: =$I$3*'｜工作區>>>'!D36 -> 38341 | L3: =$I$3*'｜工作區>>>'!E36 -> 38341 | M3: =$I$3*'｜工作區>>>'!F36 -> 40008 | N3: =$I$3*'｜工作區>>>'!G36 -> 40008 | O3: =$I$3*'｜工作區>>>'!H36 -> 41675 | P3: =$I$3*'｜工作區>>>'!I36 -> 41675 | Q3: =$I$3*'｜工作區>>>'!J36 -> 41675 | ... U3: =$I$3*'｜工作區>>>'!N36 -> 41675 | V3: =SUM(B3:U3) -> 488431
A4: TW | B4: Corporation | C4: Corporation | D4: Corporation | F4: 執行長室 : 客戶價值中心 : 客戶價值中心 | G4: 人事費用 | H4: 團隊層級獎金 - 一級主管 | I4: 500 | J4: =$I$4*'｜工作區>>>'!C2 -> 500 | K4: =$I$4*'｜工作區>>>'!D2 -> 500 | L4: =$I$4*'｜工作區>>>'!E2 -> 500 | M4: =$I$4*'｜工作區>>>'!F2 -> 500 | N4: =$I$4*'｜工作區>>>'!G2 -> 500 | O4: =$I$4*'｜工作區>>>'!H2 -> 500 | P4: =$I$4*'｜工作區>>>'!I2 -> 500 | Q4: =$I$4*'｜工作區>>>'!J2 -> 500 | ... U4: =$I$4*'｜工作區>>>'!N2 -> 500 | V4: =SUM(B4:U4) -> 6500
A5: TW | B5: Corporation | C5: Corporation | D5: Corporation | F5: 執行長室 : 客戶價值中心 : 客戶價值中心 | G5: 人事費用 | H5: 團隊層級獎金 - 二級主管 | I5: 834 | J5: =$I$5*'｜工作區>>>'!C34 -> 1668 | K5: =$I$5*'｜工作區>>>'!D34 -> 1668 | L5: =$I$5*'｜工作區>>>'!E34 -> 1668 | M5: =$I$5*'｜工作區>>>'!F34 -> 1668 | N5: =$I$5*'｜工作區>>>'!G34 -> 1668 | O5: =$I$5*'｜工作區>>>'!H34 -> 1668 | P5: =$I$5*'｜工作區>>>'!I34 -> 1668 | Q5: =$I$5*'｜工作區>>>'!J34 -> 1668 | ... U5: =$I$5*'｜工作區>>>'!N34 -> 1668 | V5: =SUM(B5:U5) -> 20850
A6: TW | B6: Corporation | C6: Corporation | D6: Corporation | F6: 執行長室 : 客戶價值中心 : 客戶價值中心 | G6: 人事費用 | H6: 團隊層級獎金 - 三級主管 | I6: 1167 | J6: =$I$6*'｜工作區>>>'!C35 -> 2334 | K6: =$I$6*'｜工作區>>>'!D35 -> 2334 | L6: =$I$6*'｜工作區>>>'!E35 -> 2334 | M6: =$I$6*'｜工作區>>>'!F35 -> 2334 | N6: =$I$6*'｜工作區>>>'!G35 -> 2334 | O6: =$I$6*'｜工作區>>>'!H35 -> 2334 | P6: =$I$6*'｜工作區>>>'!I35 -> 2334 | Q6: =$I$6*'｜工作區>>>'!J35 -> 2334 | ... U6: =$I$6*'｜工作區>>>'!N35 -> 2334 | V6: =SUM(B6:U6) -> 29175
A7: TW | B7: Corporation | C7: Corporation | D7: Corporation | F7: 執行長室 : 客戶價值中心 : 客戶價值中心 | G7: 非人事費用 | H7: 季度聚餐 | I7: 334 | J7: =$I$7*sum('｜工作區>>>'!C33:C36) -> 9352 | K7: =$I$7*sum('｜工作區>>>'!D33:D36) -> 9352 | L7: =$I$7*sum('｜工作區>>>'!E33:E36) -> 9352 | M7: =$I$7*sum('｜工作區>>>'!F33:F36) -> 9686 | N7: =$I$7*sum('｜工作區>>>'!G33:G36) -> 9686 | O7: =$I$7*sum('｜工作區>>>'!H33:H36) -> 10020 | P7: =$I$7*sum('｜工作區>>>'!I33:I36) -> 10020 | Q7: =$I$7*sum('｜工作區>>>'!J33:J36) -> 10020 | ... U7: =$I$7*sum('｜工作區>>>'!N33:N36) -> 10020 | V7: =SUM(B7:U7) -> 117902
A8: TW | B8: Corporation | C8: Corporation | D8: Corporation | F8: 執行長室 : 客戶價值中心 : 客戶價值中心 | G8: 非人事費用 | H8: 健康檢查 (在職滿一年) | I8: 250 | J8: =$I$8*sum('｜工作區>>>'!C33:C36) -> 7000 | K8: =$I$8*sum('｜工作區>>>'!D33:D36) -> 7000 | L8: =$I$8*sum('｜工作區>>>'!E33:E36) -> 7000 | M8: =$I$8*sum('｜工作區>>>'!F33:F36) -> 7250 | N8: =$I$8*sum('｜工作區>>>'!G33:G36) -> 7250 | O8: =$I$8*sum('｜工作區>>>'!H33:H36) -> 7500 | P8: =$I$8*sum('｜工作區>>>'!I33:I36) -> 7500 | Q8: =$I$8*sum('｜工作區>>>'!J33:J36) -> 7500 | ... U8: =$I$8*sum('｜工作區>>>'!N33:N36) -> 7500 | V8: =SUM(B8:U8) -> 88250
A9: TW | B9: Corporation | C9: Corporation | D9: Corporation | F9: 執行長室 : 客戶價值中心 : 客戶價值中心 | G9: 非人事費用 | H9: 團體保險 | I9: 135 | J9: =$I$9*sum('｜工作區>>>'!C33:C36) -> 3780 | K9: =$I$9*sum('｜工作區>>>'!D33:D36) -> 3780 | L9: =$I$9*sum('｜工作區>>>'!E33:E36) -> 3780 | M9: =$I$9*sum('｜工作區>>>'!F33:F36) -> 3915 | N9: =$I$9*sum('｜工作區>>>'!G33:G36) -> 3915 | O9: =$I$9*sum('｜工作區>>>'!H33:H36) -> 4050 | P9: =$I$9*sum('｜工作區>>>'!I33:I36) -> 4050 | Q9: =$I$9*sum('｜工作區>>>'!J33:J36) -> 4050 | ... U9: =$I$9*sum('｜工作區>>>'!N33:N36) -> 4050 | V9: =SUM(B9:U9) -> 47655
A10: TW | B10: Corporation | C10: Corporation | D10: Corporation | F10: 執行長室 : 客戶價值中心 : 客戶價值中心 | G10: 非人事費用 | H10: 團建/ 交際費 (一級主管) | I10: 8000 | J10: =$I$10*'｜工作區>>>'!C33 -> 8000 | K10: =$I$10*'｜工作區>>>'!D33 -> 8000 | L10: =$I$10*'｜工作區>>>'!E33 -> 8000 | M10: =$I$10*'｜工作區>>>'!F33 -> 8000 | N10: =$I$10*'｜工作區>>>'!G33 -> 8000 | O10: =$I$10*'｜工作區>>>'!H33 -> 8000 | P10: =$I$10*'｜工作區>>>'!I33 -> 8000 | Q10: =$I$10*'｜工作區>>>'!J33 -> 8000 | ... U10: =$I$10*'｜工作區>>>'!N33 -> 8000 | V10: =SUM(B10:U10) -> 104000
A11: TW | B11: Corporation | C11: Corporation | D11: Corporation | F11: 執行長室 : 客戶價值中心 : 客戶價值中心 | G11: 非人事費用 | H11: 團建/ 交際費 (二級主管) | I11: 3000 | J11: =$I$11*'｜工作區>>>'!C34 -> 6000 | K11: =$I$11*'｜工作區>>>'!D34 -> 6000 | L11: =$I$11*'｜工作區>>>'!E34 -> 6000 | M11: =$I$11*'｜工作區>>>'!F34 -> 6000 | N11: =$I$11*'｜工作區>>>'!G34 -> 6000 | O11: =$I$11*'｜工作區>>>'!H34 -> 6000 | P11: =$I$11*'｜工作區>>>'!I34 -> 6000 | Q11: =$I$11*'｜工作區>>>'!J34 -> 6000 | ... U11: =$I$11*'｜工作區>>>'!N34 -> 6000 | V11: =SUM(B11:U11) -> 75000
A12: TW | B12: Corporation | C12: Corporation | D12: Corporation | F12: 執行長室 : 客戶價值中心 : 客戶價值中心 | G12: 非人事費用 | H12: 團建/ 交際費 (三級主管) | I12: 4000 | J12: =$I$12*'｜工作區>>>'!C35 -> 8000 | K12: =$I$12*'｜工作區>>>'!D35 -> 8000 | L12: =$I$12*'｜工作區>>>'!E35 -> 8000 | M12: =$I$12*'｜工作區>>>'!F35 -> 8000 | N12: =$I$12*'｜工作區>>>'!G35 -> 8000 | O12: =$I$12*'｜工作區>>>'!H35 -> 8000 | P12: =$I$12*'｜工作區>>>'!I35 -> 8000 | Q12: =$I$12*'｜工作區>>>'!J35 -> 8000 | ... U12: =$I$12*'｜工作區>>>'!N35 -> 8000 | V12: =SUM(B12:U12) -> 100000
A13: TW | B13: Corporation | C13: Corporation | D13: Corporation | F13: 執行長室 : 客戶價值中心 : 客戶價值中心 | G13: 非人事費用 | H13: 差旅費 (一級主管) | I13: 12000 | J13: =$I$13*'｜工作區>>>'!C33 -> 12000 | K13: =$I$13*'｜工作區>>>'!D33 -> 12000 | L13: =$I$13*'｜工作區>>>'!E33 -> 12000 | M13: =$I$13*'｜工作區>>>'!F33 -> 12000 | N13: =$I$13*'｜工作區>>>'!G33 -> 12000 | O13: =$I$13*'｜工作區>>>'!H33 -> 12000 | P13: =$I$13*'｜工作區>>>'!I33 -> 12000 | Q13: =$I$13*'｜工作區>>>'!J33 -> 12000 | ... U13: =$I$13*'｜工作區>>>'!N33 -> 12000 | V13: =SUM(B13:U13) -> 156000
A14: TW | B14: Corporation | C14: Corporation | D14: Corporation | F14: 執行長室 : 客戶價值中心 : 客戶價值中心 | G14: 非人事費用 | H14: 差旅費 (二級主管 Johnson Alice ) | I14: 10000 | J14: =$I$14*'｜工作區>>>'!C34 -> 20000 | K14: =$I$14*'｜工作區>>>'!D34 -> 20000 | L14: =$I$14*'｜工作區>>>'!E34 -> 20000 | M14: =$I$14*'｜工作區>>>'!F34 -> 20000 | N14: =$I$14*'｜工作區>>>'!G34 -> 20000 | O14: =$I$14*'｜工作區>>>'!H34 -> 20000 | P14: =$I$14*'｜工作區>>>'!I34 -> 20000 | Q14: =$I$14*'｜工作區>>>'!J34 -> 20000 | ... U14: =$I$14*'｜工作區>>>'!N34 -> 20000 | V14: =SUM(B14:U14) -> 250000
A15: TW | B15: Corporation | C15: Corporation | D15: Corporation | F15: 執行長室 : 客戶價值中心 : 客戶價值中心 | G15: 非人事費用 | H15: 差旅費 (三級主管 Anna ) | I15: 3250 | J15: 3250 | K15: 3250 | L15: 3250 | M15: 3250 | N15: 3250 | O15: 3250 | P15: 3250 | Q15: 3250 | R15: 3250 | S15: 3250 | T15: 3250 | U15: 3250 | V15: =SUM(B15:U15) -> 42250
A16: TW | B16: Corporation | C16: Corporation | D16: Corporation | F16: 執行長室 : 客戶價值中心 : 客戶價值中心 | G16: 非人事費用 | H16: 裝置費用分攤（滿三年更換）ipad | I16: 9800 | J16: 0 | K16: =I16*2 -> 19600 | L16: 0 | M16: =I16*2 -> 19600 | N16: 0 | O16: =I16*2 -> 19600 | P16: 0 | Q16: 0 | R16: 0 | S16: 0 | T16: 0 | U16: 0 | V16: =SUM(B16:U16) -> 68600
A17: TW | B17: Corporation | C17: Corporation | D17: Corporation | F17: 執行長室 : 客戶價值中心 : 客戶價值中心 | G17: 非人事費用 | H17: 裝置費用分攤（滿三年更換）螢幕 | I17: 6000 | J17: =I17*2 -> 12000 | K17: 0 | L17: 0 | M17: 0 | N17: 0 | O17: 0 | P17: 0 | Q17: 0 | R17: 0 | S17: 0 | T17: 0 | U17: 0 | V17: =SUM(B17:U17) -> 18000
A18: TW | B18: Corporation | C18: Corporation | D18: Corporation | F18: 執行長室 : 客戶價值中心 : 客戶價值中心 | G18: 非人事費用 | H18: 裝置費用分攤（滿三年更換）Macbook Air | I18: 36000 | J18: 0 | K18: 0 | L18: 0 | M18: 0 | N18: 0 | O18: 0 | P18: =I18 -> 36000 | Q18: =I18 -> 36000 | R18: 0 | S18: 0 | T18: 0 | U18: 0 | V18: =SUM(B18:U18) -> 108000
A19: TW | B19: Corporation | C19: Corporation | D19: Corporation | F19: 執行長室 : 客戶價值中心 : 客戶價值中心 | G19: 非人事費用 | H19: 裝置費用分攤（新人添購） | I19: =sum(I16:I18) -> 51800 | J19: 0 | K19: 0 | L19: 0 | M19: =I19 -> 51800 | N19: 0 | O19: 0 | P19: 0 | Q19: 0 | R19: 0 | S19: 0 | T19: 0 | U19: 0 | V19: =SUM(B19:U19) -> 103600
A20: TW | B20: Corporation | C20: Corporation | D20: Corporation | F20: 執行長室 : 客戶價值中心 : 客戶價值中心 | G20: 非人事費用 | H20: 裝置折舊攤提 | J20: 17577 | K20: 17577 | L20: 17577 | M20: 17577 | N20: 17577 | O20: 17577 | P20: 17577 | Q20: 17577 | R20: 17577 | S20: 17577 | T20: 17577 | U20: 16419 | V20: =SUM(B20:U20) -> 209766
A21: TW | B21: Corporation | C21: Corporation | D21: Corporation | F21: 執行長室 : 客戶價值中心 : 客戶價值中心 | G21: 非人事費用 | H21: 1Password Business Level | I21: 5201 | J21: 5201 | K21: 5201 | L21: 5201 | M21: 5201 | N21: 5201 | O21: 5201 | P21: 5201 | Q21: 5201 | R21: 5201 | S21: 5201 | T21: 5201 | U21: 5201 | V21: =SUM(B21:U21) -> 67613
A22: TW | B22: Corporation | C22: Corporation | D22: Corporation | F22: 執行長室 : 客戶價值中心 : 客戶價值中心 | G22: 非人事費用 | H22: 通用軟體 GWS | I22: 412 | J22: =$I22*36 -> 14832 | K22: =$I22*36 -> 14832 | L22: =$I22*36 -> 14832 | M22: =$I22*36 -> 14832 | N22: =$I22*36 -> 14832 | O22: =$I22*36 -> 14832 | P22: =$I22*36 -> 14832 | Q22: =$I22*36 -> 14832 | ... U22: =$I22*36 -> 14832 | V22: =SUM(B22:U22) -> 178396
A23: TW | B23: Corporation | C23: Corporation | D23: Corporation | F23: 執行長室 : 客戶價值中心 : 客戶價值中心 | G23: 非人事費用 | H23: 專用軟體 MAC (JAMF) 裝置控管 | I23: 300 | J23: =$I$23*sum('｜工作區>>>'!C33:C36) -> 8400 | K23: =$I$23*sum('｜工作區>>>'!D33:D36) -> 8400 | L23: =$I$23*sum('｜工作區>>>'!E33:E36) -> 8400 | M23: =$I$23*sum('｜工作區>>>'!F33:F36) -> 8700 | N23: =$I$23*sum('｜工作區>>>'!G33:G36) -> 8700 | O23: =$I$23*sum('｜工作區>>>'!H33:H36) -> 9000 | P23: =$I$23*sum('｜工作區>>>'!I33:I36) -> 9000 | Q23: =$I$23*sum('｜工作區>>>'!J33:J36) -> 9000 | ... U23: =$I$23*sum('｜工作區>>>'!N33:N36) -> 9000 | V23: =SUM(B23:U23) -> 105900
A24: TW | B24: Corporation | C24: Corporation | D24: Corporation | F24: 執行長室 : 客戶價值中心 : 客戶價值中心 | G24: 非人事費用 | H24: 通用軟體 Apollo | I24: 124 | J24: =$I$24*sum('｜工作區>>>'!C33:C36) -> 3472 | K24: =$I$24*sum('｜工作區>>>'!D33:D36) -> 3472 | L24: =$I$24*sum('｜工作區>>>'!E33:E36) -> 3472 | M24: =$I$24*sum('｜工作區>>>'!F33:F36) -> 3596 | N24: =$I$24*sum('｜工作區>>>'!G33:G36) -> 3596 | O24: =$I$24*sum('｜工作區>>>'!H33:H36) -> 3720 | P24: =$I$24*sum('｜工作區>>>'!I33:I36) -> 3720 | Q24: =$I$24*sum('｜工作區>>>'!J33:J36) -> 3720 | ... U24: =$I$24*sum('｜工作區>>>'!N33:N36) -> 3720 | V24: =SUM(B24:U24) -> 43772
A25: TW | B25: Corporation | C25: Corporation | D25: Corporation | F25: 執行長室 : 客戶價值中心 : 客戶價值中心 | G25: 非人事費用 | H25: 專用軟體 Office | I25: 282 | J25: =$I$25*18 -> 5076 | K25: =$I$25*18 -> 5076 | L25: =$I$25*18 -> 5076 | M25: =$I$25*18 -> 5076 | N25: =$I$25*18 -> 5076 | O25: =$I$25*18 -> 5076 | P25: =$I$25*18 -> 5076 | Q25: =$I$25*18 -> 5076 | ... U25: =$I$25*18 -> 5076 | V25: =SUM(B25:U25) -> 61194
A26: TW | B26: Corporation | C26: Corporation | D26: Corporation | F26: 執行長室 : 客戶價值中心 : 客戶價值中心 | G26: 非人事費用 | H26: 通用軟體 Asana | I26: 830 | J26: =$I$26*sum('｜工作區>>>'!C33:C36) -> 23240 | K26: =$I$26*sum('｜工作區>>>'!D33:D36) -> 23240 | L26: =$I$26*sum('｜工作區>>>'!E33:E36) -> 23240 | M26: =$I$26*sum('｜工作區>>>'!F33:F36) -> 24070 | N26: =$I$26*sum('｜工作區>>>'!G33:G36) -> 24070 | O26: =$I$26*sum('｜工作區>>>'!H33:H36) -> 24900 | P26: =$I$26*sum('｜工作區>>>'!I33:I36) -> 24900 | Q26: =$I$26*sum('｜工作區>>>'!J33:J36) -> 24900 | ... U26: =$I$26*sum('｜工作區>>>'!N33:N36) -> 24900 | V26: =SUM(B26:U26) -> 292990
A27: TW | B27: Corporation | C27: Corporation | D27: Corporation | F27: 執行長室 : 客戶價值中心 : 客戶價值中心 | G27: 非人事費用 | H27: 通用軟體 Notion | I27: 300 | J27: =$I$26*(sum('｜工作區>>>'!C33:C36)+4) -> 26560 | K27: =$I$26*(sum('｜工作區>>>'!D33:D36)+4) -> 26560 | L27: =$I$26*(sum('｜工作區>>>'!E33:E36)+4) -> 26560 | M27: =$I$26*(sum('｜工作區>>>'!F33:F36)+4) -> 27390 | N27: =$I$26*(sum('｜工作區>>>'!G33:G36)+4) -> 27390 | O27: =$I$26*(sum('｜工作區>>>'!H33:H36)+4) -> 28220 | P27: =$I$26*(sum('｜工作區>>>'!I33:I36)+4) -> 28220 | Q27: =$I$26*(sum('｜工作區>>>'!J33:J36)+4) -> 28220 | ... U27: =$I$26*(sum('｜工作區>>>'!N33:N36)+4) -> 28220 | V27: =SUM(B27:U27) -> 332300
A28: TW | B28: Corporation | C28: Corporation | D28: Corporation | F28: 執行長室 : 客戶價值中心 : 客戶價值中心 | G28: 非人事費用 | H28: 通用軟體 Slack | I28: 218 | J28: =$I$28*sum('｜工作區>>>'!C33:C37) -> 7848 | K28: =$I$28*sum('｜工作區>>>'!D33:D37) -> 7848 | L28: =$I$28*sum('｜工作區>>>'!E33:E37) -> 7848 | M28: =$I$28*sum('｜工作區>>>'!F33:F37) -> 8066 | N28: =$I$28*sum('｜工作區>>>'!G33:G37) -> 8066 | O28: =$I$28*sum('｜工作區>>>'!H33:H37) -> 8284 | P28: =$I$28*sum('｜工作區>>>'!I33:I37) -> 8284 | Q28: =$I$28*sum('｜工作區>>>'!J33:J37) -> 8284 | ... U28: =$I$28*sum('｜工作區>>>'!N33:N37) -> 8284 | V28: =SUM(B28:U28) -> 97882
A29: TW | B29: Corporation | C29: Corporation | D29: Corporation | F29: 執行長室 : 客戶價值中心 : 客戶價值中心 | G29: 非人事費用 | H29: 每月 ChatGPT 費用 | I29: 800 | J29: =$I$29*12 -> 9600 | K29: =$I$29*12 -> 9600 | L29: =$I$29*12 -> 9600 | M29: =$I$29*12 -> 9600 | N29: =$I$29*12 -> 9600 | O29: =$I$29*12 -> 9600 | P29: =$I$29*12 -> 9600 | Q29: =$I$29*12 -> 9600 | ... U29: =$I$29*12 -> 9600 | V29: =SUM(B29:U29) -> 116000
A30: TW | B30: Corporation | C30: Corporation | D30: Corporation | F30: 執行長室 : 客戶價值中心 : 客戶價值中心 | G30: 非人事費用 | H30: 辦公室VPN | I30: 100 | J30: =$I$30*sum('｜工作區>>>'!C33:C36) -> 2800 | K30: =$I$30*sum('｜工作區>>>'!D33:D36) -> 2800 | L30: =$I$30*sum('｜工作區>>>'!E33:E36) -> 2800 | M30: =$I$30*sum('｜工作區>>>'!F33:F36) -> 2900 | N30: =$I$30*sum('｜工作區>>>'!G33:G36) -> 2900 | O30: =$I$30*sum('｜工作區>>>'!H33:H36) -> 3000 | P30: =$I$30*sum('｜工作區>>>'!I33:I36) -> 3000 | Q30: =$I$30*sum('｜工作區>>>'!J33:J36) -> 3000 | ... U30: =$I$30*sum('｜工作區>>>'!N33:N36) -> 3000 | V30: =SUM(B30:U30) -> 35300
A31: TW | B31: Corporation | C31: Corporation | D31: Corporation | F31: 執行長室 : 客戶價值中心 : 客戶價值中心 | G31: 非人事費用 | H31: 專用軟體 Netsuite 主管/看管報帳號 | I31: 1384 | J31: =$I$31*sum('｜工作區>>>'!C33:C35) -> 6920 | K31: =$I$31*sum('｜工作區>>>'!D33:D35) -> 6920 | L31: =$I$31*sum('｜工作區>>>'!E33:E35) -> 6920 | M31: =$I$31*sum('｜工作區>>>'!F33:F35) -> 6920 | N31: =$I$31*sum('｜工作區>>>'!G33:G35) -> 6920 | O31: =$I$31*sum('｜工作區>>>'!H33:H35) -> 6920 | P31: =$I$31*sum('｜工作區>>>'!I33:I35) -> 6920 | Q31: =$I$31*sum('｜工作區>>>'!J33:J35) -> 6920 | ... U31: =$I$31*sum('｜工作區>>>'!N33:N35) -> 6920 | V31: =SUM(B31:U31) -> 84424
A32: TW | B32: Corporation | C32: Corporation | D32: Corporation | F32: 執行長室 : 客戶價值中心 : 客戶價值中心 | G32: 非人事費用 | H32: 專用軟體 Netsuite 員工帳號 | I32: 229 | J32: =$I$32*'｜工作區>>>'!C36 -> 5267 | K32: =$I$32*'｜工作區>>>'!D36 -> 5267 | L32: =$I$32*'｜工作區>>>'!E36 -> 5267 | M32: =$I$32*'｜工作區>>>'!F36 -> 5496 | N32: =$I$32*'｜工作區>>>'!G36 -> 5496 | O32: =$I$32*'｜工作區>>>'!H36 -> 5725 | P32: =$I$32*'｜工作區>>>'!I36 -> 5725 | Q32: =$I$32*'｜工作區>>>'!J36 -> 5725 | ... U32: =$I$32*'｜工作區>>>'!N36 -> 5725 | V32: =SUM(B32:U32) -> 67097
A33: TW | B33: Corporation | C33: Corporation | D33: Corporation | E33: NA | F33: 執行長室 : 客戶價值中心 : 客戶價值中心 | G33: 非人事費用 | H33: 專用軟體 Tableau Viewer | I33: 352 | J33: =$I$33*'｜工作區>>>'!C34 -> 704 | K33: =$I$33*'｜工作區>>>'!D34 -> 704 | L33: =$I$33*'｜工作區>>>'!E34 -> 704 | M33: =$I$33*'｜工作區>>>'!F34 -> 704 | N33: =$I$33*'｜工作區>>>'!G34 -> 704 | O33: =$I$33*'｜工作區>>>'!H34 -> 704 | P33: =$I$33*'｜工作區>>>'!I34 -> 704 | Q33: =$I$33*'｜工作區>>>'!J34 -> 704 | ... U33: =$I$33*'｜工作區>>>'!N34 -> 704 | V33: =SUM(B33:U33) -> 8800
A34: TW | B34: Corporation | C34: Corporation | D34: Corporation | F34: 執行長室 : 客戶價值中心 : 客戶價值中心 | G34: 非人事費用 | H34: 專用軟體 Tableau Creator | I34: 2354 | J34: =$I$34*'｜工作區>>>'!C34 -> 4708 | K34: =$I$34*'｜工作區>>>'!D34 -> 4708 | L34: =$I$34*'｜工作區>>>'!E34 -> 4708 | M34: =$I$34*'｜工作區>>>'!F34 -> 4708 | N34: =$I$34*'｜工作區>>>'!G34 -> 4708 | O34: =$I$34*'｜工作區>>>'!H34 -> 4708 | P34: =$I$34*'｜工作區>>>'!I34 -> 4708 | Q34: =$I$34*'｜工作區>>>'!J34 -> 4708 | ... U34: =$I$34*'｜工作區>>>'!N34 -> 4708 | V34: =SUM(B34:U34) -> 58850
A35: TW | B35: Corporation | C35: Corporation | D35: Corporation | F35: 執行長室 : 客戶價值中心 : 客戶價值中心 | G35: 非人事費用 | H35: 專用軟體 Salesforce Service Cloud | I35: 3728 | J35: =$I$35*sum('｜工作區>>>'!C33:C36) -> 104384 | K35: =$I$35*sum('｜工作區>>>'!D33:D36) -> 104384 | L35: =$I$35*sum('｜工作區>>>'!E33:E36) -> 104384 | M35: =$I$35*sum('｜工作區>>>'!F33:F36) -> 108112 | N35: =$I$35*sum('｜工作區>>>'!G33:G36) -> 108112 | O35: =$I$35*sum('｜工作區>>>'!H33:H36) -> 111840 | P35: =$I$35*sum('｜工作區>>>'!I33:I36) -> 111840 | Q35: =$I$35*sum('｜工作區>>>'!J33:J36) -> 111840 | ... U35: =$I$35*sum('｜工作區>>>'!N33:N36) -> 111840 | V35: =SUM(B35:U35) -> 1315984
A36: TW | B36: Corporation | C36: Corporation | D36: Corporation | F36: 執行長室 : 客戶價值中心 : 客戶價值中心 | G36: 非人事費用 | H36: 專用軟體 Salesforce Sales+Service Cloud | I36: 4680 | J36: 4680 | K36: 4680 | L36: 4680 | M36: 4680 | N36: 4680 | O36: 4680 | P36: 4680 | Q36: 4680 | R36: 4680 | S36: 4680 | T36: 4680 | U36: 4680 | V36: =SUM(B36:U36) -> 60840
A37: TW | B37: Corporation | C37: Corporation | D37: Corporation | F37: 執行長室 : 客戶價值中心 : 客戶價值中心 | G37: 非人事費用 | H37: miro ( USD 8 /人/月） | I37: 250 | J37: =$I$37*5 -> 1250 | K37: =$I$37*5 -> 1250 | L37: =$I$37*5 -> 1250 | M37: =$I$37*5 -> 1250 | N37: =$I$37*5 -> 1250 | O37: =$I$37*5 -> 1250 | P37: =$I$37*5 -> 1250 | Q37: =$I$37*5 -> 1250 | ... U37: =$I$37*5 -> 1250 | V37: =SUM(B37:U37) -> 15250
A38: TW | B38: Corporation | C38: Corporation | D38: Corporation | F38: 執行長室 : 客戶價值中心 : 客戶價值中心 | G38: 非人事費用 | H38: Gamma ( USD 8 /人/月） | I38: 250 | J38: =$I$38*5 -> 1250 | K38: =$I$38*5 -> 1250 | L38: =$I$38*5 -> 1250 | M38: =$I$38*5 -> 1250 | N38: =$I$38*5 -> 1250 | O38: =$I$38*5 -> 1250 | P38: =$I$38*5 -> 1250 | Q38: =$I$38*5 -> 1250 | ... U38: =$I$38*5 -> 1250 | V38: =SUM(B38:U38) -> 15250
A39: TW | B39: Corporation | C39: Corporation | D39: Corporation | F39: 執行長室 : 客戶價值中心 : 客戶價值中心 | G39: 人事費用 | H39: 加總 | J39: 288000 | K39: 288000 | L39: 288000 | M39: 288000 | N39: 288000 | O39: 288000 | P39: 288000 | Q39: 288000 | R39: 288000 | S39: 288000 | T39: 288000 | U39: 288000 | V39: 3456000
A40: TW | B40: POS | C40: Corporation | D40: Corporation | F40: 執行長室 : 客戶價值中心 : 客戶價值中心 | G40: 人事費用 | H40: 加總 | J40: 305824 | K40: 305824 | L40: 305824 | M40: 305824 | N40: 305824 | O40: 305824 | P40: 305824 | Q40: 305824 | R40: 305824 | S40: 305824 | T40: 305824 | U40: 305824 | V40: 3669888
A41: TW | B41: OMO | C41: Corporation | D41: Corporation | F41: 執行長室 : 客戶價值中心 : 客戶價值中心 | G41: 人事費用 | H41: 加總 | J41: 415954 | K41: 415954 | L41: 415954 | M41: 415954 | N41: 386577 | O41: 386577 | P41: 386577 | Q41: 386577 | R41: 386577 | S41: 386577 | T41: 386577 | U41: 386577 | V41: 4756432
V42: =SUM(B42:U42) -> 0
V43: =SUM(B43:U43) -> 0
V44: =SUM(B44:U44) -> 0
V45: =SUM(B45:U45) -> 0
V46: =SUM(B46:U46) -> 0
V47: =SUM(B47:U47) -> 0
V48: =SUM(B48:U48) -> 0
V49: =SUM(B49:U49) -> 0
V50: =SUM(B50:U50) -> 0
V51: =SUM(B51:U51) -> 0
V52: =SUM(B52:U52) -> 0
V53: =SUM(B53:U53) -> 0
... V1000: =SUM(B1000:U1000) -> 0

Sheet 事業人力資源配置匯總表(自動彙整)
A1: 子公司 | B1: 事業單位 | C1: Si 編號 | D1: TA 編號 | E1: 價值鏈專案預算代號 | F1: 費用單位 | G1: 費用類型 | H1: 姓名 | I1: 備註 | J1: 46023 | K1: 46054 | L1: 46082 | M1: 46113 | N1: 46143 | O1: 46174 | P1: 46204 | Q1: 46235 | R1: 46266 | S1: 46296 | T1: 46327 | U1: 46357 | V1: 2026 year
A2: TW | B2: POS | C2: ENTSi1 | D2: ENT26TA1 | E2: NA | F2: 執行長室 : 客戶價值中心 : 客戶成功管理部 : 客戶成功團隊 | G2: 人事費用 | H2: 陳馨如 | J2: 0.2 | K2: 0.2 | L2: 0.2 | M2: 0.2 | N2: 0.2 | O2: 0.2 | P2: 0.2 | Q2: 0.2 | R2: 0.2 | S2: 0.2 | T2: 0.2 | U2: 0.2 | V2: 2.4
A3: TW | B3: OMO | C3: OrderingSi1 | D3: Ordering26TA2 | E3: NA | F3: 執行長室 : 客戶價值中心 : 客戶成功管理部 : 客戶成功團隊 | G3: 人事費用 | H3: 陳馨如 | J3: 0.4 | K3: 0.4 | L3: 0.4 | M3: 0.4 | N3: 0.4 | O3: 0.4 | P3: 0.4 | Q3: 0.4 | R3: 0.4 | S3: 0.4 | T3: 0.4 | U3: 0.4 | V3: 4.8
A4: TW | B4: OMO | C4: ReservationSi1 | D4: Reservation26TA1 | E4: NA | F4: 執行長室 : 客戶價值中心 : 客戶成功管理部 : 客戶成功團隊 | G4: 人事費用 | H4: 陳馨如 | J4: 0.4 | K4: 0.4 | L4: 0.4 | M4: 0.4 | N4: 0.4 | O4: 0.4 | P4: 0.4 | Q4: 0.4 | R4: 0.4 | S4: 0.4 | T4: 0.4 | U4: 0.4 | V4: 4.8
A5: TW | B5: POS | C5: ENTSi1 | D5: ENT26TA1 | E5: NA | F5: 執行長室 : 客戶價值中心 : 客戶成功管理部 : 客戶成功團隊 | G5: 人事費用 | H5: 楊麗涵 | J5: 0.2 | K5: 0.2 | L5: 0.2 | M5: 0.2 | N5: 0.2 | O5: 0.2 | P5: 0.2 | Q5: 0.2 | R5: 0.2 | S5: 0.2 | T5: 0.2 | U5: 0.2 | V5: 2.4
A6: TW | B6: OMO | C6: OrderingSi1 | D6: Ordering26TA2 | E6: NA | F6: 執行長室 : 客戶價值中心 : 客戶成功管理部 : 客戶成功團隊 | G6: 人事費用 | H6: 楊麗涵 | J6: 0.4 | K6: 0.4 | L6: 0.4 | M6: 0.4 | N6: 0.4 | O6: 0.4 | P6: 0.4 | Q6: 0.4 | R6: 0.4 | S6: 0.4 | T6: 0.4 | U6: 0.4 | V6: 2.4
A7: TW | B7: OMO | C7: ReservationSi1 | D7: Reservation26TA1 | E7: NA | F7: 執行長室 : 客戶價值中心 : 客戶成功管理部 : 客戶成功團隊 | G7: 人事費用 | H7: 楊麗涵 | J7: 0.4 | K7: 0.4 | L7: 0.4 | M7: 0.4 | N7: 0.4 | O7: 0.4 | P7: 0.4 | Q7: 0.4 | R7: 0.4 | S7: 0.4 | T7: 0.4 | U7: 0.4 | V7: 4.8
A8: TW | B8: POS | C8: ENTSi1 | D8: ENT26TA1 | E8: NA | F8: 執行長室 : 客戶價值中心 : 客戶成功管理部 : 客戶成功團隊 | G8: 人事費用 | H8: NEW - MS | I8: 預計 2025 年 11 月到職 | J8: 0.2 | K8: 0.2 | L8: 0.2 | M8: 0.2 | N8: 0.2 | O8: 0.2 | P8: 0.2 | Q8: 0.2 | R8: 0.2 | S8: 0.2 | T8: 0.2 | U8: 0.2 | V8: 4.8
A9: TW | B9: OMO | C9: OrderingSi1 | D9: Ordering26TA2 | E9: NA | F9: 執行長室 : 客戶價值中心 : 客戶成功管理部 : 客戶成功團隊 | G9: 人事費用 | H9: NEW - MS | I9: 預計 2025 年 11 月到職 | J9: 0.4 | K9: 0.4 | L9: 0.4 | M9: 0.4 | N9: 0.4 | O9: 0.4 | P9: 0.4 | Q9: 0.4 | R9: 0.4 | S9: 0.4 | T9: 0.4 | U9: 0.4 | V9: 2.4
A10: TW | B10: OMO | C10: ReservationSi1 | D10: Reservation26TA1 | E10: NA | F10: 執行長室 : 客戶價值中心 : 客戶成功管理部 : 客戶成功團隊 | G10: 人事費用 | H10: NEW - MS | I10: 預計 2025 年 11 月到職 | J10: 0.4 | K10: 0.4 | L10: 0.4 | M10: 0.4 | N10: 0.4 | O10: 0.4 | P10: 0.4 | Q10: 0.4 | R10: 0.4 | S10: 0.4 | T10: 0.4 | U10: 0.4 | V10: 4.8
A11: TW | B11: POS | C11: ENTSi1 | D11: ENT26TA1 | E11: NA | F11: 執行長室 : 客戶價值中心 : 客戶關係管理部 : 客戶經理團隊 | G11: 人事費用 | H11: 蔡佳玲 | I11: 總部 AM | J11: 0.6 | K11: 0.6 | L11: 0.6 | M11: 0.6 | N11: 0.6 | O11: 0.9 | P11: 0.9 | Q11: 0.9 | R11: 0.9 | S11: 0.9 | T11: 0.9 | U11: 0.9 | V11: 4.8
A12: TW | B12: POS | C12: SMBSi1 | D12: SMB26TA1 | E12: NA | F12: 執行長室 : 客戶價值中心 : 客戶關係管理部 : 客戶經理團隊 | G12: 人事費用 | H12: 莊媁晨 | I12: OMO+POS AM | J12: 0.5 | K12: 0.5 | L12: 0.5 | M12: 0.5 | N12: 0.5 | O12: 0.5 | P12: 0.5 | Q12: 0.5 | R12: 0.5 | S12: 0.5 | T12: 0.5 | U12: 0.5 | V12: 2.4
A13: TW | B13: OMO | C13: OrderingSi1 | D13: Ordering26TA3 | E13: NA | F13: 執行長室 : 客戶價值中心 : 客戶關係管理部 : 客戶經理團隊 | G13: 人事費用 | H13: 莊媁晨 | I13: OMO+POS AM | J13: 0.3 | K13: 0.3 | L13: 0.3 | M13: 0.3 | N13: 0.3 | O13: 0.3 | P13: 0.3 | Q13: 0.3 | R13: 0.3 | S13: 0.3 | T13: 0.3 | U13: 0.3 | V13: 4.8
A14: TW | B14: OMO | C14: ReservationSi1 | D14: Reservation26TA2 | E14: NA | F14: 執行長室 : 客戶價值中心 : 客戶關係管理部 : 客戶經理團隊 | G14: 人事費用 | H14: 莊媁晨 | I14: OMO+POS AM | J14: 0.2 | K14: 0.2 | L14: 0.2 | M14: 0.2 | N14: 0.2 | O14: 0.2 | P14: 0.2 | Q14: 0.2 | R14: 0.2 | S14: 0.2 | T14: 0.2 | U14: 0.2 | V14: 4.8
A15: TW | B15: POS | C15: ENTSi2 | D15: ENT26TA1 | E15: VC05P1 | F15: 執行長室 : 客戶價值中心 : 客戶價值中心 | G15: 人事費用 | H15: 李菩綾 | I15: 三級主管 | J15: 0.1 | K15: 0.1 | L15: 0.1 | M15: 0.1 | N15: 0.1 | O15: 0.2 | P15: 0.2 | Q15: 0.1 | R15: 0.1 | S15: 0.1 | T15: 0.1 | U15: 0.1 | V15: 1.4
A16: TW | B16: POS | C16: Maintenance | D16: Baseline | E16: NA | F16: 執行長室 : 客戶價值中心 : 客戶成功管理部 : 產品教育團隊 | G16: 人事費用 | H16: 周玟萱 | J16: 0.5 | K16: 0.5 | L16: 0.5 | M16: 0.5 | N16: 0.5 | O16: 0.5 | P16: 0.5 | Q16: 0.5 | R16: 0.5 | S16: 0.5 | T16: 0.5 | U16: 0.5 | V16: 6
A17: TW | B17: OMO | C17: Maintenance | D17: Baseline | E17: NA | F17: 執行長室 : 客戶價值中心 : 客戶成功管理部 : 產品教育團隊 | G17: 人事費用 | H17: 周玟萱 | J17: 0.5 | K17: 0.5 | L17: 0.5 | M17: 0.5 | N17: 0.5 | O17: 0.5 | P17: 0.5 | Q17: 0.5 | R17: 0.5 | S17: 0.5 | T17: 0.5 | U17: 0.5 | V17: 6
A18: TW | B18: POS | C18: Maintenance | D18: Baseline | E18: NA | F18: 執行長室 : 客戶價值中心 : 客戶成功管理部 : 產品教育團隊 | G18: 人事費用 | H18: 朱肇平 | J18: 0.5 | K18: 0.5 | L18: 0.5 | M18: 0.5 | N18: 0.5 | O18: 0.5 | P18: 0.5 | Q18: 0.5 | R18: 0.5 | S18: 0.5 | T18: 0.5 | U18: 0.5 | V18: 6
A19: TW | B19: OMO | C19: Maintenance | D19: Baseline | E19: NA | F19: 執行長室 : 客戶價值中心 : 客戶成功管理部 : 產品教育團隊 | G19: 人事費用 | H19: 朱肇平 | J19: 0.5 | K19: 0.5 | L19: 0.5 | M19: 0.5 | N19: 0.5 | O19: 0.5 | P19: 0.5 | Q19: 0.5 | R19: 0.5 | S19: 0.5 | T19: 0.5 | U19: 0.5 | V19: 6
A20: TW | B20: POS | C20: Maintenance | D20: Baseline | E20: NA | F20: 執行長室 : 客戶價值中心 : 客戶關係管理部 : TSE 團隊 | G20: 人事費用 | H20: 丁伊柔 | J20: 0.7 | K20: 0.7 | L20: 0.7 | M20: 0.7 | N20: 0.7 | O20: 0.7 | P20: 0.7 | Q20: 0.7 | R20: 0.7 | S20: 0.7 | T20: 0.7 | U20: 0.7 | V20: 8.4
A21: TW | B21: OMO | C21: Maintenance | D21: Baseline | E21: NA | F21: 執行長室 : 客戶價值中心 : 客戶關係管理部 : TSE 團隊 | G21: 人事費用 | H21: 丁伊柔 | J21: 0.3 | K21: 0.3 | L21: 0.3 | M21: 0.3 | N21: 0.3 | O21: 0.3 | P21: 0.3 | Q21: 0.3 | R21: 0.3 | S21: 0.3 | T21: 0.3 | U21: 0.3 | V21: 3.6
A22: TW | B22: POS | C22: Maintenance | D22: Baseline | E22: NA | F22: 執行長室 : 客戶價值中心 : 客戶關係管理部 : TSE 團隊 | G22: 人事費用 | H22: 林展甫 | J22: 0.7 | K22: 0.7 | L22: 0.7 | M22: 0.7 | N22: 0.7 | O22: 0.7 | P22: 0.7 | Q22: 0.7 | R22: 0.7 | S22: 0.7 | T22: 0.7 | U22: 0.7 | V22: 8.4
A23: TW | B23: OMO | C23: Maintenance | D23: Baseline | E23: NA | F23: 執行長室 : 客戶價值中心 : 客戶關係管理部 : TSE 團隊 | G23: 人事費用 | H23: 林展甫 | J23: 0.3 | K23: 0.3 | L23: 0.3 | M23: 0.3 | N23: 0.3 | O23: 0.3 | P23: 0.3 | Q23: 0.3 | R23: 0.3 | S23: 0.3 | T23: 0.3 | U23: 0.3 | V23: 3.6
A24: TW | B24: POS | C24: Maintenance | D24: Baseline | E24: NA | F24: 執行長室 : 客戶價值中心 : 客戶關係管理部 : 客服團隊 | G24: 人事費用 | H24: 吳芯儀 | J24: 0.8 | K24: 0.8 | L24: 0.8 | M24: 0.8 | N24: 0.8 | O24: 0.8 | P24: 0.8 | Q24: 0.8 | R24: 0.8 | S24: 0.8 | T24: 0.8 | U24: 0.8 | V24: 9.6
A25: TW | B25: OMO | C25: Maintenance | D25: Baseline | E25: NA | F25: 執行長室 : 客戶價值中心 : 客戶關係管理部 : 客服團隊 | G25: 人事費用 | H25: 吳芯儀 | J25: 0.2 | K25: 0.2 | L25: 0.2 | M25: 0.2 | N25: 0.2 | O25: 0.2 | P25: 0.2 | Q25: 0.2 | R25: 0.2 | S25: 0.2 | T25: 0.2 | U25: 0.2 | V25: 2.4
A26: TW | B26: POS | C26: Maintenance | D26: Baseline | E26: NA | F26: 執行長室 : 客戶價值中心 : 客戶關係管理部 : 客服團隊 | G26: 人事費用 | H26: 戴馨妤 | J26: 0.8 | K26: 0.8 | L26: 0.8 | M26: 0.8 | N26: 0.8 | O26: 0.8 | P26: 0.8 | Q26: 0.8 | R26: 0.8 | S26: 0.8 | T26: 0.8 | U26: 0.8 | V26: 9.6
A27: TW | B27: OMO | C27: Maintenance | D27: Baseline | E27: NA | F27: 執行長室 : 客戶價值中心 : 客戶關係管理部 : 客服團隊 | G27: 人事費用 | H27: 戴馨妤 | J27: 0.2 | K27: 0.2 | L27: 0.2 | M27: 0.2 | N27: 0.2 | O27: 0.2 | P27: 0.2 | Q27: 0.2 | R27: 0.2 | S27: 0.2 | T27: 0.2 | U27: 0.2 | V27: 2.4
... A39: TW | B39: OMO | C39: Maintenance | D39: Baseline | E39: NA | F39: 執行長室 : 客戶價值中心 : 客戶關係管理部 : 客服團隊 | G39: 人事費用 | H39: 周思吟 | J39: 0.2 | K39: 0.2 | L39: 0.2 | M39: 0.2 | N39: 0.2 | O39: 0.2 | P39: 0.2 | Q39: 0.2 | R39: 0.2 | S39: 0.2 | T39: 0.2 | U39: 0.2 | V39: 2.4
A40: TW | B40: POS | C40: Maintenance | D40: Baseline | E40: NA | F40: 執行長室 : 客戶價值中心 : 客戶關係管理部 : 客服團隊 | G40: 人事費用 | H40: 劉晏廷 | I40: TW-CS 工讀生 | J40: 1 | K40: 1 | L40: 1 | M40: 1 | N40: 1 | O40: 1 | P40: 1 | Q40: 1 | R40: 1 | S40: 1 | T40: 1 | U40: 1 | V40: 12
A41: TW | B41: POS | C41: Maintenance | D41: Baseline | E41: NA | F41: 執行長室 : 客戶價值中心 : 客戶關係管理部 : 客服團隊 | G41: 人事費用 | H41: 盧欣妤 | I41: TW-CS 工讀生 | J41: 1 | K41: 1 | L41: 1 | M41: 1 | N41: 1 | O41: 1 | P41: 1 | Q41: 1 | R41: 1 | S41: 1 | T41: 1 | U41: 1 | V41: 12
A42: SG | B42: POS | C42: Maintenance | D42: Baseline | E42: NA | F42: 執行長室 : 客戶價值中心 : 客戶關係管理部 : 客服團隊 | G42: 人事費用 | H42: 陳怡婷 | I42: SG-CS 工讀生 | J42: 1 | K42: 1 | L42: 1 | M42: 1 | N42: 1 | O42: 1 | P42: 1 | Q42: 1 | R42: 1 | S42: 1 | T42: 1 | U42: 1 | V42: 12
A43: TW | B43: POS | C43: Maintenance | D43: Baseline | E43: NA | F43: 執行長室 : 客戶價值中心 : 客戶關係管理部 : 客戶經理團隊 | G43: 人事費用 | H43: 陳嘉汶 | I43: 總部 AM ( 育嬰留停） | J43: NA | K43: NA | L43: NA | M43: NA | N43: NA | O43: 1 | P43: 1 | Q43: 1 | R43: 1 | S43: 1 | T43: 1 | U43: 1 | V43: 7
A44: TW | B44: POS | C44: Maintenance | D44: Baseline | E44: NA | F44: 執行長室 : 客戶價值中心 : 客戶關係管理部 : 客戶經理團隊 | G44: 人事費用 | H44: 蔡佳玲 | I44: 總部 AM | J44: 0.4 | K44: 0.4 | L44: 0.4 | M44: 0.4 | N44: 0.4 | O44: 0.2 | P44: 0.2 | Q44: 0.2 | R44: 0.2 | S44: 0.2 | T44: 0.2 | U44: 0.2 | V44: 3.4
A45: TW | B45: POS | C45: Maintenance | D45: Baseline | E45: NA | F45: 執行長室 : 客戶價值中心 : 客戶關係管理部 : 客戶經理團隊 | G45: 人事費用 | H45: 許裴宸 | I45: TW-POS-AM | J45: 1 | K45: 1 | L45: 1 | M45: 1 | N45: 1 | O45: 1 | P45: 1 | Q45: 1 | R45: 1 | S45: 1 | T45: 1 | U45: 1 | V45: 12
A46: TW | B46: OMO | C46: Maintenance | D46: Baseline | E46: NA | F46: 執行長室 : 客戶價值中心 : 客戶關係管理部 : 客戶經理團隊 | G46: 人事費用 | H46: 黃如蘭 | I46: TW-OMO-AM | J46: 1 | K46: 1 | L46: 1 | M46: 1 | N46: 1 | O46: 1 | P46: 1 | Q46: 1 | R46: 1 | S46: 1 | T46: 1 | U46: 1 | V46: 12
A47: TW | B47: POS | C47: Maintenance | D47: Baseline | E47: NA | F47: 執行長室 : 客戶價值中心 : 客戶關係管理部 : 客服團隊 | G47: 人事費用 | H47: ( A ) NEW-CS T1 | J47: 0.8 | K47: 0.8 | L47: 0.8 | M47: 0.8 | N47: 0.8 | O47: 0.8 | P47: 0.8 | Q47: 0.8 | R47: 0.8 | S47: 0.8 | T47: 0.8 | U47: 0.8 | V47: 9.6
A48: TW | B48: OMO | C48: Maintenance | D48: Baseline | E48: NA | F48: 執行長室 : 客戶價值中心 : 客戶關係管理部 : 客服團隊 | G48: 人事費用 | H48: ( A ) NEW-CS T1 | J48: 0.2 | K48: 0.2 | L48: 0.2 | M48: 0.2 | N48: 0.2 | O48: 0.2 | P48: 0.2 | Q48: 0.2 | R48: 0.2 | S48: 0.2 | T48: 0.2 | U48: 0.2 | V48: 2.4
A49: TW | B49: POS | C49: Maintenance | D49: Baseline | E49: NA | F49: 執行長室 : 客戶價值中心 : 客戶關係管理部 : 客服團隊 | G49: 人事費用 | H49: ( B ) NEW-CS T1 | J49: NA | K49: NA | L49: NA | M49: 0.8 | N49: 0.8 | O49: 0.8 | P49: 0.8 | Q49: 0.8 | R49: 0.8 | S49: 0.8 | T49: 0.8 | U49: 0.8 | V49: 7.2
A50: TW | B50: OMO | C50: Maintenance | D50: Baseline | E50: NA | F50: 執行長室 : 客戶價值中心 : 客戶關係管理部 : 客服團隊 | G50: 人事費用 | H50: ( B ) NEW-CS T1 | J50: NA | K50: NA | L50: NA | M50: 0.2 | N50: 0.2 | O50: 0.2 | P50: 0.2 | Q50: 0.2 | R50: 0.2 | S50: 0.2 | T50: 0.2 | U50: 0.2 | V50: 1.8
A51: TW | B51: Corporation | C51: Corporation | D51: Corporation | E51: NA | F51: 執行長室 : 客戶價值中心 : 客戶價值中心 | G51: 人事費用 | H51: 梁方瑜 | I51: 一級主管 | J51: 1 | K51: 1 | L51: 1 | M51: 1 | N51: 1 | O51: 1 | P51: 1 | Q51: 1 | R51: 1 | S51: 1 | T51: 1 | U51: 1 | V51: 12
A52: TW | B52: POS | C52: Corporation | D52: Corporation | E52: NA | F52: 執行長室 : 客戶價值中心 : 客戶價值中心 | G52: 人事費用 | H52: 謝孟娟 | I52: 二級主管 | J52: 0.2 | K52: 0.2 | L52: 0.2 | M52: 0.2 | N52: 0.2 | O52: 0.2 | P52: 0.2 | Q52: 0.2 | R52: 0.2 | S52: 0.2 | T52: 0.2 | U52: 0.2 | V52: 2.4
A53: TW | B53: OMO | C53: Corporation | D53: Corporation | E53: NA | F53: 執行長室 : 客戶價值中心 : 客戶價值中心 | G53: 人事費用 | H53: 謝孟娟 | I53: 二級主管 | J53: 0.8 | K53: 0.8 | L53: 0.8 | M53: 0.8 | N53: 0.8 | O53: 0.8 | P53: 0.8 | Q53: 0.8 | R53: 0.8 | S53: 0.8 | T53: 0.8 | U53: 0.8 | V53: 9.6
A54: TW | B54: POS | C54: Corporation | D54: Corporation | E54: NA | F54: 執行長室 : 客戶價值中心 : 客戶價值中心 | G54: 人事費用 | H54: 陳繼訓 | I54: 二級主管 | J54: 0.6 | K54: 0.6 | L54: 0.6 | M54: 0.6 | N54: 0.6 | O54: 0.6 | P54: 0.6 | Q54: 0.6 | R54: 0.6 | S54: 0.6 | T54: 0.6 | U54: 0.6 | V54: 7.2
A55: TW | B55: OMO | C55: Corporation | D55: Corporation | E55: NA | F55: 執行長室 : 客戶價值中心 : 客戶價值中心 | G55: 人事費用 | H55: 陳繼訓 | I55: 二級主管 | J55: 0.4 | K55: 0.4 | L55: 0.4 | M55: 0.4 | N55: 0.4 | O55: 0.4 | P55: 0.4 | Q55: 0.4 | R55: 0.4 | S55: 0.4 | T55: 0.4 | U55: 0.4 | V55: 4.8
A56: TW | B56: POS | C56: Corporation | D56: Corporation | E56: NA | F56: 執行長室 : 客戶價值中心 : 客戶價值中心 | G56: 人事費用 | H56: 林怡儒 | I56: 三級主管 | J56: 0.6 | K56: 0.6 | L56: 0.6 | M56: 0.6 | N56: 0.6 | O56: 0.6 | P56: 0.6 | Q56: 0.6 | R56: 0.6 | S56: 0.6 | T56: 0.6 | U56: 0.6 | V56: 7.2
A57: TW | B57: OMO | C57: Corporation | D57: Corporation | E57: NA | F57: 執行長室 : 客戶價值中心 : 客戶價值中心 | G57: 人事費用 | H57: 林怡儒 | I57: 三級主管 | J57: 0.5 | K57: 0.5 | L57: 0.5 | M57: 0.5 | N57: 0.4 | O57: 0.4 | P57: 0.4 | Q57: 0.4 | R57: 0.4 | S57: 0.4 | T57: 0.4 | U57: 0.4 | V57: 5.2
A58: TW | B58: POS | C58: Corporation | D58: Corporation | E58: NA | F58: 執行長室 : 客戶價值中心 : 客戶價值中心 | G58: 人事費用 | H58: 李菩綾 | I58: 三級主管 | J58: 0.3 | K58: 0.3 | L58: 0.3 | M58: 0.3 | N58: 0.3 | O58: 0.3 | P58: 0.3 | Q58: 0.3 | R58: 0.3 | S58: 0.3 | T58: 0.3 | U58: 0.3 | V58: 3.6
A59: TW | B59: OMO | C59: Corporation | D59: Corporation | E59: NA | F59: 執行長室 : 客戶價值中心 : 客戶價值中心 | G59: 人事費用 | H59: 李菩綾 | I59: 三級主管 | J59: 0.7 | K59: 0.7 | L59: 0.7 | M59: 0.7 | N59: 0.6 | O59: 0.6 | P59: 0.6 | Q59: 0.6 | R59: 0.6 | S59: 0.6 | T59: 0.6 | U59: 0.6 | V59: 7.6

Sheet 維運攤分
A1: 子公司 | B1: 事業單位 | C1: Si 編號 | D1: TA 編號 | E1: 價值鏈專案預算代號 | F1: 費用單位 | G1: 費用類型 | H1: 費用項目 | I1: 備註 | J1: 46023 | K1: 46054 | L1: 46082 | M1: 46113 | N1: 46143 | O1: 46174 | P1: 46204 | Q1: 46235 | R1: 46266 | S1: 46296 | T1: 46327 | U1: 46357 | V1: 2026 year
A2: TW | B2: OMO | C2: Maintenance | D2: Baseline | E2: NA | F2: 執行長室 : 客戶價值中心 : 客戶價值中心 | G2: 非人事費用 | H2: 維運費用分攤 | J2: 82112.04 | K2: 80770.79 | L2: 81927.04 | M2: 81485.82 | N2: 80070.57 | O2: 79376.82 | P2: 81226.82 | Q2: 81411.82 | R2: 81458.07 | S2: 82780.82 | T2: 80070.57 | U2: 81874.32 | V2: 974565.48
A3: TW | B3: POS | C3: Maintenance | D3: Baseline | E3: NA | F3: 執行長室 : 客戶價值中心 : 客戶價值中心 | G3: 非人事費用 | H3: 維運費用分攤 | J3: 1305585.7 | K3: 792426.96 | L3: 803770.71 | M3: 799441.93 | N3: 785557.18 | O3: 778750.93 | P3: 796900.93 | Q3: 798715.93 | R3: 799169.68 | S3: 812146.93 | T3: 785557.18 | U3: 803253.43 | V3: 9561277.5

Sheet 集團攤分
A1: 子公司 | B1: 事業單位 | C1: Si 編號 | D1: TA 編號 | E1: 價值鏈專案預算代號 | F1: 費用單位 | G1: 費用類型 | H1: 費用項目 | I1: 備註 | J1: 46023 | K1: 46054 | L1: 46082 | M1: 46113 | N1: 46143 | O1: 46174 | P1: 46204 | Q1: 46235 | R1: 46266 | S1: 46296 | T1: 46327 | U1: 46357 | V1: 2026 year
A2: TW | B2: OMO | C2: Corporation | D2: Corporation | E2: NA | F2: 執行長室 : 客戶價值中心 : 客戶價值中心 | G2: 非人事費用 | H2: 集團費用分攤 | J2: 31741.47 | K2: 32444.47 | L2: 30631.47 | M2: 37890.68 | N2: 31286.18 | O2: 33753.9 | P2: 35270.9 | Q2: 35270.9 | R2: 31940.9 | S2: 31940.9 | T2: 31940.9 | U2: 31833.78 | V2: 411335.01
A3: TW | B3: POS | C3: Corporation | D3: Corporation | E3: NA | F3: 執行長室 : 客戶價值中心 : 客戶價值中心 | G3: 非人事費用 | H3: 集團費用分攤 | J3: 311409.53 | K3: 318306.53 | L3: 300519.53 | M3: 371738.32 | N3: 306942.82 | O3: 331153.1 | P3: 346036.1 | Q3: 346036.1 | R3: 313366.1 | S3: 313366.1 | T3: 313366.1 | U3: 312315.22 | V3: 4035530
A4: TW | B4: OMO | C4: Corporation | D4: Corporation | E4: NA | F4: 執行長室 : 客戶價值中心 : 客戶價值中心 | G4: 人事費用 | H4: 集團費用分攤 | J4: 446556.98 | K4: 446556.98 | L4: 446556.98 | M4: 446711.18 | N4: 417334.18 | O4: 417488.37 | P4: 417488.37 | Q4: 417488.37 | R4: 417488.37 | S4: 417488.37 | T4: 417488.37 | U4: 417488.37 | V4: 5126520.4
A5: TW | B5: POS | C5: Corporation | D5: Corporation | E5: NA | F5: 執行長室 : 客戶價值中心 : 客戶價值中心 | G5: 人事費用 | H5: 集團費用分攤 | J5: 606064.02 | K5: 606064.02 | L5: 606064.02 | M5: 607576.82 | N5: 607576.82 | O5: 609089.63 | P5: 609089.63 | Q5: 609089.63 | R5: 609089.63 | S5: 609089.63 | T5: 609089.63 | U5: 609089.63 | V5: 7300755.6

Sheet ｜工作區>>>
C1: 46023 | D1: 46054 | E1: 46082 | F1: 46113 | G1: 46143 | H1: 46174 | I1: 46204 | J1: 46235 | K1: 46266 | L1: 46296 | M1: 46327 | N1: 46357
A2: 梁方瑜 | B2: 一級主管 | C2: 1 | D2: 1 | E2: 1 | F2: 1 | G2: 1 | H2: 1 | I2: 1 | J2: 1 | K2: 1 | L2: 1 | M2: 1 | N2: 1
A3: 謝孟娟 | B3: 二級主管 | C3: 1 | D3: 1 | E3: 1 | F3: 1 | G3: 1 | H3: 1 | I3: 1 | J3: 1 | K3: 1 | L3: 1 | M3: 1 | N3: 1
A4: 陳繼訓 | B4: 二級主管 | C4: 1 | D4: 1 | E4: 1 | F4: 1 | G4: 1 | H4: 1 | I4: 1 | J4: 1 | K4: 1 | L4: 1 | M4: 1 | N4: 1
A5: 林怡儒 | B5: 三級主管 | C5: 1 | D5: 1 | E5: 1 | F5: 1 | G5: 1 | H5: 1 | I5: 1 | J5: 1 | K5: 1 | L5: 1 | M5: 1 | N5: 1
A6: 李菩綾 | B6: 三級主管 | C6: 1 | D6: 1 | E6: 1 | F6: 1 | G6: 1 | H6: 1 | I6: 1 | J6: 1 | K6: 1 | L6: 1 | M6: 1 | N6: 1
A7: 周玟萱 | B7: IC 職 | C7: 1 | D7: 1 | E7: 1 | F7: 1 | G7: 1 | H7: 1 | I7: 1 | J7: 1 | K7: 1 | L7: 1 | M7: 1 | N7: 1
A8: 朱肇平 | B8: IC 職 | C8: 1 | D8: 1 | E8: 1 | F8: 1 | G8: 1 | H8: 1 | I8: 1 | J8: 1 | K8: 1 | L8: 1 | M8: 1 | N8: 1
A9: 丁伊柔 | B9: IC 職 | C9: 1 | D9: 1 | E9: 1 | F9: 1 | G9: 1 | H9: 1 | I9: 1 | J9: 1 | K9: 1 | L9: 1 | M9: 1 | N9: 1
A10: 林展甫 | B10: IC 職 | C10: 1 | D10: 1 | E10: 1 | F10: 1 | G10: 1 | H10: 1 | I10: 1 | J10: 1 | K10: 1 | L10: 1 | M10: 1 | N10: 1
A11: 吳芯儀 | B11: IC 職 | C11: 1 | D11: 1 | E11: 1 | F11: 1 | G11: 1 | H11: 1 | I11: 1 | J11: 1 | K11: 1 | L11: 1 | M11: 1 | N11: 1
A12: 戴馨妤 | B12: IC 職 | C12: 1 | D12: 1 | E12: 1 | F12: 1 | G12: 1 | H12: 1 | I12: 1 | J12: 1 | K12: 1 | L12: 1 | M12: 1 | N12: 1
A13: 蔡仲惠 | B13: IC 職 | C13: 1 | D13: 1 | E13: 1 | F13: 1 | G13: 1 | H13: 1 | I13: 1 | J13: 1 | K13: 1 | L13: 1 | M13: 1 | N13: 1
... A18: 周思吟 | B18: IC 職 | C18: 1 | D18: 1 | E18: 1 | F18: 1 | G18: 1 | H18: 1 | I18: 1 | J18: 1 | K18: 1 | L18: 1 | M18: 1 | N18: 1
A19: 陳嘉汶 | B19: IC 職 | C19: NA | D19: NA | E19: NA | F19: NA | G19: NA | H19: 1 | I19: 1 | J19: 1 | K19: 1 | L19: 1 | M19: 1 | N19: 1
A20: 蔡佳玲 | B20: IC 職 | C20: 1 | D20: 1 | E20: 1 | F20: 1 | G20: 1 | H20: 1 | I20: 1 | J20: 1 | K20: 1 | L20: 1 | M20: 1 | N20: 1
A21: 許裴宸 | B21: IC 職 | C21: 1 | D21: 1 | E21: 1 | F21: 1 | G21: 1 | H21: 1 | I21: 1 | J21: 1 | K21: 1 | L21: 1 | M21: 1 | N21: 1
A22: 黃如蘭 | B22: IC 職 | C22: 1 | D22: 1 | E22: 1 | F22: 1 | G22: 1 | H22: 1 | I22: 1 | J22: 1 | K22: 1 | L22: 1 | M22: 1 | N22: 1
A23: 陳馨如 | B23: IC 職 | C23: 1 | D23: 1 | E23: 1 | F23: 1 | G23: 1 | H23: 1 | I23: 1 | J23: 1 | K23: 1 | L23: 1 | M23: 1 | N23: 1
A24: 楊麗涵 | B24: IC 職 | C24: 1 | D24: 1 | E24: 1 | F24: 1 | G24: 1 | H24: 1 | I24: 1 | J24: 1 | K24: 1 | L24: 1 | M24: 1 | N24: 1
A25: 莊媁晨 | B25: IC 職 | C25: 1 | D25: 1 | E25: 1 | F25: 1 | G25: 1 | H25: 1 | I25: 1 | J25: 1 | K25: 1 | L25: 1 | M25: 1 | N25: 1
A26: 劉晏廷 | B26: IC 職 | C26: 1 | D26: 1 | E26: 1 | F26: 1 | G26: 1 | H26: 1 | I26: 1 | J26: 1 | K26: 1 | L26: 1 | M26: 1 | N26: 1
A27: 盧欣妤 | B27: IC 職 | C27: 1 | D27: 1 | E27: 1 | F27: 1 | G27: 1 | H27: 1 | I27: 1 | J27: 1 | K27: 1 | L27: 1 | M27: 1 | N27: 1
A28: 陳怡婷 | B28: IC 職 | C28: 1 | D28: 1 | E28: 1 | F28: 1 | G28: 1 | H28: 1 | I28: 1 | J28: 1 | K28: 1 | L28: 1 | M28: 1 | N28: 1
A29: ( A ) NEW-CS T1 | B29: 新人 | C29: 1 | D29: 1 | E29: 1 | F29: 1 | G29: 1 | H29: 1 | I29: 1 | J29: 1 | K29: 1 | L29: 1 | M29: 1 | N29: 1
A30: ( B ) NEW-CS T1 | B30: 新人 | C30: NA | D30: NA | E30: NA | F30: 1 | G30: 1 | H30: 1 | I30: 1 | J30: 1 | K30: 1 | L30: 1 | M30: 1 | N30: 1
A31: NEW - MS | B31: 新人 | C31: 1 | D31: 1 | E31: 1 | F31: 1 | G31: 1 | H31: 1 | I31: 1 | J31: 1 | K31: 1 | L31: 1 | M31: 1 | N31: 1
B33: 一級主管 | C33: 1 | D33: 1 | E33: 1 | F33: 1 | G33: 1 | H33: 1 | I33: 1 | J33: 1 | K33: 1 | L33: 1 | M33: 1 | N33: 1
B34: 二級主管 | C34: 2 | D34: 2 | E34: 2 | F34: 2 | G34: 2 | H34: 2 | I34: 2 | J34: 2 | K34: 2 | L34: 2 | M34: 2 | N34: 2
B35: 三級主管 | C35: 2 | D35: 2 | E35: 2 | F35: 2 | G35: 2 | H35: 2 | I35: 2 | J35: 2 | K35: 2 | L35: 2 | M35: 2 | N35: 2
B36: IC 職 | C36: =COUNT(C7:C31) -> 23 | D36: =COUNT(D7:D31) -> 23 | E36: =COUNT(E7:E31) -> 23 | F36: =COUNT(F7:F31) -> 24 | G36: =COUNT(G7:G31) -> 24 | H36: =COUNT(H7:H31) -> 25 | I36: =COUNT(I7:I31) -> 25 | J36: =COUNT(J7:J31) -> 25 | ... N36: =COUNT(N7:N31) -> 25
B37: 網訊 | C37: 8 | D37: 8 | E37: 8 | F37: 8 | G37: 8 | H37: 8 | I37: 8 | J37: 8 | K37: 8 | L37: 8 | M37: 8 | N37: 8

Sheet 集團分攤費用表
A1: =IFERROR(__xludf.DUMMYFUNCTION("IMPORTRANGE(""https://docs.google.com/spreadsheets/d/1-YuSlnwICv7dSIIRxQFJU2gwgM9OHTbandHa0RE3CW8/edit?gid=1671067433#gid=1671067433"",""集團共用費用分攤比例!A1:Z100"")"),"子公司") -> 子公司 | B1: =IFERROR(__xludf.DUMMYFUNCTION("""COMPUTED_VALUE"""),"事業單位") -> 事業單位 | C1: =IFERROR(__xludf.DUMMYFUNCTION("""COMPUTED_VALUE"""),"2025/01-09 營收") -> 2025/01-09 營收 | D1: =IFERROR(__xludf.DUMMYFUNCTION("""COMPUTED_VALUE"""),"2025/01-09 營收占比") -> 2025/01-09 營收占比 | E1: =IFERROR(__xludf.DUMMYFUNCTION("""COMPUTED_VALUE"""),"含 QLR") -> 含 QLR | F1: =IFERROR(__xludf.DUMMYFUNCTION("""COMPUTED_VALUE"""),"不含 QLR") -> 不含 QLR
C2: =IFERROR(__xludf.DUMMYFUNCTION("""COMPUTED_VALUE"""),3.8659835712E8) -> 3.8659836e+08 | D2: =IFERROR(__xludf.DUMMYFUNCTION("""COMPUTED_VALUE"""),1.0) -> 1 | E2: =IFERROR(__xludf.DUMMYFUNCTION("""COMPUTED_VALUE"""),"集團分攤：iCHEF 管理中心、iCHEF 財務中心、iCHEF 策略資料中心 的人事費用與非人事費用") -> 集團分攤：iCHEF 管理中心、iCHEF 財務中心、iCHEF 策略資料中心 的人事費用與非人事費用 | F2: =IFERROR(__xludf.DUMMYFUNCTION("""COMPUTED_VALUE"""),"集團分攤：iCHEF 研發中心、iCHEF 行銷營運中心、iCHEF 客戶價值中心 的事業單位 Corporation、Si Corporation 人事費用與非人事費用 維運分攤：iCHEF 研發中心、iCHEF 行銷營運中心、iCHEF 客戶價值中心 的事業單位 Corporation Si Maintenance 人事費用與非人事費用") -> 集團分攤：iCHEF 研發中心、iCHEF 行銷營運中心、iCHEF 客戶價值中心 的事業單位 Corporation、Si Corporation 人事費用與非人事費用 維運分攤：iCHEF 研發中心、iCHEF 行銷營運中心、iCHEF 客戶價值中心 的事業單位 Corporation Si Maintenance 人事費用與非人事費用
A3: =IFERROR(__xludf.DUMMYFUNCTION("""COMPUTED_VALUE"""),"TW") -> TW | B3: =IFERROR(__xludf.DUMMYFUNCTION("""COMPUTED_VALUE"""),"OMO") -> OMO | C3: =IFERROR(__xludf.DUMMYFUNCTION("""COMPUTED_VALUE"""),3.4158435E7) -> 34158435 | D3: =IFERROR(__xludf.DUMMYFUNCTION("""COMPUTED_VALUE"""),0.08835638944372759) -> 0.088356389 | E3: =IFERROR(__xludf.DUMMYFUNCTION("""COMPUTED_VALUE"""),0.0884) -> 0.0884 | F3: =IFERROR(__xludf.DUMMYFUNCTION("""COMPUTED_VALUE"""),0.0925) -> 0.0925
A4: =IFERROR(__xludf.DUMMYFUNCTION("""COMPUTED_VALUE"""),"TW") -> TW | B4: =IFERROR(__xludf.DUMMYFUNCTION("""COMPUTED_VALUE"""),"POS") -> POS | C4: =IFERROR(__xludf.DUMMYFUNCTION("""COMPUTED_VALUE"""),3.3499497812E8) -> 3.3499498e+08 | D4: =IFERROR(__xludf.DUMMYFUNCTION("""COMPUTED_VALUE"""),0.8665194043129824) -> 0.8665194 | E4: =IFERROR(__xludf.DUMMYFUNCTION("""COMPUTED_VALUE"""),0.8665) -> 0.8665 | F4: =IFERROR(__xludf.DUMMYFUNCTION("""COMPUTED_VALUE"""),0.9075) -> 0.9075
A5: =IFERROR(__xludf.DUMMYFUNCTION("""COMPUTED_VALUE"""),"QLR") -> QLR | B5: =IFERROR(__xludf.DUMMYFUNCTION("""COMPUTED_VALUE"""),"OMO") -> OMO | C5: =IFERROR(__xludf.DUMMYFUNCTION("""COMPUTED_VALUE"""),1.7444944E7) -> 17444944 | D5: =IFERROR(__xludf.DUMMYFUNCTION("""COMPUTED_VALUE"""),0.0451242062432901) -> 0.045124206 | E5: =IFERROR(__xludf.DUMMYFUNCTION("""COMPUTED_VALUE"""),0.0451) -> 0.0451

Sheet 共通費用參考資料
B1: =IFERROR(__xludf.DUMMYFUNCTION("IMPORTRANGE(""https://docs.google.com/spreadsheets/d/1fiD6EDAkov9pRwQ_8sXhwmAj-vJoUCNKTRov_ZiHklw/edit?gid=1913353331#gid=1913353331"",""2026 定版資料!A1:Z"")"),"#") -> # | C1: =IFERROR(__xludf.DUMMYFUNCTION("""COMPUTED_VALUE"""),"費用類型") -> 費用類型 | D1: =IFERROR(__xludf.DUMMYFUNCTION("""COMPUTED_VALUE"""),"子公司") -> 子公司 | E1: =IFERROR(__xludf.DUMMYFUNCTION("""COMPUTED_VALUE"""),"會科代號") -> 會科代號 | F1: =IFERROR(__xludf.DUMMYFUNCTION("""COMPUTED_VALUE"""),"會計科目") -> 會計科目 | G1: =IFERROR(__xludf.DUMMYFUNCTION("""COMPUTED_VALUE"""),"明細科目") -> 明細科目 | H1: =IFERROR(__xludf.DUMMYFUNCTION("""COMPUTED_VALUE"""),"說明") -> 說明 | I1: =IFERROR(__xludf.DUMMYFUNCTION("""COMPUTED_VALUE"""),"月 額度 (每人)") -> 月 額度 (每人) | J1: =IFERROR(__xludf.DUMMYFUNCTION("""COMPUTED_VALUE"""),"年 額度 (每人)") -> 年 額度 (每人) | K1: =IFERROR(__xludf.DUMMYFUNCTION("""COMPUTED_VALUE"""),"預算編製、計算單位") -> 預算編製、計算單位 | L1: =IFERROR(__xludf.DUMMYFUNCTION("""COMPUTED_VALUE"""),"預算歸屬單位") -> 預算歸屬單位 | M1: =IFERROR(__xludf.DUMMYFUNCTION("""COMPUTED_VALUE"""),"備註") -> 備註
B2: =IFERROR(__xludf.DUMMYFUNCTION("""COMPUTED_VALUE"""),1.0) -> 1 | C2: =IFERROR(__xludf.DUMMYFUNCTION("""COMPUTED_VALUE"""),"人事費用") -> 人事費用 | D2: =IFERROR(__xludf.DUMMYFUNCTION("""COMPUTED_VALUE"""),"iCHEF+QLR") -> iCHEF+QLR | E2: =IFERROR(__xludf.DUMMYFUNCTION("""COMPUTED_VALUE"""),"6x1001") -> 6x1001 | F2: =IFERROR(__xludf.DUMMYFUNCTION("""COMPUTED_VALUE"""),"薪資費用") -> 薪資費用 | G2: =IFERROR(__xludf.DUMMYFUNCTION("""COMPUTED_VALUE"""),"本薪") -> 本薪 | H2: =IFERROR(__xludf.DUMMYFUNCTION("""COMPUTED_VALUE"""),"薪資") -> 薪資 | K2: =IFERROR(__xludf.DUMMYFUNCTION("""COMPUTED_VALUE"""),"管理中心提供薪資，各專業中心依人員配置編列") -> 管理中心提供薪資，各專業中心依人員配置編列 | L2: =IFERROR(__xludf.DUMMYFUNCTION("""COMPUTED_VALUE"""),"各專業中心") -> 各專業中心 | M2: =IFERROR(__xludf.DUMMYFUNCTION("""COMPUTED_VALUE"""),"金額由 HR 計算") -> 金額由 HR 計算
B3: =IFERROR(__xludf.DUMMYFUNCTION("""COMPUTED_VALUE"""),2.0) -> 2 | C3: =IFERROR(__xludf.DUMMYFUNCTION("""COMPUTED_VALUE"""),"人事費用") -> 人事費用 | D3: =IFERROR(__xludf.DUMMYFUNCTION("""COMPUTED_VALUE"""),"iCHEF+QLR") -> iCHEF+QLR | E3: =IFERROR(__xludf.DUMMYFUNCTION("""COMPUTED_VALUE"""),"6x27") -> 6x27 | F3: =IFERROR(__xludf.DUMMYFUNCTION("""COMPUTED_VALUE"""),"伙食費") -> 伙食費 | G3: =IFERROR(__xludf.DUMMYFUNCTION("""COMPUTED_VALUE"""),"伙食費") -> 伙食費 | H3: =IFERROR(__xludf.DUMMYFUNCTION("""COMPUTED_VALUE"""),"伙食費") -> 伙食費 | K3: =IFERROR(__xludf.DUMMYFUNCTION("""COMPUTED_VALUE"""),"管理中心提供薪資，各專業中心依人員配置編列") -> 管理中心提供薪資，各專業中心依人員配置編列 | L3: =IFERROR(__xludf.DUMMYFUNCTION("""COMPUTED_VALUE"""),"各專業中心") -> 各專業中心 | M3: =IFERROR(__xludf.DUMMYFUNCTION("""COMPUTED_VALUE"""),"金額由 HR 計算") -> 金額由 HR 計算
B4: =IFERROR(__xludf.DUMMYFUNCTION("""COMPUTED_VALUE"""),3.0) -> 3 | C4: =IFERROR(__xludf.DUMMYFUNCTION("""COMPUTED_VALUE"""),"人事費用") -> 人事費用 | D4: =IFERROR(__xludf.DUMMYFUNCTION("""COMPUTED_VALUE"""),"iCHEF+QLR") -> iCHEF+QLR | E4: =IFERROR(__xludf.DUMMYFUNCTION("""COMPUTED_VALUE"""),"6x1009") -> 6x1009 | F4: =IFERROR(__xludf.DUMMYFUNCTION("""COMPUTED_VALUE"""),"薪資費用") -> 薪資費用 | G4: =IFERROR(__xludf.DUMMYFUNCTION("""COMPUTED_VALUE"""),"主管津貼") -> 主管津貼 | H4: =IFERROR(__xludf.DUMMYFUNCTION("""COMPUTED_VALUE"""),"主管津貼") -> 主管津貼 | K4: =IFERROR(__xludf.DUMMYFUNCTION("""COMPUTED_VALUE"""),"管理中心提供薪資，各專業中心依人員配置編列") -> 管理中心提供薪資，各專業中心依人員配置編列 | L4: =IFERROR(__xludf.DUMMYFUNCTION("""COMPUTED_VALUE"""),"各專業中心") -> 各專業中心 | M4: =IFERROR(__xludf.DUMMYFUNCTION("""COMPUTED_VALUE"""),"金額由 HR 計算") -> 金額由 HR 計算
B5: =IFERROR(__xludf.DUMMYFUNCTION("""COMPUTED_VALUE"""),4.0) -> 4 | C5: =IFERROR(__xludf.DUMMYFUNCTION("""COMPUTED_VALUE"""),"人事費用") -> 人事費用 | D5: =IFERROR(__xludf.DUMMYFUNCTION("""COMPUTED_VALUE"""),"iCHEF+QLR") -> iCHEF+QLR | E5: =IFERROR(__xludf.DUMMYFUNCTION("""COMPUTED_VALUE"""),"6x1003") -> 6x1003 | F5: =IFERROR(__xludf.DUMMYFUNCTION("""COMPUTED_VALUE"""),"薪資費用") -> 薪資費用 | G5: =IFERROR(__xludf.DUMMYFUNCTION("""COMPUTED_VALUE"""),"加班費") -> 加班費 | H5: =IFERROR(__xludf.DUMMYFUNCTION("""COMPUTED_VALUE"""),"加班費") -> 加班費 | K5: =IFERROR(__xludf.DUMMYFUNCTION("""COMPUTED_VALUE"""),"管理中心提供薪資，各專業中心依人員配置編列") -> 管理中心提供薪資，各專業中心依人員配置編列 | L5: =IFERROR(__xludf.DUMMYFUNCTION("""COMPUTED_VALUE"""),"各專業中心") -> 各專業中心 | M5: =IFERROR(__xludf.DUMMYFUNCTION("""COMPUTED_VALUE"""),"金額由 HR 計算") -> 金額由 HR 計算
B6: =IFERROR(__xludf.DUMMYFUNCTION("""COMPUTED_VALUE"""),5.0) -> 5 | C6: =IFERROR(__xludf.DUMMYFUNCTION("""COMPUTED_VALUE"""),"人事費用") -> 人事費用 | D6: =IFERROR(__xludf.DUMMYFUNCTION("""COMPUTED_VALUE"""),"iCHEF+QLR") -> iCHEF+QLR | E6: =IFERROR(__xludf.DUMMYFUNCTION("""COMPUTED_VALUE"""),"6x1004") -> 6x1004 | F6: =IFERROR(__xludf.DUMMYFUNCTION("""COMPUTED_VALUE"""),"薪資費用") -> 薪資費用 | G6: =IFERROR(__xludf.DUMMYFUNCTION("""COMPUTED_VALUE"""),"退休金") -> 退休金 | H6: =IFERROR(__xludf.DUMMYFUNCTION("""COMPUTED_VALUE"""),"退休金") -> 退休金 | K6: =IFERROR(__xludf.DUMMYFUNCTION("""COMPUTED_VALUE"""),"管理中心提供薪資，各專業中心依人員配置編列") -> 管理中心提供薪資，各專業中心依人員配置編列 | L6: =IFERROR(__xludf.DUMMYFUNCTION("""COMPUTED_VALUE"""),"各專業中心") -> 各專業中心 | M6: =IFERROR(__xludf.DUMMYFUNCTION("""COMPUTED_VALUE"""),"金額由 HR 計算") -> 金額由 HR 計算
B7: =IFERROR(__xludf.DUMMYFUNCTION("""COMPUTED_VALUE"""),6.0) -> 6 | C7: =IFERROR(__xludf.DUMMYFUNCTION("""COMPUTED_VALUE"""),"人事費用") -> 人事費用 | D7: =IFERROR(__xludf.DUMMYFUNCTION("""COMPUTED_VALUE"""),"iCHEF+QLR") -> iCHEF+QLR | E7: =IFERROR(__xludf.DUMMYFUNCTION("""COMPUTED_VALUE"""),"6x1901") -> 6x1901 | F7: =IFERROR(__xludf.DUMMYFUNCTION("""COMPUTED_VALUE"""),"保險費") -> 保險費 | G7: =IFERROR(__xludf.DUMMYFUNCTION("""COMPUTED_VALUE"""),"健保費") -> 健保費 | H7: =IFERROR(__xludf.DUMMYFUNCTION("""COMPUTED_VALUE"""),"健保費") -> 健保費 | K7: =IFERROR(__xludf.DUMMYFUNCTION("""COMPUTED_VALUE"""),"管理中心提供薪資，各專業中心依人員配置編列") -> 管理中心提供薪資，各專業中心依人員配置編列 | L7: =IFERROR(__xludf.DUMMYFUNCTION("""COMPUTED_VALUE"""),"各專業中心") -> 各專業中心 | M7: =IFERROR(__xludf.DUMMYFUNCTION("""COMPUTED_VALUE"""),"金額由 HR 計算") -> 金額由 HR 計算
B8: =IFERROR(__xludf.DUMMYFUNCTION("""COMPUTED_VALUE"""),7.0) -> 7 | C8: =IFERROR(__xludf.DUMMYFUNCTION("""COMPUTED_VALUE"""),"人事費用") -> 人事費用 | D8: =IFERROR(__xludf.DUMMYFUNCTION("""COMPUTED_VALUE"""),"iCHEF+QLR") -> iCHEF+QLR | E8: =IFERROR(__xludf.DUMMYFUNCTION("""COMPUTED_VALUE"""),"6x1902") -> 6x1902 | F8: =IFERROR(__xludf.DUMMYFUNCTION("""COMPUTED_VALUE"""),"保險費") -> 保險費 | G8: =IFERROR(__xludf.DUMMYFUNCTION("""COMPUTED_VALUE"""),"勞保費") -> 勞保費 | H8: =IFERROR(__xludf.DUMMYFUNCTION("""COMPUTED_VALUE"""),"勞保費") -> 勞保費 | K8: =IFERROR(__xludf.DUMMYFUNCTION("""COMPUTED_VALUE"""),"管理中心提供薪資，各專業中心依人員配置編列") -> 管理中心提供薪資，各專業中心依人員配置編列 | L8: =IFERROR(__xludf.DUMMYFUNCTION("""COMPUTED_VALUE"""),"各專業中心") -> 各專業中心 | M8: =IFERROR(__xludf.DUMMYFUNCTION("""COMPUTED_VALUE"""),"金額由 HR 計算") -> 金額由 HR 計算
B9: =IFERROR(__xludf.DUMMYFUNCTION("""COMPUTED_VALUE"""),8.0) -> 8 | C9: =IFERROR(__xludf.DUMMYFUNCTION("""COMPUTED_VALUE"""),"人事費用") -> 人事費用 | D9: =IFERROR(__xludf.DUMMYFUNCTION("""COMPUTED_VALUE"""),"iCHEF+QLR") -> iCHEF+QLR | E9: =IFERROR(__xludf.DUMMYFUNCTION("""COMPUTED_VALUE"""),"6x1005") -> 6x1005 | F9: =IFERROR(__xludf.DUMMYFUNCTION("""COMPUTED_VALUE"""),"薪資費用") -> 薪資費用 | G9: =IFERROR(__xludf.DUMMYFUNCTION("""COMPUTED_VALUE"""),"年終獎金") -> 年終獎金 | H9: =IFERROR(__xludf.DUMMYFUNCTION("""COMPUTED_VALUE"""),"第十三個月") -> 第十三個月 | K9: =IFERROR(__xludf.DUMMYFUNCTION("""COMPUTED_VALUE"""),"管理中心提供薪資，各專業中心依人員配置編列") -> 管理中心提供薪資，各專業中心依人員配置編列 | L9: =IFERROR(__xludf.DUMMYFUNCTION("""COMPUTED_VALUE"""),"各專業中心") -> 各專業中心 | M9: =IFERROR(__xludf.DUMMYFUNCTION("""COMPUTED_VALUE"""),"金額由 HR 計算") -> 金額由 HR 計算
B10: =IFERROR(__xludf.DUMMYFUNCTION("""COMPUTED_VALUE"""),9.0) -> 9 | C10: =IFERROR(__xludf.DUMMYFUNCTION("""COMPUTED_VALUE"""),"人事費用") -> 人事費用 | D10: =IFERROR(__xludf.DUMMYFUNCTION("""COMPUTED_VALUE"""),"iCHEF+QLR") -> iCHEF+QLR | E10: =IFERROR(__xludf.DUMMYFUNCTION("""COMPUTED_VALUE"""),"6x1006") -> 6x1006 | F10: =IFERROR(__xludf.DUMMYFUNCTION("""COMPUTED_VALUE"""),"薪資費用") -> 薪資費用 | G10: =IFERROR(__xludf.DUMMYFUNCTION("""COMPUTED_VALUE"""),"績效獎金") -> 績效獎金 | H10: =IFERROR(__xludf.DUMMYFUNCTION("""COMPUTED_VALUE"""),"團隊層級獎金 - IC職") -> 團隊層級獎金 - IC職 | I10: =IFERROR(__xludf.DUMMYFUNCTION("""COMPUTED_VALUE"""),1667.0) -> 1667 | J10: =IFERROR(__xludf.DUMMYFUNCTION("""COMPUTED_VALUE"""),20000.0) -> 20000 | K10: =IFERROR(__xludf.DUMMYFUNCTION("""COMPUTED_VALUE"""),"各專業中心") -> 各專業中心 | L10: =IFERROR(__xludf.DUMMYFUNCTION("""COMPUTED_VALUE"""),"各專業中心") -> 各專業中心
B11: =IFERROR(__xludf.DUMMYFUNCTION("""COMPUTED_VALUE"""),10.0) -> 10 | C11: =IFERROR(__xludf.DUMMYFUNCTION("""COMPUTED_VALUE"""),"人事費用") -> 人事費用 | D11: =IFERROR(__xludf.DUMMYFUNCTION("""COMPUTED_VALUE"""),"iCHEF+QLR") -> iCHEF+QLR | E11: =IFERROR(__xludf.DUMMYFUNCTION("""COMPUTED_VALUE"""),"6x1006") -> 6x1006 | F11: =IFERROR(__xludf.DUMMYFUNCTION("""COMPUTED_VALUE"""),"薪資費用") -> 薪資費用 | G11: =IFERROR(__xludf.DUMMYFUNCTION("""COMPUTED_VALUE"""),"績效獎金") -> 績效獎金 | H11: =IFERROR(__xludf.DUMMYFUNCTION("""COMPUTED_VALUE"""),"團隊層級獎金 - 一級主管") -> 團隊層級獎金 - 一級主管 | I11: =IFERROR(__xludf.DUMMYFUNCTION("""COMPUTED_VALUE"""),500.0) -> 500 | J11: =IFERROR(__xludf.DUMMYFUNCTION("""COMPUTED_VALUE"""),6000.0) -> 6000 | K11: =IFERROR(__xludf.DUMMYFUNCTION("""COMPUTED_VALUE"""),"各專業中心") -> 各專業中心 | L11: =IFERROR(__xludf.DUMMYFUNCTION("""COMPUTED_VALUE"""),"各專業中心") -> 各專業中心
B12: =IFERROR(__xludf.DUMMYFUNCTION("""COMPUTED_VALUE"""),11.0) -> 11 | C12: =IFERROR(__xludf.DUMMYFUNCTION("""COMPUTED_VALUE"""),"人事費用") -> 人事費用 | D12: =IFERROR(__xludf.DUMMYFUNCTION("""COMPUTED_VALUE"""),"iCHEF+QLR") -> iCHEF+QLR | E12: =IFERROR(__xludf.DUMMYFUNCTION("""COMPUTED_VALUE"""),"6x1006") -> 6x1006 | F12: =IFERROR(__xludf.DUMMYFUNCTION("""COMPUTED_VALUE"""),"薪資費用") -> 薪資費用 | G12: =IFERROR(__xludf.DUMMYFUNCTION("""COMPUTED_VALUE"""),"績效獎金") -> 績效獎金 | H12: =IFERROR(__xludf.DUMMYFUNCTION("""COMPUTED_VALUE"""),"團隊層級獎金 - 二級主管") -> 團隊層級獎金 - 二級主管 | I12: =IFERROR(__xludf.DUMMYFUNCTION("""COMPUTED_VALUE"""),834.0) -> 834 | J12: =IFERROR(__xludf.DUMMYFUNCTION("""COMPUTED_VALUE"""),10000.0) -> 10000 | K12: =IFERROR(__xludf.DUMMYFUNCTION("""COMPUTED_VALUE"""),"各專業中心") -> 各專業中心 | L12: =IFERROR(__xludf.DUMMYFUNCTION("""COMPUTED_VALUE"""),"各專業中心") -> 各專業中心
B13: =IFERROR(__xludf.DUMMYFUNCTION("""COMPUTED_VALUE"""),12.0) -> 12 | C13: =IFERROR(__xludf.DUMMYFUNCTION("""COMPUTED_VALUE"""),"人事費用") -> 人事費用 | D13: =IFERROR(__xludf.DUMMYFUNCTION("""COMPUTED_VALUE"""),"iCHEF+QLR") -> iCHEF+QLR | E13: =IFERROR(__xludf.DUMMYFUNCTION("""COMPUTED_VALUE"""),"6x1006") -> 6x1006 | F13: =IFERROR(__xludf.DUMMYFUNCTION("""COMPUTED_VALUE"""),"薪資費用") -> 薪資費用 | G13: =IFERROR(__xludf.DUMMYFUNCTION("""COMPUTED_VALUE"""),"績效獎金") -> 績效獎金 | H13: =IFERROR(__xludf.DUMMYFUNCTION("""COMPUTED_VALUE"""),"團隊層級獎金 - 三級主管") -> 團隊層級獎金 - 三級主管 | I13: =IFERROR(__xludf.DUMMYFUNCTION("""COMPUTED_VALUE"""),1167.0) -> 1167 | J13: =IFERROR(__xludf.DUMMYFUNCTION("""COMPUTED_VALUE"""),14000.0) -> 14000 | K13: =IFERROR(__xludf.DUMMYFUNCTION("""COMPUTED_VALUE"""),"各專業中心") -> 各專業中心 | L13: =IFERROR(__xludf.DUMMYFUNCTION("""COMPUTED_VALUE"""),"各專業中心") -> 各專業中心
B14: =IFERROR(__xludf.DUMMYFUNCTION("""COMPUTED_VALUE"""),13.0) -> 13 | C14: =IFERROR(__xludf.DUMMYFUNCTION("""COMPUTED_VALUE"""),"人事費用") -> 人事費用 | D14: =IFERROR(__xludf.DUMMYFUNCTION("""COMPUTED_VALUE"""),"iCHEF+QLR") -> iCHEF+QLR | E14: =IFERROR(__xludf.DUMMYFUNCTION("""COMPUTED_VALUE"""),"6x1095") -> 6x1095 | F14: =IFERROR(__xludf.DUMMYFUNCTION("""COMPUTED_VALUE"""),"薪資費用") -> 薪資費用 | G14: =IFERROR(__xludf.DUMMYFUNCTION("""COMPUTED_VALUE"""),"公司層級獎金") -> 公司層級獎金 | H14: =IFERROR(__xludf.DUMMYFUNCTION("""COMPUTED_VALUE"""),"公司層級獎金") -> 公司層級獎金 | J14: =IFERROR(__xludf.DUMMYFUNCTION("""COMPUTED_VALUE"""),"2.5% of ARR") -> 2.5% of ARR | K14: =IFERROR(__xludf.DUMMYFUNCTION("""COMPUTED_VALUE"""),"CEO") -> CEO | L14: =IFERROR(__xludf.DUMMYFUNCTION("""COMPUTED_VALUE"""),"CEO") -> CEO
B15: =IFERROR(__xludf.DUMMYFUNCTION("""COMPUTED_VALUE"""),14.0) -> 14 | C15: =IFERROR(__xludf.DUMMYFUNCTION("""COMPUTED_VALUE"""),"非人事費用") -> 非人事費用 | D15: =IFERROR(__xludf.DUMMYFUNCTION("""COMPUTED_VALUE"""),"iCHEF") -> iCHEF | E15: =IFERROR(__xludf.DUMMYFUNCTION("""COMPUTED_VALUE"""),"6x3299") -> 6x3299 | F15: =IFERROR(__xludf.DUMMYFUNCTION("""COMPUTED_VALUE"""),"其他費用") -> 其他費用 | G15: =IFERROR(__xludf.DUMMYFUNCTION("""COMPUTED_VALUE"""),"其他") -> 其他 | H15: =IFERROR(__xludf.DUMMYFUNCTION("""COMPUTED_VALUE"""),"季度聚餐") -> 季度聚餐 | I15: =IFERROR(__xludf.DUMMYFUNCTION("""COMPUTED_VALUE"""),334.0) -> 334 | J15: =IFERROR(__xludf.DUMMYFUNCTION("""COMPUTED_VALUE"""),4000.0) -> 4000 | K15: =IFERROR(__xludf.DUMMYFUNCTION("""COMPUTED_VALUE"""),"各專業中心") -> 各專業中心 | L15: =IFERROR(__xludf.DUMMYFUNCTION("""COMPUTED_VALUE"""),"各專業中心") -> 各專業中心
B16: =IFERROR(__xludf.DUMMYFUNCTION("""COMPUTED_VALUE"""),15.0) -> 15 | C16: =IFERROR(__xludf.DUMMYFUNCTION("""COMPUTED_VALUE"""),"非人事費用") -> 非人事費用 | D16: =IFERROR(__xludf.DUMMYFUNCTION("""COMPUTED_VALUE"""),"QLR") -> QLR | E16: =IFERROR(__xludf.DUMMYFUNCTION("""COMPUTED_VALUE"""),"6x3299") -> 6x3299 | F16: =IFERROR(__xludf.DUMMYFUNCTION("""COMPUTED_VALUE"""),"其他費用") -> 其他費用 | G16: =IFERROR(__xludf.DUMMYFUNCTION("""COMPUTED_VALUE"""),"其他") -> 其他 | H16: =IFERROR(__xludf.DUMMYFUNCTION("""COMPUTED_VALUE"""),"體驗基金") -> 體驗基金 | I16: =IFERROR(__xludf.DUMMYFUNCTION("""COMPUTED_VALUE"""),334.0) -> 334 | J16: =IFERROR(__xludf.DUMMYFUNCTION("""COMPUTED_VALUE"""),4000.0) -> 4000 | K16: =IFERROR(__xludf.DUMMYFUNCTION("""COMPUTED_VALUE"""),"各專業中心") -> 各專業中心 | L16: =IFERROR(__xludf.DUMMYFUNCTION("""COMPUTED_VALUE"""),"各專業中心") -> 各專業中心
B17: =IFERROR(__xludf.DUMMYFUNCTION("""COMPUTED_VALUE"""),16.0) -> 16 | C17: =IFERROR(__xludf.DUMMYFUNCTION("""COMPUTED_VALUE"""),"非人事費用") -> 非人事費用 | D17: =IFERROR(__xludf.DUMMYFUNCTION("""COMPUTED_VALUE"""),"iCHEF") -> iCHEF | E17: =IFERROR(__xludf.DUMMYFUNCTION("""COMPUTED_VALUE"""),"613299 612999") -> 613299 612999 | F17: =IFERROR(__xludf.DUMMYFUNCTION("""COMPUTED_VALUE"""),"其他費用 勞務費") -> 其他費用 勞務費 | G17: =IFERROR(__xludf.DUMMYFUNCTION("""COMPUTED_VALUE"""),"其他 其他") -> 其他 其他 | H17: =IFERROR(__xludf.DUMMYFUNCTION("""COMPUTED_VALUE"""),"健康檢查 (在職滿一年)") -> 健康檢查 (在職滿一年) | I17: =IFERROR(__xludf.DUMMYFUNCTION("""COMPUTED_VALUE"""),250.0) -> 250 | J17: =IFERROR(__xludf.DUMMYFUNCTION("""COMPUTED_VALUE"""),3000.0) -> 3000 | K17: =IFERROR(__xludf.DUMMYFUNCTION("""COMPUTED_VALUE"""),"各專業中心") -> 各專業中心 | L17: =IFERROR(__xludf.DUMMYFUNCTION("""COMPUTED_VALUE"""),"各專業中心") -> 各專業中心
B18: =IFERROR(__xludf.DUMMYFUNCTION("""COMPUTED_VALUE"""),17.0) -> 17 | C18: =IFERROR(__xludf.DUMMYFUNCTION("""COMPUTED_VALUE"""),"非人事費用") -> 非人事費用 | D18: =IFERROR(__xludf.DUMMYFUNCTION("""COMPUTED_VALUE"""),"iCHEF") -> iCHEF | E18: =IFERROR(__xludf.DUMMYFUNCTION("""COMPUTED_VALUE"""),"6x19") -> 6x19 | F18: =IFERROR(__xludf.DUMMYFUNCTION("""COMPUTED_VALUE"""),"保險費") -> 保險費 | G18: =IFERROR(__xludf.DUMMYFUNCTION("""COMPUTED_VALUE"""),"團體保險") -> 團體保險 | H18: =IFERROR(__xludf.DUMMYFUNCTION("""COMPUTED_VALUE"""),"團體保險") -> 團體保險 | I18: =IFERROR(__xludf.DUMMYFUNCTION("""COMPUTED_VALUE"""),135.0) -> 135 | J18: =IFERROR(__xludf.DUMMYFUNCTION("""COMPUTED_VALUE"""),1625.0) -> 1625 | K18: =IFERROR(__xludf.DUMMYFUNCTION("""COMPUTED_VALUE"""),"各專業中心") -> 各專業中心 | L18: =IFERROR(__xludf.DUMMYFUNCTION("""COMPUTED_VALUE"""),"各專業中心") -> 各專業中心
B19: =IFERROR(__xludf.DUMMYFUNCTION("""COMPUTED_VALUE"""),18.0) -> 18 | C19: =IFERROR(__xludf.DUMMYFUNCTION("""COMPUTED_VALUE"""),"非人事費用") -> 非人事費用 | D19: =IFERROR(__xludf.DUMMYFUNCTION("""COMPUTED_VALUE"""),"iCHEF") -> iCHEF | E19: =IFERROR(__xludf.DUMMYFUNCTION("""COMPUTED_VALUE"""),"6x20") -> 6x20 | F19: =IFERROR(__xludf.DUMMYFUNCTION("""COMPUTED_VALUE"""),"交際費") -> 交際費 | G19: =IFERROR(__xludf.DUMMYFUNCTION("""COMPUTED_VALUE"""),"交際費") -> 交際費 | H19: =IFERROR(__xludf.DUMMYFUNCTION("""COMPUTED_VALUE"""),"交際費 (CEO)") -> 交際費 (CEO) | I19: =IFERROR(__xludf.DUMMYFUNCTION("""COMPUTED_VALUE"""),10000.0) -> 10000 | J19: =IFERROR(__xludf.DUMMYFUNCTION("""COMPUTED_VALUE"""),120000.0) -> 120000 | K19: =IFERROR(__xludf.DUMMYFUNCTION("""COMPUTED_VALUE"""),"各專業中心") -> 各專業中心 | L19: =IFERROR(__xludf.DUMMYFUNCTION("""COMPUTED_VALUE"""),"各專業中心") -> 各專業中心
B20: =IFERROR(__xludf.DUMMYFUNCTION("""COMPUTED_VALUE"""),19.0) -> 19 | C20: =IFERROR(__xludf.DUMMYFUNCTION("""COMPUTED_VALUE"""),"非人事費用") -> 非人事費用 | D20: =IFERROR(__xludf.DUMMYFUNCTION("""COMPUTED_VALUE"""),"iCHEF+QLR") -> iCHEF+QLR | E20: =IFERROR(__xludf.DUMMYFUNCTION("""COMPUTED_VALUE"""),"6x20") -> 6x20 | F20: =IFERROR(__xludf.DUMMYFUNCTION("""COMPUTED_VALUE"""),"交際費") -> 交際費 | G20: =IFERROR(__xludf.DUMMYFUNCTION("""COMPUTED_VALUE"""),"交際費") -> 交際費 | H20: =IFERROR(__xludf.DUMMYFUNCTION("""COMPUTED_VALUE"""),"交際費 (一級主管)") -> 交際費 (一級主管) | I20: =IFERROR(__xludf.DUMMYFUNCTION("""COMPUTED_VALUE"""),8000.0) -> 8000 | J20: =IFERROR(__xludf.DUMMYFUNCTION("""COMPUTED_VALUE"""),96000.0) -> 96000 | K20: =IFERROR(__xludf.DUMMYFUNCTION("""COMPUTED_VALUE"""),"各專業中心") -> 各專業中心 | L20: =IFERROR(__xludf.DUMMYFUNCTION("""COMPUTED_VALUE"""),"各專業中心") -> 各專業中心
B21: =IFERROR(__xludf.DUMMYFUNCTION("""COMPUTED_VALUE"""),20.0) -> 20 | C21: =IFERROR(__xludf.DUMMYFUNCTION("""COMPUTED_VALUE"""),"非人事費用") -> 非人事費用 | D21: =IFERROR(__xludf.DUMMYFUNCTION("""COMPUTED_VALUE"""),"iCHEF+QLR") -> iCHEF+QLR | E21: =IFERROR(__xludf.DUMMYFUNCTION("""COMPUTED_VALUE"""),"6x20") -> 6x20 | F21: =IFERROR(__xludf.DUMMYFUNCTION("""COMPUTED_VALUE"""),"交際費") -> 交際費 | G21: =IFERROR(__xludf.DUMMYFUNCTION("""COMPUTED_VALUE"""),"交際費") -> 交際費 | H21: =IFERROR(__xludf.DUMMYFUNCTION("""COMPUTED_VALUE"""),"交際費 (二級主管)") -> 交際費 (二級主管) | I21: =IFERROR(__xludf.DUMMYFUNCTION("""COMPUTED_VALUE"""),3000.0) -> 3000 | J21: =IFERROR(__xludf.DUMMYFUNCTION("""COMPUTED_VALUE"""),36000.0) -> 36000 | K21: =IFERROR(__xludf.DUMMYFUNCTION("""COMPUTED_VALUE"""),"各專業中心") -> 各專業中心 | L21: =IFERROR(__xludf.DUMMYFUNCTION("""COMPUTED_VALUE"""),"各專業中心") -> 各專業中心
B22: =IFERROR(__xludf.DUMMYFUNCTION("""COMPUTED_VALUE"""),21.0) -> 21 | C22: =IFERROR(__xludf.DUMMYFUNCTION("""COMPUTED_VALUE"""),"非人事費用") -> 非人事費用 | D22: =IFERROR(__xludf.DUMMYFUNCTION("""COMPUTED_VALUE"""),"iCHEF+QLR") -> iCHEF+QLR | E22: =IFERROR(__xludf.DUMMYFUNCTION("""COMPUTED_VALUE"""),"6x1302 6x1303") -> 6x1302 6x1303 | F22: =IFERROR(__xludf.DUMMYFUNCTION("""COMPUTED_VALUE"""),"旅費 旅費") -> 旅費 旅費 | G22: =IFERROR(__xludf.DUMMYFUNCTION("""COMPUTED_VALUE"""),"國內差旅費 國外差旅費") -> 國內差旅費 國外差旅費 | H22: =IFERROR(__xludf.DUMMYFUNCTION("""COMPUTED_VALUE"""),"差旅費") -> 差旅費 | K22: =IFERROR(__xludf.DUMMYFUNCTION("""COMPUTED_VALUE"""),"各專業中心") -> 各專業中心 | L22: =IFERROR(__xludf.DUMMYFUNCTION("""COMPUTED_VALUE"""),"各專業中心") -> 各專業中心 | M22: =IFERROR(__xludf.DUMMYFUNCTION("""COMPUTED_VALUE"""),"金額由各中心自行評估") -> 金額由各中心自行評估
B23: =IFERROR(__xludf.DUMMYFUNCTION("""COMPUTED_VALUE"""),22.0) -> 22 | C23: =IFERROR(__xludf.DUMMYFUNCTION("""COMPUTED_VALUE"""),"非人事費用") -> 非人事費用 | D23: =IFERROR(__xludf.DUMMYFUNCTION("""COMPUTED_VALUE"""),"iCHEF+QLR") -> iCHEF+QLR | E23: =IFERROR(__xludf.DUMMYFUNCTION("""COMPUTED_VALUE"""),"6x1301") -> 6x1301 | F23: =IFERROR(__xludf.DUMMYFUNCTION("""COMPUTED_VALUE"""),"旅費") -> 旅費 | G23: =IFERROR(__xludf.DUMMYFUNCTION("""COMPUTED_VALUE"""),"交通費") -> 交通費 | H23: =IFERROR(__xludf.DUMMYFUNCTION("""COMPUTED_VALUE"""),"交通費") -> 交通費 | K23: =IFERROR(__xludf.DUMMYFUNCTION("""COMPUTED_VALUE"""),"各專業中心") -> 各專業中心 | L23: =IFERROR(__xludf.DUMMYFUNCTION("""COMPUTED_VALUE"""),"各專業中心") -> 各專業中心 | M23: =IFERROR(__xludf.DUMMYFUNCTION("""COMPUTED_VALUE"""),"金額由各中心自行評估") -> 金額由各中心自行評估
B24: =IFERROR(__xludf.DUMMYFUNCTION("""COMPUTED_VALUE"""),23.0) -> 23 | C24: =IFERROR(__xludf.DUMMYFUNCTION("""COMPUTED_VALUE"""),"非人事費用") -> 非人事費用 | D24: =IFERROR(__xludf.DUMMYFUNCTION("""COMPUTED_VALUE"""),"iCHEF") -> iCHEF | E24: =IFERROR(__xludf.DUMMYFUNCTION("""COMPUTED_VALUE"""),613299.0) -> 613299 | F24: =IFERROR(__xludf.DUMMYFUNCTION("""COMPUTED_VALUE"""),"其他費用") -> 其他費用 | G24: =IFERROR(__xludf.DUMMYFUNCTION("""COMPUTED_VALUE"""),"其他") -> 其他 | H24: =IFERROR(__xludf.DUMMYFUNCTION("""COMPUTED_VALUE"""),"新人到職第一餐") -> 新人到職第一餐 | I24: =IFERROR(__xludf.DUMMYFUNCTION("""COMPUTED_VALUE"""),1000.0) -> 1000 | J24: =IFERROR(__xludf.DUMMYFUNCTION("""COMPUTED_VALUE"""),"人") -> 人 | K24: =IFERROR(__xludf.DUMMYFUNCTION("""COMPUTED_VALUE"""),"各專業中心") -> 各專業中心 | L24: =IFERROR(__xludf.DUMMYFUNCTION("""COMPUTED_VALUE"""),"各專業中心") -> 各專業中心
B25: =IFERROR(__xludf.DUMMYFUNCTION("""COMPUTED_VALUE"""),24.0) -> 24 | C25: =IFERROR(__xludf.DUMMYFUNCTION("""COMPUTED_VALUE"""),"非人事費用") -> 非人事費用 | D25: =IFERROR(__xludf.DUMMYFUNCTION("""COMPUTED_VALUE"""),"iCHEF") -> iCHEF | E25: =IFERROR(__xludf.DUMMYFUNCTION("""COMPUTED_VALUE"""),"6x31") -> 6x31 | F25: =IFERROR(__xludf.DUMMYFUNCTION("""COMPUTED_VALUE"""),"訓練費") -> 訓練費 | G25: =IFERROR(__xludf.DUMMYFUNCTION("""COMPUTED_VALUE"""),"訓練費") -> 訓練費 | H25: =IFERROR(__xludf.DUMMYFUNCTION("""COMPUTED_VALUE"""),"教育訓練") -> 教育訓練 | J25: =IFERROR(__xludf.DUMMYFUNCTION("""COMPUTED_VALUE"""),"由 HR 統一管理") -> 由 HR 統一管理 | K25: =IFERROR(__xludf.DUMMYFUNCTION("""COMPUTED_VALUE"""),"管理中心") -> 管理中心 | L25: =IFERROR(__xludf.DUMMYFUNCTION("""COMPUTED_VALUE"""),"管理中心") -> 管理中心 | M25: =IFERROR(__xludf.DUMMYFUNCTION("""COMPUTED_VALUE"""),"由 HR 統一管理、安排教育訓練課程") -> 由 HR 統一管理、安排教育訓練課程
B26: =IFERROR(__xludf.DUMMYFUNCTION("""COMPUTED_VALUE"""),25.0) -> 25 | C26: =IFERROR(__xludf.DUMMYFUNCTION("""COMPUTED_VALUE"""),"非人事費用") -> 非人事費用 | D26: =IFERROR(__xludf.DUMMYFUNCTION("""COMPUTED_VALUE"""),"iCHEF") -> iCHEF | E26: =IFERROR(__xludf.DUMMYFUNCTION("""COMPUTED_VALUE"""),"6x19") -> 6x19 | F26: =IFERROR(__xludf.DUMMYFUNCTION("""COMPUTED_VALUE"""),"保險費") -> 保險費 | G26: =IFERROR(__xludf.DUMMYFUNCTION("""COMPUTED_VALUE"""),"其他") -> 其他 | H26: =IFERROR(__xludf.DUMMYFUNCTION("""COMPUTED_VALUE"""),"火災保險") -> 火災保險 | I26: =IFERROR(__xludf.DUMMYFUNCTION("""COMPUTED_VALUE"""),6.0) -> 6 | J26: =IFERROR(__xludf.DUMMYFUNCTION("""COMPUTED_VALUE"""),69.0) -> 69 | K26: =IFERROR(__xludf.DUMMYFUNCTION("""COMPUTED_VALUE"""),"管理中心") -> 管理中心 | L26: =IFERROR(__xludf.DUMMYFUNCTION("""COMPUTED_VALUE"""),"管理中心") -> 管理中心 | M26: =IFERROR(__xludf.DUMMYFUNCTION("""COMPUTED_VALUE"""),"2026 台中辦公室也要保火險、要估列 火險包含裝修、設備、存貨 總金額估在管理中心即可") -> 2026 台中辦公室也要保火險、要估列 火險包含裝修、設備、存貨 總金額估在管理中心即可
B27: =IFERROR(__xludf.DUMMYFUNCTION("""COMPUTED_VALUE"""),26.0) -> 26 | C27: =IFERROR(__xludf.DUMMYFUNCTION("""COMPUTED_VALUE"""),"非人事費用") -> 非人事費用 | D27: =IFERROR(__xludf.DUMMYFUNCTION("""COMPUTED_VALUE"""),"iCHEF+QLR") -> iCHEF+QLR | E27: =IFERROR(__xludf.DUMMYFUNCTION("""COMPUTED_VALUE"""),613299.0) -> 613299 | F27: =IFERROR(__xludf.DUMMYFUNCTION("""COMPUTED_VALUE"""),"其他費用") -> 其他費用 | G27: =IFERROR(__xludf.DUMMYFUNCTION("""COMPUTED_VALUE"""),"其他") -> 其他 | H27: =IFERROR(__xludf.DUMMYFUNCTION("""COMPUTED_VALUE"""),"三節禮品") -> 三節禮品 | I27: =IFERROR(__xludf.DUMMYFUNCTION("""COMPUTED_VALUE"""),175.0) -> 175 | J27: =IFERROR(__xludf.DUMMYFUNCTION("""COMPUTED_VALUE"""),2100.0) -> 2100 | K27: =IFERROR(__xludf.DUMMYFUNCTION("""COMPUTED_VALUE"""),"管理中心") -> 管理中心 | L27: =IFERROR(__xludf.DUMMYFUNCTION("""COMPUTED_VALUE"""),"管理中心") -> 管理中心
B28: =IFERROR(__xludf.DUMMYFUNCTION("""COMPUTED_VALUE"""),27.0) -> 27 | C28: =IFERROR(__xludf.DUMMYFUNCTION("""COMPUTED_VALUE"""),"非人事費用") -> 非人事費用 | D28: =IFERROR(__xludf.DUMMYFUNCTION("""COMPUTED_VALUE"""),"iCHEF+QLR") -> iCHEF+QLR | E28: =IFERROR(__xludf.DUMMYFUNCTION("""COMPUTED_VALUE"""),613299.0) -> 613299 | F28: =IFERROR(__xludf.DUMMYFUNCTION("""COMPUTED_VALUE"""),"其他費用") -> 其他費用 | G28: =IFERROR(__xludf.DUMMYFUNCTION("""COMPUTED_VALUE"""),"其他") -> 其他 | H28: =IFERROR(__xludf.DUMMYFUNCTION("""COMPUTED_VALUE"""),"尾牙/春酒") -> 尾牙/春酒 | I28: =IFERROR(__xludf.DUMMYFUNCTION("""COMPUTED_VALUE"""),250.0) -> 250 | J28: =IFERROR(__xludf.DUMMYFUNCTION("""COMPUTED_VALUE"""),3000.0) -> 3000 | K28: =IFERROR(__xludf.DUMMYFUNCTION("""COMPUTED_VALUE"""),"管理中心") -> 管理中心 | L28: =IFERROR(__xludf.DUMMYFUNCTION("""COMPUTED_VALUE"""),"管理中心") -> 管理中心
B29: =IFERROR(__xludf.DUMMYFUNCTION("""COMPUTED_VALUE"""),28.0) -> 28 | C29: =IFERROR(__xludf.DUMMYFUNCTION("""COMPUTED_VALUE"""),"非人事費用") -> 非人事費用 | D29: =IFERROR(__xludf.DUMMYFUNCTION("""COMPUTED_VALUE"""),"iCHEF+QLR") -> iCHEF+QLR | E29: =IFERROR(__xludf.DUMMYFUNCTION("""COMPUTED_VALUE"""),613299.0) -> 613299 | F29: =IFERROR(__xludf.DUMMYFUNCTION("""COMPUTED_VALUE"""),"其他費用") -> 其他費用 | G29: =IFERROR(__xludf.DUMMYFUNCTION("""COMPUTED_VALUE"""),"其他") -> 其他 | H29: =IFERROR(__xludf.DUMMYFUNCTION("""COMPUTED_VALUE"""),"Pizza Meeting 餐費 (每週 NT$ 170)") -> Pizza Meeting 餐費 (每週 NT$ 170) | I29: =IFERROR(__xludf.DUMMYFUNCTION("""COMPUTED_VALUE"""),600.0) -> 600 | J29: =IFERROR(__xludf.DUMMYFUNCTION("""COMPUTED_VALUE"""),7200.0) -> 7200 | K29: =IFERROR(__xludf.DUMMYFUNCTION("""COMPUTED_VALUE"""),"管理中心") -> 管理中心 | L29: =IFERROR(__xludf.DUMMYFUNCTION("""COMPUTED_VALUE"""),"管理中心") -> 管理中心
B30: =IFERROR(__xludf.DUMMYFUNCTION("""COMPUTED_VALUE"""),29.0) -> 29 | C30: =IFERROR(__xludf.DUMMYFUNCTION("""COMPUTED_VALUE"""),"非人事費用") -> 非人事費用 | D30: =IFERROR(__xludf.DUMMYFUNCTION("""COMPUTED_VALUE"""),"iCHEF") -> iCHEF | H30: =IFERROR(__xludf.DUMMYFUNCTION("""COMPUTED_VALUE"""),"業務 公務機津貼") -> 業務 公務機津貼 | I30: =IFERROR(__xludf.DUMMYFUNCTION("""COMPUTED_VALUE"""),1200.0) -> 1200 | J30: =IFERROR(__xludf.DUMMYFUNCTION("""COMPUTED_VALUE"""),14400.0) -> 14400 | K30: =IFERROR(__xludf.DUMMYFUNCTION("""COMPUTED_VALUE"""),"行銷營運中心") -> 行銷營運中心 | L30: =IFERROR(__xludf.DUMMYFUNCTION("""COMPUTED_VALUE"""),"行銷營運中心") -> 行銷營運中心
B31: =IFERROR(__xludf.DUMMYFUNCTION("""COMPUTED_VALUE"""),30.0) -> 30 | C31: =IFERROR(__xludf.DUMMYFUNCTION("""COMPUTED_VALUE"""),"非人事費用") -> 非人事費用 | D31: =IFERROR(__xludf.DUMMYFUNCTION("""COMPUTED_VALUE"""),"iCHEF") -> iCHEF | H31: =IFERROR(__xludf.DUMMYFUNCTION("""COMPUTED_VALUE"""),"業務 多店顧問 交通費") -> 業務 多店顧問 交通費 | I31: =IFERROR(__xludf.DUMMYFUNCTION("""COMPUTED_VALUE"""),15000.0) -> 15000 | J31: =IFERROR(__xludf.DUMMYFUNCTION("""COMPUTED_VALUE"""),180000.0) -> 180000 | K31: =IFERROR(__xludf.DUMMYFUNCTION("""COMPUTED_VALUE"""),"行銷營運中心") -> 行銷營運中心 | L31: =IFERROR(__xludf.DUMMYFUNCTION("""COMPUTED_VALUE"""),"行銷營運中心") -> 行銷營運中心
B32: =IFERROR(__xludf.DUMMYFUNCTION("""COMPUTED_VALUE"""),31.0) -> 31 | C32: =IFERROR(__xludf.DUMMYFUNCTION("""COMPUTED_VALUE"""),"非人事費用") -> 非人事費用 | D32: =IFERROR(__xludf.DUMMYFUNCTION("""COMPUTED_VALUE"""),"iCHEF") -> iCHEF | H32: =IFERROR(__xludf.DUMMYFUNCTION("""COMPUTED_VALUE"""),"業務 多店顧問 交際費") -> 業務 多店顧問 交際費 | I32: =IFERROR(__xludf.DUMMYFUNCTION("""COMPUTED_VALUE"""),3000.0) -> 3000 | J32: =IFERROR(__xludf.DUMMYFUNCTION("""COMPUTED_VALUE"""),36000.0) -> 36000 | K32: =IFERROR(__xludf.DUMMYFUNCTION("""COMPUTED_VALUE"""),"行銷營運中心") -> 行銷營運中心 | L32: =IFERROR(__xludf.DUMMYFUNCTION("""COMPUTED_VALUE"""),"行銷營運中心") -> 行銷營運中心
B33: =IFERROR(__xludf.DUMMYFUNCTION("""COMPUTED_VALUE"""),32.0) -> 32 | C33: =IFERROR(__xludf.DUMMYFUNCTION("""COMPUTED_VALUE"""),"人事費用") -> 人事費用 | D33: =IFERROR(__xludf.DUMMYFUNCTION("""COMPUTED_VALUE"""),"iCHEF") -> iCHEF | H33: =IFERROR(__xludf.DUMMYFUNCTION("""COMPUTED_VALUE"""),"業務 季度績效獎金 (一般業務)") -> 業務 季度績效獎金 (一般業務) | I33: =IFERROR(__xludf.DUMMYFUNCTION("""COMPUTED_VALUE"""),3334.0) -> 3334 | J33: =IFERROR(__xludf.DUMMYFUNCTION("""COMPUTED_VALUE"""),40000.0) -> 40000 | K33: =IFERROR(__xludf.DUMMYFUNCTION("""COMPUTED_VALUE"""),"行銷營運中心") -> 行銷營運中心 | L33: =IFERROR(__xludf.DUMMYFUNCTION("""COMPUTED_VALUE"""),"行銷營運中心") -> 行銷營運中心
B34: =IFERROR(__xludf.DUMMYFUNCTION("""COMPUTED_VALUE"""),33.0) -> 33 | C34: =IFERROR(__xludf.DUMMYFUNCTION("""COMPUTED_VALUE"""),"人事費用") -> 人事費用 | D34: =IFERROR(__xludf.DUMMYFUNCTION("""COMPUTED_VALUE"""),"iCHEF") -> iCHEF | H34: =IFERROR(__xludf.DUMMYFUNCTION("""COMPUTED_VALUE"""),"業務 季度績效獎金 (資深業務)") -> 業務 季度績效獎金 (資深業務) | I34: =IFERROR(__xludf.DUMMYFUNCTION("""COMPUTED_VALUE"""),5000.0) -> 5000 | J34: =IFERROR(__xludf.DUMMYFUNCTION("""COMPUTED_VALUE"""),60000.0) -> 60000 | K34: =IFERROR(__xludf.DUMMYFUNCTION("""COMPUTED_VALUE"""),"行銷營運中心") -> 行銷營運中心 | L34: =IFERROR(__xludf.DUMMYFUNCTION("""COMPUTED_VALUE"""),"行銷營運中心") -> 行銷營運中心
B35: =IFERROR(__xludf.DUMMYFUNCTION("""COMPUTED_VALUE"""),34.0) -> 34 | C35: =IFERROR(__xludf.DUMMYFUNCTION("""COMPUTED_VALUE"""),"人事費用") -> 人事費用 | D35: =IFERROR(__xludf.DUMMYFUNCTION("""COMPUTED_VALUE"""),"iCHEF") -> iCHEF | H35: =IFERROR(__xludf.DUMMYFUNCTION("""COMPUTED_VALUE"""),"業務 季度績效獎金 (業務團隊主管)") -> 業務 季度績效獎金 (業務團隊主管) | I35: =IFERROR(__xludf.DUMMYFUNCTION("""COMPUTED_VALUE"""),15000.0) -> 15000 | J35: =IFERROR(__xludf.DUMMYFUNCTION("""COMPUTED_VALUE"""),180000.0) -> 180000 | K35: =IFERROR(__xludf.DUMMYFUNCTION("""COMPUTED_VALUE"""),"行銷營運中心") -> 行銷營運中心 | L35: =IFERROR(__xludf.DUMMYFUNCTION("""COMPUTED_VALUE"""),"行銷營運中心") -> 行銷營運中心
B36: =IFERROR(__xludf.DUMMYFUNCTION("""COMPUTED_VALUE"""),35.0) -> 35 | C36: =IFERROR(__xludf.DUMMYFUNCTION("""COMPUTED_VALUE"""),"人事費用") -> 人事費用 | D36: =IFERROR(__xludf.DUMMYFUNCTION("""COMPUTED_VALUE"""),"iCHEF") -> iCHEF | H36: =IFERROR(__xludf.DUMMYFUNCTION("""COMPUTED_VALUE"""),"業務 帳號啟用費獎金 (開發/混編)") -> 業務 帳號啟用費獎金 (開發/混編) | I36: =IFERROR(__xludf.DUMMYFUNCTION("""COMPUTED_VALUE"""),510.0) -> 510 | J36: =IFERROR(__xludf.DUMMYFUNCTION("""COMPUTED_VALUE"""),"間") -> 間 | K36: =IFERROR(__xludf.DUMMYFUNCTION("""COMPUTED_VALUE"""),"行銷營運中心") -> 行銷營運中心 | L36: =IFERROR(__xludf.DUMMYFUNCTION("""COMPUTED_VALUE"""),"行銷營運中心") -> 行銷營運中心
B37: =IFERROR(__xludf.DUMMYFUNCTION("""COMPUTED_VALUE"""),36.0) -> 36 | C37: =IFERROR(__xludf.DUMMYFUNCTION("""COMPUTED_VALUE"""),"人事費用") -> 人事費用 | D37: =IFERROR(__xludf.DUMMYFUNCTION("""COMPUTED_VALUE"""),"iCHEF") -> iCHEF | H37: =IFERROR(__xludf.DUMMYFUNCTION("""COMPUTED_VALUE"""),"業務 標準方案啟用獎金 (開發/混編)") -> 業務 標準方案啟用獎金 (開發/混編) | I37: =IFERROR(__xludf.DUMMYFUNCTION("""COMPUTED_VALUE"""),1500.0) -> 1500 | J37: =IFERROR(__xludf.DUMMYFUNCTION("""COMPUTED_VALUE"""),"間") -> 間 | K37: =IFERROR(__xludf.DUMMYFUNCTION("""COMPUTED_VALUE"""),"行銷營運中心") -> 行銷營運中心 | L37: =IFERROR(__xludf.DUMMYFUNCTION("""COMPUTED_VALUE"""),"行銷營運中心") -> 行銷營運中心
B38: =IFERROR(__xludf.DUMMYFUNCTION("""COMPUTED_VALUE"""),37.0) -> 37 | C38: =IFERROR(__xludf.DUMMYFUNCTION("""COMPUTED_VALUE"""),"人事費用") -> 人事費用 | D38: =IFERROR(__xludf.DUMMYFUNCTION("""COMPUTED_VALUE"""),"iCHEF") -> iCHEF | H38: =IFERROR(__xludf.DUMMYFUNCTION("""COMPUTED_VALUE"""),"業務 進階方案啟用獎金 (開發/混編)") -> 業務 進階方案啟用獎金 (開發/混編) | I38: =IFERROR(__xludf.DUMMYFUNCTION("""COMPUTED_VALUE"""),3500.0) -> 3500 | J38: =IFERROR(__xludf.DUMMYFUNCTION("""COMPUTED_VALUE"""),"間") -> 間 | K38: =IFERROR(__xludf.DUMMYFUNCTION("""COMPUTED_VALUE"""),"行銷營運中心") -> 行銷營運中心 | L38: =IFERROR(__xludf.DUMMYFUNCTION("""COMPUTED_VALUE"""),"行銷營運中心") -> 行銷營運中心
B39: =IFERROR(__xludf.DUMMYFUNCTION("""COMPUTED_VALUE"""),38.0) -> 38 | C39: =IFERROR(__xludf.DUMMYFUNCTION("""COMPUTED_VALUE"""),"人事費用") -> 人事費用 | D39: =IFERROR(__xludf.DUMMYFUNCTION("""COMPUTED_VALUE"""),"iCHEF") -> iCHEF | H39: =IFERROR(__xludf.DUMMYFUNCTION("""COMPUTED_VALUE"""),"業務 頂級方案啟用獎金 (開發/混編)") -> 業務 頂級方案啟用獎金 (開發/混編) | I39: =IFERROR(__xludf.DUMMYFUNCTION("""COMPUTED_VALUE"""),5500.0) -> 5500 | J39: =IFERROR(__xludf.DUMMYFUNCTION("""COMPUTED_VALUE"""),"間") -> 間 | K39: =IFERROR(__xludf.DUMMYFUNCTION("""COMPUTED_VALUE"""),"行銷營運中心") -> 行銷營運中心 | L39: =IFERROR(__xludf.DUMMYFUNCTION("""COMPUTED_VALUE"""),"行銷營運中心") -> 行銷營運中心
B40: =IFERROR(__xludf.DUMMYFUNCTION("""COMPUTED_VALUE"""),39.0) -> 39 | C40: =IFERROR(__xludf.DUMMYFUNCTION("""COMPUTED_VALUE"""),"人事費用") -> 人事費用 | D40: =IFERROR(__xludf.DUMMYFUNCTION("""COMPUTED_VALUE"""),"iCHEF") -> iCHEF | H40: =IFERROR(__xludf.DUMMYFUNCTION("""COMPUTED_VALUE"""),"業務 轉介通路獎金 (業務)") -> 業務 轉介通路獎金 (業務) | I40: =IFERROR(__xludf.DUMMYFUNCTION("""COMPUTED_VALUE"""),1500.0) -> 1500 | J40: =IFERROR(__xludf.DUMMYFUNCTION("""COMPUTED_VALUE"""),"間") -> 間 | K40: =IFERROR(__xludf.DUMMYFUNCTION("""COMPUTED_VALUE"""),"行銷營運中心") -> 行銷營運中心 | L40: =IFERROR(__xludf.DUMMYFUNCTION("""COMPUTED_VALUE"""),"行銷營運中心") -> 行銷營運中心
B41: =IFERROR(__xludf.DUMMYFUNCTION("""COMPUTED_VALUE"""),40.0) -> 40 | C41: =IFERROR(__xludf.DUMMYFUNCTION("""COMPUTED_VALUE"""),"人事費用") -> 人事費用 | D41: =IFERROR(__xludf.DUMMYFUNCTION("""COMPUTED_VALUE"""),"iCHEF") -> iCHEF | H41: =IFERROR(__xludf.DUMMYFUNCTION("""COMPUTED_VALUE"""),"業務 激勵獎金 (開發顧問)") -> 業務 激勵獎金 (開發顧問) | I41: =IFERROR(__xludf.DUMMYFUNCTION("""COMPUTED_VALUE"""),5000.0) -> 5000 | J41: =IFERROR(__xludf.DUMMYFUNCTION("""COMPUTED_VALUE"""),"北區、非北區開發顧問各一名") -> 北區、非北區開發顧問各一名 | K41: =IFERROR(__xludf.DUMMYFUNCTION("""COMPUTED_VALUE"""),"行銷營運中心") -> 行銷營運中心 | L41: =IFERROR(__xludf.DUMMYFUNCTION("""COMPUTED_VALUE"""),"行銷營運中心") -> 行銷營運中心
B42: =IFERROR(__xludf.DUMMYFUNCTION("""COMPUTED_VALUE"""),41.0) -> 41 | C42: =IFERROR(__xludf.DUMMYFUNCTION("""COMPUTED_VALUE"""),"人事費用") -> 人事費用 | D42: =IFERROR(__xludf.DUMMYFUNCTION("""COMPUTED_VALUE"""),"iCHEF") -> iCHEF | H42: =IFERROR(__xludf.DUMMYFUNCTION("""COMPUTED_VALUE"""),"業務 導入津貼 (混編顧問)") -> 業務 導入津貼 (混編顧問) | I42: =IFERROR(__xludf.DUMMYFUNCTION("""COMPUTED_VALUE"""),1500.0) -> 1500 | J42: =IFERROR(__xludf.DUMMYFUNCTION("""COMPUTED_VALUE"""),"間") -> 間 | K42: =IFERROR(__xludf.DUMMYFUNCTION("""COMPUTED_VALUE"""),"行銷營運中心") -> 行銷營運中心 | L42: =IFERROR(__xludf.DUMMYFUNCTION("""COMPUTED_VALUE"""),"行銷營運中心") -> 行銷營運中心
B43: =IFERROR(__xludf.DUMMYFUNCTION("""COMPUTED_VALUE"""),42.0) -> 42 | C43: =IFERROR(__xludf.DUMMYFUNCTION("""COMPUTED_VALUE"""),"人事費用") -> 人事費用 | D43: =IFERROR(__xludf.DUMMYFUNCTION("""COMPUTED_VALUE"""),"iCHEF") -> iCHEF | H43: =IFERROR(__xludf.DUMMYFUNCTION("""COMPUTED_VALUE"""),"業務 超額導入津貼 (導入教練)") -> 業務 超額導入津貼 (導入教練) | I43: =IFERROR(__xludf.DUMMYFUNCTION("""COMPUTED_VALUE"""),1500.0) -> 1500 | J43: =IFERROR(__xludf.DUMMYFUNCTION("""COMPUTED_VALUE"""),"間") -> 間 | K43: =IFERROR(__xludf.DUMMYFUNCTION("""COMPUTED_VALUE"""),"行銷營運中心") -> 行銷營運中心 | L43: =IFERROR(__xludf.DUMMYFUNCTION("""COMPUTED_VALUE"""),"行銷營運中心") -> 行銷營運中心
B44: =IFERROR(__xludf.DUMMYFUNCTION("""COMPUTED_VALUE"""),43.0) -> 43 | C44: =IFERROR(__xludf.DUMMYFUNCTION("""COMPUTED_VALUE"""),"人事費用") -> 人事費用 | D44: =IFERROR(__xludf.DUMMYFUNCTION("""COMPUTED_VALUE"""),"iCHEF") -> iCHEF | H44: =IFERROR(__xludf.DUMMYFUNCTION("""COMPUTED_VALUE"""),"業務 總店系統啟用獎金") -> 業務 總店系統啟用獎金 | I44: =IFERROR(__xludf.DUMMYFUNCTION("""COMPUTED_VALUE"""),3000.0) -> 3000 | J44: =IFERROR(__xludf.DUMMYFUNCTION("""COMPUTED_VALUE"""),"間") -> 間 | K44: =IFERROR(__xludf.DUMMYFUNCTION("""COMPUTED_VALUE"""),"行銷營運中心") -> 行銷營運中心 | L44: =IFERROR(__xludf.DUMMYFUNCTION("""COMPUTED_VALUE"""),"行銷營運中心") -> 行銷營運中心
B45: =IFERROR(__xludf.DUMMYFUNCTION("""COMPUTED_VALUE"""),44.0) -> 44 | C45: =IFERROR(__xludf.DUMMYFUNCTION("""COMPUTED_VALUE"""),"人事費用") -> 人事費用 | D45: =IFERROR(__xludf.DUMMYFUNCTION("""COMPUTED_VALUE"""),"iCHEF") -> iCHEF | H45: =IFERROR(__xludf.DUMMYFUNCTION("""COMPUTED_VALUE"""),"業務 總店系統導入獎金") -> 業務 總店系統導入獎金 | I45: =IFERROR(__xludf.DUMMYFUNCTION("""COMPUTED_VALUE"""),2000.0) -> 2000 | J45: =IFERROR(__xludf.DUMMYFUNCTION("""COMPUTED_VALUE"""),"品牌") -> 品牌 | K45: =IFERROR(__xludf.DUMMYFUNCTION("""COMPUTED_VALUE"""),"行銷營運中心") -> 行銷營運中心 | L45: =IFERROR(__xludf.DUMMYFUNCTION("""COMPUTED_VALUE"""),"行銷營運中心") -> 行銷營運中心
B46: =IFERROR(__xludf.DUMMYFUNCTION("""COMPUTED_VALUE"""),45.0) -> 45 | C46: =IFERROR(__xludf.DUMMYFUNCTION("""COMPUTED_VALUE"""),"人事費用") -> 人事費用 | D46: =IFERROR(__xludf.DUMMYFUNCTION("""COMPUTED_VALUE"""),"iCHEF") -> iCHEF | H46: =IFERROR(__xludf.DUMMYFUNCTION("""COMPUTED_VALUE"""),"業務 總店系統轉介獎金") -> 業務 總店系統轉介獎金 | I46: =IFERROR(__xludf.DUMMYFUNCTION("""COMPUTED_VALUE"""),1500.0) -> 1500 | J46: =IFERROR(__xludf.DUMMYFUNCTION("""COMPUTED_VALUE"""),"品牌") -> 品牌 | K46: =IFERROR(__xludf.DUMMYFUNCTION("""COMPUTED_VALUE"""),"行銷營運中心") -> 行銷營運中心 | L46: =IFERROR(__xludf.DUMMYFUNCTION("""COMPUTED_VALUE"""),"行銷營運中心") -> 行銷營運中心
B47: =IFERROR(__xludf.DUMMYFUNCTION("""COMPUTED_VALUE"""),46.0) -> 46 | C47: =IFERROR(__xludf.DUMMYFUNCTION("""COMPUTED_VALUE"""),"人事費用") -> 人事費用 | D47: =IFERROR(__xludf.DUMMYFUNCTION("""COMPUTED_VALUE"""),"iCHEF") -> iCHEF | H47: =IFERROR(__xludf.DUMMYFUNCTION("""COMPUTED_VALUE"""),"業務 總店系統首批軟體獎金") -> 業務 總店系統首批軟體獎金 | I47: =IFERROR(__xludf.DUMMYFUNCTION("""COMPUTED_VALUE"""),3200.0) -> 3200 | J47: =IFERROR(__xludf.DUMMYFUNCTION("""COMPUTED_VALUE"""),"席") -> 席 | K47: =IFERROR(__xludf.DUMMYFUNCTION("""COMPUTED_VALUE"""),"行銷營運中心") -> 行銷營運中心 | L47: =IFERROR(__xludf.DUMMYFUNCTION("""COMPUTED_VALUE"""),"行銷營運中心") -> 行銷營運中心
B48: =IFERROR(__xludf.DUMMYFUNCTION("""COMPUTED_VALUE"""),47.0) -> 47 | C48: =IFERROR(__xludf.DUMMYFUNCTION("""COMPUTED_VALUE"""),"人事費用") -> 人事費用 | D48: =IFERROR(__xludf.DUMMYFUNCTION("""COMPUTED_VALUE"""),"iCHEF") -> iCHEF | H48: =IFERROR(__xludf.DUMMYFUNCTION("""COMPUTED_VALUE"""),"業務 總店系統加購軟體獎金") -> 業務 總店系統加購軟體獎金 | I48: =IFERROR(__xludf.DUMMYFUNCTION("""COMPUTED_VALUE"""),400.0) -> 400 | J48: =IFERROR(__xludf.DUMMYFUNCTION("""COMPUTED_VALUE"""),"席") -> 席 | K48: =IFERROR(__xludf.DUMMYFUNCTION("""COMPUTED_VALUE"""),"行銷營運中心") -> 行銷營運中心 | L48: =IFERROR(__xludf.DUMMYFUNCTION("""COMPUTED_VALUE"""),"行銷營運中心") -> 行銷營運中心
B49: =IFERROR(__xludf.DUMMYFUNCTION("""COMPUTED_VALUE"""),48.0) -> 48 | C49: =IFERROR(__xludf.DUMMYFUNCTION("""COMPUTED_VALUE"""),"人事費用") -> 人事費用 | D49: =IFERROR(__xludf.DUMMYFUNCTION("""COMPUTED_VALUE"""),"iCHEF") -> iCHEF | H49: =IFERROR(__xludf.DUMMYFUNCTION("""COMPUTED_VALUE"""),"業務 iDIS 軟體軟體獎金") -> 業務 iDIS 軟體軟體獎金 | I49: =IFERROR(__xludf.DUMMYFUNCTION("""COMPUTED_VALUE"""),3000.0) -> 3000 | J49: =IFERROR(__xludf.DUMMYFUNCTION("""COMPUTED_VALUE"""),"席") -> 席 | K49: =IFERROR(__xludf.DUMMYFUNCTION("""COMPUTED_VALUE"""),"行銷營運中心") -> 行銷營運中心 | L49: =IFERROR(__xludf.DUMMYFUNCTION("""COMPUTED_VALUE"""),"行銷營運中心") -> 行銷營運中心
B50: =IFERROR(__xludf.DUMMYFUNCTION("""COMPUTED_VALUE"""),49.0) -> 49 | C50: =IFERROR(__xludf.DUMMYFUNCTION("""COMPUTED_VALUE"""),"人事費用") -> 人事費用 | D50: =IFERROR(__xludf.DUMMYFUNCTION("""COMPUTED_VALUE"""),"iCHEF") -> iCHEF | H50: =IFERROR(__xludf.DUMMYFUNCTION("""COMPUTED_VALUE"""),"業務 離職業務的二次教學") -> 業務 離職業務的二次教學 | I50: =IFERROR(__xludf.DUMMYFUNCTION("""COMPUTED_VALUE"""),750.0) -> 750 | J50: =IFERROR(__xludf.DUMMYFUNCTION("""COMPUTED_VALUE"""),"次") -> 次 | K50: =IFERROR(__xludf.DUMMYFUNCTION("""COMPUTED_VALUE"""),"行銷營運中心") -> 行銷營運中心 | L50: =IFERROR(__xludf.DUMMYFUNCTION("""COMPUTED_VALUE"""),"行銷營運中心") -> 行銷營運中心
B51: =IFERROR(__xludf.DUMMYFUNCTION("""COMPUTED_VALUE"""),50.0) -> 50 | C51: =IFERROR(__xludf.DUMMYFUNCTION("""COMPUTED_VALUE"""),"人事費用") -> 人事費用 | D51: =IFERROR(__xludf.DUMMYFUNCTION("""COMPUTED_VALUE"""),"iCHEF") -> iCHEF | H51: =IFERROR(__xludf.DUMMYFUNCTION("""COMPUTED_VALUE"""),"業務 店家付費 2000 元移機安裝") -> 業務 店家付費 2000 元移機安裝 | I51: =IFERROR(__xludf.DUMMYFUNCTION("""COMPUTED_VALUE"""),1500.0) -> 1500 | J51: =IFERROR(__xludf.DUMMYFUNCTION("""COMPUTED_VALUE"""),"次") -> 次 | K51: =IFERROR(__xludf.DUMMYFUNCTION("""COMPUTED_VALUE"""),"行銷營運中心") -> 行銷營運中心 | L51: =IFERROR(__xludf.DUMMYFUNCTION("""COMPUTED_VALUE"""),"行銷營運中心") -> 行銷營運中心
B52: =IFERROR(__xludf.DUMMYFUNCTION("""COMPUTED_VALUE"""),51.0) -> 51 | C52: =IFERROR(__xludf.DUMMYFUNCTION("""COMPUTED_VALUE"""),"人事費用") -> 人事費用 | D52: =IFERROR(__xludf.DUMMYFUNCTION("""COMPUTED_VALUE"""),"iCHEF") -> iCHEF | H52: =IFERROR(__xludf.DUMMYFUNCTION("""COMPUTED_VALUE"""),"業務 奶媽工單") -> 業務 奶媽工單 | I52: =IFERROR(__xludf.DUMMYFUNCTION("""COMPUTED_VALUE"""),750.0) -> 750 | J52: =IFERROR(__xludf.DUMMYFUNCTION("""COMPUTED_VALUE"""),"次") -> 次 | K52: =IFERROR(__xludf.DUMMYFUNCTION("""COMPUTED_VALUE"""),"行銷營運中心") -> 行銷營運中心 | L52: =IFERROR(__xludf.DUMMYFUNCTION("""COMPUTED_VALUE"""),"行銷營運中心") -> 行銷營運中心
B53: =IFERROR(__xludf.DUMMYFUNCTION("""COMPUTED_VALUE"""),52.0) -> 52 | C53: =IFERROR(__xludf.DUMMYFUNCTION("""COMPUTED_VALUE"""),"人事費用") -> 人事費用 | D53: =IFERROR(__xludf.DUMMYFUNCTION("""COMPUTED_VALUE"""),"iCHEF") -> iCHEF | H53: =IFERROR(__xludf.DUMMYFUNCTION("""COMPUTED_VALUE"""),"業務 硬體設備到店安裝") -> 業務 硬體設備到店安裝 | I53: =IFERROR(__xludf.DUMMYFUNCTION("""COMPUTED_VALUE"""),750.0) -> 750 | J53: =IFERROR(__xludf.DUMMYFUNCTION("""COMPUTED_VALUE"""),"次") -> 次 | K53: =IFERROR(__xludf.DUMMYFUNCTION("""COMPUTED_VALUE"""),"行銷營運中心") -> 行銷營運中心 | L53: =IFERROR(__xludf.DUMMYFUNCTION("""COMPUTED_VALUE"""),"行銷營運中心") -> 行銷營運中心
B54: =IFERROR(__xludf.DUMMYFUNCTION("""COMPUTED_VALUE"""),53.0) -> 53 | C54: =IFERROR(__xludf.DUMMYFUNCTION("""COMPUTED_VALUE"""),"人事費用") -> 人事費用 | D54: =IFERROR(__xludf.DUMMYFUNCTION("""COMPUTED_VALUE"""),"iCHEF") -> iCHEF | H54: =IFERROR(__xludf.DUMMYFUNCTION("""COMPUTED_VALUE"""),"業務 加值服務：系統教學") -> 業務 加值服務：系統教學 | I54: =IFERROR(__xludf.DUMMYFUNCTION("""COMPUTED_VALUE"""),1500.0) -> 1500 | J54: =IFERROR(__xludf.DUMMYFUNCTION("""COMPUTED_VALUE"""),"次") -> 次 | K54: =IFERROR(__xludf.DUMMYFUNCTION("""COMPUTED_VALUE"""),"行銷營運中心") -> 行銷營運中心 | L54: =IFERROR(__xludf.DUMMYFUNCTION("""COMPUTED_VALUE"""),"行銷營運中心") -> 行銷營運中心
B55: =IFERROR(__xludf.DUMMYFUNCTION("""COMPUTED_VALUE"""),54.0) -> 54 | C55: =IFERROR(__xludf.DUMMYFUNCTION("""COMPUTED_VALUE"""),"人事費用") -> 人事費用 | D55: =IFERROR(__xludf.DUMMYFUNCTION("""COMPUTED_VALUE"""),"iCHEF") -> iCHEF | H55: =IFERROR(__xludf.DUMMYFUNCTION("""COMPUTED_VALUE"""),"業務 加值服務：硬體安裝") -> 業務 加值服務：硬體安裝 | I55: =IFERROR(__xludf.DUMMYFUNCTION("""COMPUTED_VALUE"""),1500.0) -> 1500 | J55: =IFERROR(__xludf.DUMMYFUNCTION("""COMPUTED_VALUE"""),"次") -> 次 | K55: =IFERROR(__xludf.DUMMYFUNCTION("""COMPUTED_VALUE"""),"行銷營運中心") -> 行銷營運中心 | L55: =IFERROR(__xludf.DUMMYFUNCTION("""COMPUTED_VALUE"""),"行銷營運中心") -> 行銷營運中心
B56: =IFERROR(__xludf.DUMMYFUNCTION("""COMPUTED_VALUE"""),55.0) -> 55 | C56: =IFERROR(__xludf.DUMMYFUNCTION("""COMPUTED_VALUE"""),"人事費用") -> 人事費用 | D56: =IFERROR(__xludf.DUMMYFUNCTION("""COMPUTED_VALUE"""),"iCHEF") -> iCHEF | H56: =IFERROR(__xludf.DUMMYFUNCTION("""COMPUTED_VALUE"""),"業務 加值服務：UberEats 菜單設定") -> 業務 加值服務：UberEats 菜單設定 | I56: =IFERROR(__xludf.DUMMYFUNCTION("""COMPUTED_VALUE"""),1500.0) -> 1500 | J56: =IFERROR(__xludf.DUMMYFUNCTION("""COMPUTED_VALUE"""),"次") -> 次 | K56: =IFERROR(__xludf.DUMMYFUNCTION("""COMPUTED_VALUE"""),"行銷營運中心") -> 行銷營運中心 | L56: =IFERROR(__xludf.DUMMYFUNCTION("""COMPUTED_VALUE"""),"行銷營運中心") -> 行銷營運中心
B57: =IFERROR(__xludf.DUMMYFUNCTION("""COMPUTED_VALUE"""),56.0) -> 56 | C57: =IFERROR(__xludf.DUMMYFUNCTION("""COMPUTED_VALUE"""),"人事費用") -> 人事費用 | D57: =IFERROR(__xludf.DUMMYFUNCTION("""COMPUTED_VALUE"""),"iCHEF") -> iCHEF | H57: =IFERROR(__xludf.DUMMYFUNCTION("""COMPUTED_VALUE"""),"業務 加值服務：foodpanda 菜單設定") -> 業務 加值服務：foodpanda 菜單設定 | I57: =IFERROR(__xludf.DUMMYFUNCTION("""COMPUTED_VALUE"""),1500.0) -> 1500 | J57: =IFERROR(__xludf.DUMMYFUNCTION("""COMPUTED_VALUE"""),"次") -> 次 | K57: =IFERROR(__xludf.DUMMYFUNCTION("""COMPUTED_VALUE"""),"行銷營運中心") -> 行銷營運中心 | L57: =IFERROR(__xludf.DUMMYFUNCTION("""COMPUTED_VALUE"""),"行銷營運中心") -> 行銷營運中心
B58: =IFERROR(__xludf.DUMMYFUNCTION("""COMPUTED_VALUE"""),57.0) -> 57 | C58: =IFERROR(__xludf.DUMMYFUNCTION("""COMPUTED_VALUE"""),"人事費用") -> 人事費用 | D58: =IFERROR(__xludf.DUMMYFUNCTION("""COMPUTED_VALUE"""),"iCHEF") -> iCHEF | H58: =IFERROR(__xludf.DUMMYFUNCTION("""COMPUTED_VALUE"""),"社群工單 課程講師費 (授課）") -> 社群工單 課程講師費 (授課） | I58: =IFERROR(__xludf.DUMMYFUNCTION("""COMPUTED_VALUE"""),2000.0) -> 2000 | J58: =IFERROR(__xludf.DUMMYFUNCTION("""COMPUTED_VALUE"""),"次") -> 次 | K58: =IFERROR(__xludf.DUMMYFUNCTION("""COMPUTED_VALUE"""),"行銷營運中心") -> 行銷營運中心 | L58: =IFERROR(__xludf.DUMMYFUNCTION("""COMPUTED_VALUE"""),"行銷營運中心") -> 行銷營運中心
B59: =IFERROR(__xludf.DUMMYFUNCTION("""COMPUTED_VALUE"""),58.0) -> 58 | C59: =IFERROR(__xludf.DUMMYFUNCTION("""COMPUTED_VALUE"""),"人事費用") -> 人事費用 | D59: =IFERROR(__xludf.DUMMYFUNCTION("""COMPUTED_VALUE"""),"iCHEF") -> iCHEF | H59: =IFERROR(__xludf.DUMMYFUNCTION("""COMPUTED_VALUE"""),"社群工單 課程講師費 (錄影）") -> 社群工單 課程講師費 (錄影） | I59: =IFERROR(__xludf.DUMMYFUNCTION("""COMPUTED_VALUE"""),3000.0) -> 3000 | J59: =IFERROR(__xludf.DUMMYFUNCTION("""COMPUTED_VALUE"""),"次") -> 次 | K59: =IFERROR(__xludf.DUMMYFUNCTION("""COMPUTED_VALUE"""),"行銷營運中心") -> 行銷營運中心 | L59: =IFERROR(__xludf.DUMMYFUNCTION("""COMPUTED_VALUE"""),"行銷營運中心") -> 行銷營運中心
B60: =IFERROR(__xludf.DUMMYFUNCTION("""COMPUTED_VALUE"""),59.0) -> 59 | C60: =IFERROR(__xludf.DUMMYFUNCTION("""COMPUTED_VALUE"""),"人事費用") -> 人事費用 | D60: =IFERROR(__xludf.DUMMYFUNCTION("""COMPUTED_VALUE"""),"iCHEF") -> iCHEF | H60: =IFERROR(__xludf.DUMMYFUNCTION("""COMPUTED_VALUE"""),"社群工單 課程講師費 (授課＋簡報）") -> 社群工單 課程講師費 (授課＋簡報） | I60: =IFERROR(__xludf.DUMMYFUNCTION("""COMPUTED_VALUE"""),4000.0) -> 4000 | J60: =IFERROR(__xludf.DUMMYFUNCTION("""COMPUTED_VALUE"""),"次") -> 次 | K60: =IFERROR(__xludf.DUMMYFUNCTION("""COMPUTED_VALUE"""),"行銷營運中心") -> 行銷營運中心 | L60: =IFERROR(__xludf.DUMMYFUNCTION("""COMPUTED_VALUE"""),"行銷營運中心") -> 行銷營運中心
B61: =IFERROR(__xludf.DUMMYFUNCTION("""COMPUTED_VALUE"""),60.0) -> 60 | C61: =IFERROR(__xludf.DUMMYFUNCTION("""COMPUTED_VALUE"""),"人事費用") -> 人事費用 | D61: =IFERROR(__xludf.DUMMYFUNCTION("""COMPUTED_VALUE"""),"iCHEF") -> iCHEF | H61: =IFERROR(__xludf.DUMMYFUNCTION("""COMPUTED_VALUE"""),"社群工單 課程講師費 (授課＋簡報＋錄影）") -> 社群工單 課程講師費 (授課＋簡報＋錄影） | I61: =IFERROR(__xludf.DUMMYFUNCTION("""COMPUTED_VALUE"""),5000.0) -> 5000 | J61: =IFERROR(__xludf.DUMMYFUNCTION("""COMPUTED_VALUE"""),"次") -> 次 | K61: =IFERROR(__xludf.DUMMYFUNCTION("""COMPUTED_VALUE"""),"行銷營運中心") -> 行銷營運中心 | L61: =IFERROR(__xludf.DUMMYFUNCTION("""COMPUTED_VALUE"""),"行銷營運中心") -> 行銷營運中心
B62: =IFERROR(__xludf.DUMMYFUNCTION("""COMPUTED_VALUE"""),61.0) -> 61 | C62: =IFERROR(__xludf.DUMMYFUNCTION("""COMPUTED_VALUE"""),"人事費用") -> 人事費用 | D62: =IFERROR(__xludf.DUMMYFUNCTION("""COMPUTED_VALUE"""),"iCHEF") -> iCHEF | H62: =IFERROR(__xludf.DUMMYFUNCTION("""COMPUTED_VALUE"""),"社群工單 小聚活動") -> 社群工單 小聚活動 | I62: =IFERROR(__xludf.DUMMYFUNCTION("""COMPUTED_VALUE"""),1500.0) -> 1500 | J62: =IFERROR(__xludf.DUMMYFUNCTION("""COMPUTED_VALUE"""),"次") -> 次 | K62: =IFERROR(__xludf.DUMMYFUNCTION("""COMPUTED_VALUE"""),"行銷營運中心") -> 行銷營運中心 | L62: =IFERROR(__xludf.DUMMYFUNCTION("""COMPUTED_VALUE"""),"行銷營運中心") -> 行銷營運中心
B63: =IFERROR(__xludf.DUMMYFUNCTION("""COMPUTED_VALUE"""),62.0) -> 62 | C63: =IFERROR(__xludf.DUMMYFUNCTION("""COMPUTED_VALUE"""),"人事費用") -> 人事費用 | D63: =IFERROR(__xludf.DUMMYFUNCTION("""COMPUTED_VALUE"""),"iCHEF") -> iCHEF | H63: =IFERROR(__xludf.DUMMYFUNCTION("""COMPUTED_VALUE"""),"社群工單 複雜專案") -> 社群工單 複雜專案 | I63: =IFERROR(__xludf.DUMMYFUNCTION("""COMPUTED_VALUE"""),2250.0) -> 2250 | J63: =IFERROR(__xludf.DUMMYFUNCTION("""COMPUTED_VALUE"""),"次") -> 次 | K63: =IFERROR(__xludf.DUMMYFUNCTION("""COMPUTED_VALUE"""),"行銷營運中心") -> 行銷營運中心 | L63: =IFERROR(__xludf.DUMMYFUNCTION("""COMPUTED_VALUE"""),"行銷營運中心") -> 行銷營運中心
B64: =IFERROR(__xludf.DUMMYFUNCTION("""COMPUTED_VALUE"""),63.0) -> 63 | C64: =IFERROR(__xludf.DUMMYFUNCTION("""COMPUTED_VALUE"""),"人事費用") -> 人事費用 | D64: =IFERROR(__xludf.DUMMYFUNCTION("""COMPUTED_VALUE"""),"iCHEF") -> iCHEF | H64: =IFERROR(__xludf.DUMMYFUNCTION("""COMPUTED_VALUE"""),"社群工單 複雜專案 超時費") -> 社群工單 複雜專案 超時費 | I64: =IFERROR(__xludf.DUMMYFUNCTION("""COMPUTED_VALUE"""),750.0) -> 750 | J64: =IFERROR(__xludf.DUMMYFUNCTION("""COMPUTED_VALUE"""),"小時") -> 小時 | K64: =IFERROR(__xludf.DUMMYFUNCTION("""COMPUTED_VALUE"""),"行銷營運中心") -> 行銷營運中心 | L64: =IFERROR(__xludf.DUMMYFUNCTION("""COMPUTED_VALUE"""),"行銷營運中心") -> 行銷營運中心
B65: =IFERROR(__xludf.DUMMYFUNCTION("""COMPUTED_VALUE"""),64.0) -> 64 | C65: =IFERROR(__xludf.DUMMYFUNCTION("""COMPUTED_VALUE"""),"人事費用") -> 人事費用 | D65: =IFERROR(__xludf.DUMMYFUNCTION("""COMPUTED_VALUE"""),"iCHEF") -> iCHEF | H65: =IFERROR(__xludf.DUMMYFUNCTION("""COMPUTED_VALUE"""),"社群工單 一般專案") -> 社群工單 一般專案 | I65: =IFERROR(__xludf.DUMMYFUNCTION("""COMPUTED_VALUE"""),1000.0) -> 1000 | J65: =IFERROR(__xludf.DUMMYFUNCTION("""COMPUTED_VALUE"""),"次") -> 次 | K65: =IFERROR(__xludf.DUMMYFUNCTION("""COMPUTED_VALUE"""),"行銷營運中心") -> 行銷營運中心 | L65: =IFERROR(__xludf.DUMMYFUNCTION("""COMPUTED_VALUE"""),"行銷營運中心") -> 行銷營運中心
B66: =IFERROR(__xludf.DUMMYFUNCTION("""COMPUTED_VALUE"""),65.0) -> 65 | C66: =IFERROR(__xludf.DUMMYFUNCTION("""COMPUTED_VALUE"""),"人事費用") -> 人事費用 | D66: =IFERROR(__xludf.DUMMYFUNCTION("""COMPUTED_VALUE"""),"iCHEF") -> iCHEF | H66: =IFERROR(__xludf.DUMMYFUNCTION("""COMPUTED_VALUE"""),"社群工單 一般專案 超時費") -> 社群工單 一般專案 超時費 | I66: =IFERROR(__xludf.DUMMYFUNCTION("""COMPUTED_VALUE"""),400.0) -> 400 | J66: =IFERROR(__xludf.DUMMYFUNCTION("""COMPUTED_VALUE"""),"小時") -> 小時 | K66: =IFERROR(__xludf.DUMMYFUNCTION("""COMPUTED_VALUE"""),"行銷營運中心") -> 行銷營運中心 | L66: =IFERROR(__xludf.DUMMYFUNCTION("""COMPUTED_VALUE"""),"行銷營運中心") -> 行銷營運中心
B67: =IFERROR(__xludf.DUMMYFUNCTION("""COMPUTED_VALUE"""),66.0) -> 66 | C67: =IFERROR(__xludf.DUMMYFUNCTION("""COMPUTED_VALUE"""),"人事費用") -> 人事費用 | D67: =IFERROR(__xludf.DUMMYFUNCTION("""COMPUTED_VALUE"""),"iCHEF") -> iCHEF | H67: =IFERROR(__xludf.DUMMYFUNCTION("""COMPUTED_VALUE"""),"客服 一般工單") -> 客服 一般工單 | I67: =IFERROR(__xludf.DUMMYFUNCTION("""COMPUTED_VALUE"""),750.0) -> 750 | J67: =IFERROR(__xludf.DUMMYFUNCTION("""COMPUTED_VALUE"""),"次") -> 次 | K67: =IFERROR(__xludf.DUMMYFUNCTION("""COMPUTED_VALUE"""),"研發中心") -> 研發中心 | L67: =IFERROR(__xludf.DUMMYFUNCTION("""COMPUTED_VALUE"""),"研發中心") -> 研發中心
B68: =IFERROR(__xludf.DUMMYFUNCTION("""COMPUTED_VALUE"""),67.0) -> 67 | C68: =IFERROR(__xludf.DUMMYFUNCTION("""COMPUTED_VALUE"""),"人事費用") -> 人事費用 | D68: =IFERROR(__xludf.DUMMYFUNCTION("""COMPUTED_VALUE"""),"iCHEF") -> iCHEF | H68: =IFERROR(__xludf.DUMMYFUNCTION("""COMPUTED_VALUE"""),"RD 值班費 ") -> RD 值班費 | I68: =IFERROR(__xludf.DUMMYFUNCTION("""COMPUTED_VALUE"""),"不定") -> 不定 | J68: =IFERROR(__xludf.DUMMYFUNCTION("""COMPUTED_VALUE"""),"每月 $1,667 (BE, iOS)") -> 每月 $1,667 (BE, iOS) | K68: =IFERROR(__xludf.DUMMYFUNCTION("""COMPUTED_VALUE"""),"研發中心") -> 研發中心 | L68: =IFERROR(__xludf.DUMMYFUNCTION("""COMPUTED_VALUE"""),"研發中心") -> 研發中心
B69: =IFERROR(__xludf.DUMMYFUNCTION("""COMPUTED_VALUE"""),68.0) -> 68 | C69: =IFERROR(__xludf.DUMMYFUNCTION("""COMPUTED_VALUE"""),"人事費用") -> 人事費用 | D69: =IFERROR(__xludf.DUMMYFUNCTION("""COMPUTED_VALUE"""),"iCHEF") -> iCHEF | H69: =IFERROR(__xludf.DUMMYFUNCTION("""COMPUTED_VALUE"""),"RD 加班費") -> RD 加班費 | I69: =IFERROR(__xludf.DUMMYFUNCTION("""COMPUTED_VALUE"""),"不定") -> 不定 | J69: =IFERROR(__xludf.DUMMYFUNCTION("""COMPUTED_VALUE"""),"每月 $2,354 (SE, PM, DSN,QA,PE)") -> 每月 $2,354 (SE, PM, DSN,QA,PE) | K69: =IFERROR(__xludf.DUMMYFUNCTION("""COMPUTED_VALUE"""),"研發中心") -> 研發中心 | L69: =IFERROR(__xludf.DUMMYFUNCTION("""COMPUTED_VALUE"""),"研發中心") -> 研發中心
B70: =IFERROR(__xludf.DUMMYFUNCTION("""COMPUTED_VALUE"""),69.0) -> 69 | C70: =IFERROR(__xludf.DUMMYFUNCTION("""COMPUTED_VALUE"""),"非人事費用") -> 非人事費用 | D70: =IFERROR(__xludf.DUMMYFUNCTION("""COMPUTED_VALUE"""),"iCHEF") -> iCHEF | H70: =IFERROR(__xludf.DUMMYFUNCTION("""COMPUTED_VALUE"""),"資訊裝置") -> 資訊裝置 | I70: =IFERROR(__xludf.DUMMYFUNCTION("""COMPUTED_VALUE"""),"計算參照：中心設備明細（滿三年、新人）") -> 計算參照：中心設備明細（滿三年、新人） | J70: =IFERROR(__xludf.DUMMYFUNCTION("""COMPUTED_VALUE"""),"4年/人") -> 4年/人 | K70: =IFERROR(__xludf.DUMMYFUNCTION("""COMPUTED_VALUE"""),"各專業中心") -> 各專業中心 | L70: =IFERROR(__xludf.DUMMYFUNCTION("""COMPUTED_VALUE"""),"各專業中心") -> 各專業中心 | M70: =IFERROR(__xludf.DUMMYFUNCTION("""COMPUTED_VALUE"""),"金額請參考中心設備明細（滿三年、新人）") -> 金額請參考中心設備明細（滿三年、新人）
B71: =IFERROR(__xludf.DUMMYFUNCTION("""COMPUTED_VALUE"""),70.0) -> 70 | C71: =IFERROR(__xludf.DUMMYFUNCTION("""COMPUTED_VALUE"""),"非人事費用") -> 非人事費用 | D71: =IFERROR(__xludf.DUMMYFUNCTION("""COMPUTED_VALUE"""),"iCHEF") -> iCHEF | E71: =IFERROR(__xludf.DUMMYFUNCTION("""COMPUTED_VALUE"""),"6x3201") -> 6x3201 | F71: =IFERROR(__xludf.DUMMYFUNCTION("""COMPUTED_VALUE"""),"其他費用") -> 其他費用 | G71: =IFERROR(__xludf.DUMMYFUNCTION("""COMPUTED_VALUE"""),"辦公軟體") -> 辦公軟體 | H71: =IFERROR(__xludf.DUMMYFUNCTION("""COMPUTED_VALUE"""),"通用軟體 GWS") -> 通用軟體 GWS | I71: =IFERROR(__xludf.DUMMYFUNCTION("""COMPUTED_VALUE"""),412.0) -> 412 | J71: =IFERROR(__xludf.DUMMYFUNCTION("""COMPUTED_VALUE"""),4944.0) -> 4944 | K71: =IFERROR(__xludf.DUMMYFUNCTION("""COMPUTED_VALUE"""),"各專業中心") -> 各專業中心 | L71: =IFERROR(__xludf.DUMMYFUNCTION("""COMPUTED_VALUE"""),"各專業中心") -> 各專業中心 | M71: =IFERROR(__xludf.DUMMYFUNCTION("""COMPUTED_VALUE"""),"牌價上漲USD 12/月 -> USD 14/月") -> 牌價上漲USD 12/月 -> USD 14/月
B72: =IFERROR(__xludf.DUMMYFUNCTION("""COMPUTED_VALUE"""),71.0) -> 71 | C72: =IFERROR(__xludf.DUMMYFUNCTION("""COMPUTED_VALUE"""),"非人事費用") -> 非人事費用 | D72: =IFERROR(__xludf.DUMMYFUNCTION("""COMPUTED_VALUE"""),"iCHEF") -> iCHEF | E72: =IFERROR(__xludf.DUMMYFUNCTION("""COMPUTED_VALUE"""),"6x3201") -> 6x3201 | F72: =IFERROR(__xludf.DUMMYFUNCTION("""COMPUTED_VALUE"""),"其他費用") -> 其他費用 | G72: =IFERROR(__xludf.DUMMYFUNCTION("""COMPUTED_VALUE"""),"辦公軟體") -> 辦公軟體 | H72: =IFERROR(__xludf.DUMMYFUNCTION("""COMPUTED_VALUE"""),"專用軟體 MAC (JAMF) 裝置控管") -> 專用軟體 MAC (JAMF) 裝置控管 | I72: =IFERROR(__xludf.DUMMYFUNCTION("""COMPUTED_VALUE"""),300.0) -> 300 | J72: =IFERROR(__xludf.DUMMYFUNCTION("""COMPUTED_VALUE"""),3600.0) -> 3600 | K72: =IFERROR(__xludf.DUMMYFUNCTION("""COMPUTED_VALUE"""),"各專業中心") -> 各專業中心 | L72: =IFERROR(__xludf.DUMMYFUNCTION("""COMPUTED_VALUE"""),"各專業中心") -> 各專業中心 | M72: =IFERROR(__xludf.DUMMYFUNCTION("""COMPUTED_VALUE"""),"2025 新方案, 單價下降 NT 4548 -> NT 3600") -> 2025 新方案, 單價下降 NT 4548 -> NT 3600
B73: =IFERROR(__xludf.DUMMYFUNCTION("""COMPUTED_VALUE"""),72.0) -> 72 | C73: =IFERROR(__xludf.DUMMYFUNCTION("""COMPUTED_VALUE"""),"非人事費用") -> 非人事費用 | D73: =IFERROR(__xludf.DUMMYFUNCTION("""COMPUTED_VALUE"""),"iCHEF") -> iCHEF | E73: =IFERROR(__xludf.DUMMYFUNCTION("""COMPUTED_VALUE"""),"6x3201") -> 6x3201 | F73: =IFERROR(__xludf.DUMMYFUNCTION("""COMPUTED_VALUE"""),"其他費用") -> 其他費用 | G73: =IFERROR(__xludf.DUMMYFUNCTION("""COMPUTED_VALUE"""),"辦公軟體") -> 辦公軟體 | H73: =IFERROR(__xludf.DUMMYFUNCTION("""COMPUTED_VALUE"""),"通用軟體 Apollo") -> 通用軟體 Apollo | I73: =IFERROR(__xludf.DUMMYFUNCTION("""COMPUTED_VALUE"""),124.0) -> 124 | J73: =IFERROR(__xludf.DUMMYFUNCTION("""COMPUTED_VALUE"""),1482.0) -> 1482 | K73: =IFERROR(__xludf.DUMMYFUNCTION("""COMPUTED_VALUE"""),"各專業中心") -> 各專業中心 | L73: =IFERROR(__xludf.DUMMYFUNCTION("""COMPUTED_VALUE"""),"各專業中心") -> 各專業中心 | M73: =IFERROR(__xludf.DUMMYFUNCTION("""COMPUTED_VALUE"""),"2026/1/1 改成 通用軟體 104人資系統") -> 2026/1/1 改成 通用軟體 104人資系統
B74: =IFERROR(__xludf.DUMMYFUNCTION("""COMPUTED_VALUE"""),73.0) -> 73 | C74: =IFERROR(__xludf.DUMMYFUNCTION("""COMPUTED_VALUE"""),"非人事費用") -> 非人事費用 | D74: =IFERROR(__xludf.DUMMYFUNCTION("""COMPUTED_VALUE"""),"iCHEF") -> iCHEF | E74: =IFERROR(__xludf.DUMMYFUNCTION("""COMPUTED_VALUE"""),"6x3201") -> 6x3201 | F74: =IFERROR(__xludf.DUMMYFUNCTION("""COMPUTED_VALUE"""),"其他費用") -> 其他費用 | G74: =IFERROR(__xludf.DUMMYFUNCTION("""COMPUTED_VALUE"""),"辦公軟體") -> 辦公軟體 | H74: =IFERROR(__xludf.DUMMYFUNCTION("""COMPUTED_VALUE"""),"專用軟體 Netsuite 主管/看管報帳號") -> 專用軟體 Netsuite 主管/看管報帳號 | I74: =IFERROR(__xludf.DUMMYFUNCTION("""COMPUTED_VALUE"""),1384.0) -> 1384 | J74: =IFERROR(__xludf.DUMMYFUNCTION("""COMPUTED_VALUE"""),16608.0) -> 16608 | K74: =IFERROR(__xludf.DUMMYFUNCTION("""COMPUTED_VALUE"""),"各專業中心") -> 各專業中心 | L74: =IFERROR(__xludf.DUMMYFUNCTION("""COMPUTED_VALUE"""),"各專業中心") -> 各專業中心
B75: =IFERROR(__xludf.DUMMYFUNCTION("""COMPUTED_VALUE"""),74.0) -> 74 | C75: =IFERROR(__xludf.DUMMYFUNCTION("""COMPUTED_VALUE"""),"非人事費用") -> 非人事費用 | D75: =IFERROR(__xludf.DUMMYFUNCTION("""COMPUTED_VALUE"""),"iCHEF") -> iCHEF | E75: =IFERROR(__xludf.DUMMYFUNCTION("""COMPUTED_VALUE"""),"6x3201") -> 6x3201 | F75: =IFERROR(__xludf.DUMMYFUNCTION("""COMPUTED_VALUE"""),"其他費用") -> 其他費用 | G75: =IFERROR(__xludf.DUMMYFUNCTION("""COMPUTED_VALUE"""),"辦公軟體") -> 辦公軟體 | H75: =IFERROR(__xludf.DUMMYFUNCTION("""COMPUTED_VALUE"""),"專用軟體 Netsuite 員工帳號") -> 專用軟體 Netsuite 員工帳號 | I75: =IFERROR(__xludf.DUMMYFUNCTION("""COMPUTED_VALUE"""),229.0) -> 229 | J75: =IFERROR(__xludf.DUMMYFUNCTION("""COMPUTED_VALUE"""),2748.0) -> 2748 | K75: =IFERROR(__xludf.DUMMYFUNCTION("""COMPUTED_VALUE"""),"各專業中心") -> 各專業中心 | L75: =IFERROR(__xludf.DUMMYFUNCTION("""COMPUTED_VALUE"""),"各專業中心") -> 各專業中心
B76: =IFERROR(__xludf.DUMMYFUNCTION("""COMPUTED_VALUE"""),75.0) -> 75 | C76: =IFERROR(__xludf.DUMMYFUNCTION("""COMPUTED_VALUE"""),"非人事費用") -> 非人事費用 | D76: =IFERROR(__xludf.DUMMYFUNCTION("""COMPUTED_VALUE"""),"iCHEF") -> iCHEF | E76: =IFERROR(__xludf.DUMMYFUNCTION("""COMPUTED_VALUE"""),"6x3201") -> 6x3201 | F76: =IFERROR(__xludf.DUMMYFUNCTION("""COMPUTED_VALUE"""),"其他費用") -> 其他費用 | G76: =IFERROR(__xludf.DUMMYFUNCTION("""COMPUTED_VALUE"""),"辦公軟體") -> 辦公軟體 | H76: =IFERROR(__xludf.DUMMYFUNCTION("""COMPUTED_VALUE"""),"專用軟體 Office") -> 專用軟體 Office | I76: =IFERROR(__xludf.DUMMYFUNCTION("""COMPUTED_VALUE"""),282.0) -> 282 | J76: =IFERROR(__xludf.DUMMYFUNCTION("""COMPUTED_VALUE"""),3381.0) -> 3381 | K76: =IFERROR(__xludf.DUMMYFUNCTION("""COMPUTED_VALUE"""),"各專業中心") -> 各專業中心 | L76: =IFERROR(__xludf.DUMMYFUNCTION("""COMPUTED_VALUE"""),"各專業中心") -> 各專業中心
B77: =IFERROR(__xludf.DUMMYFUNCTION("""COMPUTED_VALUE"""),76.0) -> 76 | C77: =IFERROR(__xludf.DUMMYFUNCTION("""COMPUTED_VALUE"""),"非人事費用") -> 非人事費用 | D77: =IFERROR(__xludf.DUMMYFUNCTION("""COMPUTED_VALUE"""),"iCHEF") -> iCHEF | E77: =IFERROR(__xludf.DUMMYFUNCTION("""COMPUTED_VALUE"""),"6x3201") -> 6x3201 | F77: =IFERROR(__xludf.DUMMYFUNCTION("""COMPUTED_VALUE"""),"其他費用") -> 其他費用 | G77: =IFERROR(__xludf.DUMMYFUNCTION("""COMPUTED_VALUE"""),"辦公軟體") -> 辦公軟體 | H77: =IFERROR(__xludf.DUMMYFUNCTION("""COMPUTED_VALUE"""),"專用軟體 Tableau Viewer") -> 專用軟體 Tableau Viewer | I77: =IFERROR(__xludf.DUMMYFUNCTION("""COMPUTED_VALUE"""),352.0) -> 352 | J77: =IFERROR(__xludf.DUMMYFUNCTION("""COMPUTED_VALUE"""),4224.0) -> 4224 | K77: =IFERROR(__xludf.DUMMYFUNCTION("""COMPUTED_VALUE"""),"各專業中心") -> 各專業中心 | L77: =IFERROR(__xludf.DUMMYFUNCTION("""COMPUTED_VALUE"""),"各專業中心") -> 各專業中心
B78: =IFERROR(__xludf.DUMMYFUNCTION("""COMPUTED_VALUE"""),77.0) -> 77 | C78: =IFERROR(__xludf.DUMMYFUNCTION("""COMPUTED_VALUE"""),"非人事費用") -> 非人事費用 | D78: =IFERROR(__xludf.DUMMYFUNCTION("""COMPUTED_VALUE"""),"iCHEF") -> iCHEF | E78: =IFERROR(__xludf.DUMMYFUNCTION("""COMPUTED_VALUE"""),"6x3201") -> 6x3201 | F78: =IFERROR(__xludf.DUMMYFUNCTION("""COMPUTED_VALUE"""),"其他費用") -> 其他費用 | G78: =IFERROR(__xludf.DUMMYFUNCTION("""COMPUTED_VALUE"""),"辦公軟體") -> 辦公軟體 | H78: =IFERROR(__xludf.DUMMYFUNCTION("""COMPUTED_VALUE"""),"專用軟體 Tableau Creator") -> 專用軟體 Tableau Creator | I78: =IFERROR(__xludf.DUMMYFUNCTION("""COMPUTED_VALUE"""),2354.0) -> 2354 | J78: =IFERROR(__xludf.DUMMYFUNCTION("""COMPUTED_VALUE"""),28248.0) -> 28248 | K78: =IFERROR(__xludf.DUMMYFUNCTION("""COMPUTED_VALUE"""),"各專業中心") -> 各專業中心 | L78: =IFERROR(__xludf.DUMMYFUNCTION("""COMPUTED_VALUE"""),"各專業中心") -> 各專業中心
B79: =IFERROR(__xludf.DUMMYFUNCTION("""COMPUTED_VALUE"""),78.0) -> 78 | C79: =IFERROR(__xludf.DUMMYFUNCTION("""COMPUTED_VALUE"""),"非人事費用") -> 非人事費用 | D79: =IFERROR(__xludf.DUMMYFUNCTION("""COMPUTED_VALUE"""),"iCHEF") -> iCHEF | E79: =IFERROR(__xludf.DUMMYFUNCTION("""COMPUTED_VALUE"""),"6x3201") -> 6x3201 | F79: =IFERROR(__xludf.DUMMYFUNCTION("""COMPUTED_VALUE"""),"其他費用") -> 其他費用 | G79: =IFERROR(__xludf.DUMMYFUNCTION("""COMPUTED_VALUE"""),"辦公軟體") -> 辦公軟體 | H79: =IFERROR(__xludf.DUMMYFUNCTION("""COMPUTED_VALUE"""),"專用軟體 Adobe Std") -> 專用軟體 Adobe Std | I79: =IFERROR(__xludf.DUMMYFUNCTION("""COMPUTED_VALUE"""),510.0) -> 510 | J79: =IFERROR(__xludf.DUMMYFUNCTION("""COMPUTED_VALUE"""),6120.0) -> 6120 | K79: =IFERROR(__xludf.DUMMYFUNCTION("""COMPUTED_VALUE"""),"各專業中心") -> 各專業中心 | L79: =IFERROR(__xludf.DUMMYFUNCTION("""COMPUTED_VALUE"""),"各專業中心") -> 各專業中心 | M79: =IFERROR(__xludf.DUMMYFUNCTION("""COMPUTED_VALUE"""),"匯差") -> 匯差
B80: =IFERROR(__xludf.DUMMYFUNCTION("""COMPUTED_VALUE"""),79.0) -> 79 | C80: =IFERROR(__xludf.DUMMYFUNCTION("""COMPUTED_VALUE"""),"非人事費用") -> 非人事費用 | D80: =IFERROR(__xludf.DUMMYFUNCTION("""COMPUTED_VALUE"""),"iCHEF") -> iCHEF | E80: =IFERROR(__xludf.DUMMYFUNCTION("""COMPUTED_VALUE"""),"6x3201") -> 6x3201 | F80: =IFERROR(__xludf.DUMMYFUNCTION("""COMPUTED_VALUE"""),"其他費用") -> 其他費用 | G80: =IFERROR(__xludf.DUMMYFUNCTION("""COMPUTED_VALUE"""),"辦公軟體") -> 辦公軟體 | H80: =IFERROR(__xludf.DUMMYFUNCTION("""COMPUTED_VALUE"""),"專用軟體 Adobe Creative Cloud") -> 專用軟體 Adobe Creative Cloud | I80: =IFERROR(__xludf.DUMMYFUNCTION("""COMPUTED_VALUE"""),3000.0) -> 3000 | J80: =IFERROR(__xludf.DUMMYFUNCTION("""COMPUTED_VALUE"""),36000.0) -> 36000 | K80: =IFERROR(__xludf.DUMMYFUNCTION("""COMPUTED_VALUE"""),"各專業中心") -> 各專業中心 | L80: =IFERROR(__xludf.DUMMYFUNCTION("""COMPUTED_VALUE"""),"各專業中心") -> 各專業中心 | M80: =IFERROR(__xludf.DUMMYFUNCTION("""COMPUTED_VALUE"""),"匯差") -> 匯差
B81: =IFERROR(__xludf.DUMMYFUNCTION("""COMPUTED_VALUE"""),80.0) -> 80 | C81: =IFERROR(__xludf.DUMMYFUNCTION("""COMPUTED_VALUE"""),"非人事費用") -> 非人事費用 | D81: =IFERROR(__xludf.DUMMYFUNCTION("""COMPUTED_VALUE"""),"iCHEF") -> iCHEF | E81: =IFERROR(__xludf.DUMMYFUNCTION("""COMPUTED_VALUE"""),"6x3201") -> 6x3201 | F81: =IFERROR(__xludf.DUMMYFUNCTION("""COMPUTED_VALUE"""),"其他費用") -> 其他費用 | G81: =IFERROR(__xludf.DUMMYFUNCTION("""COMPUTED_VALUE"""),"辦公軟體") -> 辦公軟體 | H81: =IFERROR(__xludf.DUMMYFUNCTION("""COMPUTED_VALUE"""),"專用軟體 Salesforce Sales Cloud") -> 專用軟體 Salesforce Sales Cloud | I81: =IFERROR(__xludf.DUMMYFUNCTION("""COMPUTED_VALUE"""),3728.0) -> 3728 | J81: =IFERROR(__xludf.DUMMYFUNCTION("""COMPUTED_VALUE"""),44730.0) -> 44730 | K81: =IFERROR(__xludf.DUMMYFUNCTION("""COMPUTED_VALUE"""),"各專業中心") -> 各專業中心 | L81: =IFERROR(__xludf.DUMMYFUNCTION("""COMPUTED_VALUE"""),"各專業中心") -> 各專業中心 | M81: =IFERROR(__xludf.DUMMYFUNCTION("""COMPUTED_VALUE"""),"續約單價上漲 USD 115.5 -> USD 124.25, 匯率下降") -> 續約單價上漲 USD 115.5 -> USD 124.25, 匯率下降
B82: =IFERROR(__xludf.DUMMYFUNCTION("""COMPUTED_VALUE"""),81.0) -> 81 | C82: =IFERROR(__xludf.DUMMYFUNCTION("""COMPUTED_VALUE"""),"非人事費用") -> 非人事費用 | D82: =IFERROR(__xludf.DUMMYFUNCTION("""COMPUTED_VALUE"""),"iCHEF") -> iCHEF | E82: =IFERROR(__xludf.DUMMYFUNCTION("""COMPUTED_VALUE"""),"6x3201") -> 6x3201 | F82: =IFERROR(__xludf.DUMMYFUNCTION("""COMPUTED_VALUE"""),"其他費用") -> 其他費用 | G82: =IFERROR(__xludf.DUMMYFUNCTION("""COMPUTED_VALUE"""),"辦公軟體") -> 辦公軟體 | H82: =IFERROR(__xludf.DUMMYFUNCTION("""COMPUTED_VALUE"""),"專用軟體 Salesforce Service Cloud") -> 專用軟體 Salesforce Service Cloud | I82: =IFERROR(__xludf.DUMMYFUNCTION("""COMPUTED_VALUE"""),3728.0) -> 3728 | J82: =IFERROR(__xludf.DUMMYFUNCTION("""COMPUTED_VALUE"""),44730.0) -> 44730 | K82: =IFERROR(__xludf.DUMMYFUNCTION("""COMPUTED_VALUE"""),"各專業中心") -> 各專業中心 | L82: =IFERROR(__xludf.DUMMYFUNCTION("""COMPUTED_VALUE"""),"各專業中心") -> 各專業中心 | M82: =IFERROR(__xludf.DUMMYFUNCTION("""COMPUTED_VALUE"""),"續約單價上漲 USD 115.5 -> USD 124.25, 匯率下降") -> 續約單價上漲 USD 115.5 -> USD 124.25, 匯率下降
B83: =IFERROR(__xludf.DUMMYFUNCTION("""COMPUTED_VALUE"""),82.0) -> 82 | C83: =IFERROR(__xludf.DUMMYFUNCTION("""COMPUTED_VALUE"""),"非人事費用") -> 非人事費用 | D83: =IFERROR(__xludf.DUMMYFUNCTION("""COMPUTED_VALUE"""),"iCHEF") -> iCHEF | E83: =IFERROR(__xludf.DUMMYFUNCTION("""COMPUTED_VALUE"""),"6x3201") -> 6x3201 | F83: =IFERROR(__xludf.DUMMYFUNCTION("""COMPUTED_VALUE"""),"其他費用") -> 其他費用 | G83: =IFERROR(__xludf.DUMMYFUNCTION("""COMPUTED_VALUE"""),"辦公軟體") -> 辦公軟體 | H83: =IFERROR(__xludf.DUMMYFUNCTION("""COMPUTED_VALUE"""),"專用軟體 Salesforce Sales+Service Cloud") -> 專用軟體 Salesforce Sales+Service Cloud | I83: =IFERROR(__xludf.DUMMYFUNCTION("""COMPUTED_VALUE"""),4680.0) -> 4680 | J83: =IFERROR(__xludf.DUMMYFUNCTION("""COMPUTED_VALUE"""),56160.0) -> 56160 | K83: =IFERROR(__xludf.DUMMYFUNCTION("""COMPUTED_VALUE"""),"各專業中心") -> 各專業中心 | L83: =IFERROR(__xludf.DUMMYFUNCTION("""COMPUTED_VALUE"""),"各專業中心") -> 各專業中心 | M83: =IFERROR(__xludf.DUMMYFUNCTION("""COMPUTED_VALUE"""),"續約單價上漲 USD 147-> USD 156, 匯率下降") -> 續約單價上漲 USD 147-> USD 156, 匯率下降
B84: =IFERROR(__xludf.DUMMYFUNCTION("""COMPUTED_VALUE"""),83.0) -> 83 | C84: =IFERROR(__xludf.DUMMYFUNCTION("""COMPUTED_VALUE"""),"非人事費用") -> 非人事費用 | D84: =IFERROR(__xludf.DUMMYFUNCTION("""COMPUTED_VALUE"""),"iCHEF") -> iCHEF | E84: =IFERROR(__xludf.DUMMYFUNCTION("""COMPUTED_VALUE"""),"6x3201") -> 6x3201 | F84: =IFERROR(__xludf.DUMMYFUNCTION("""COMPUTED_VALUE"""),"其他費用") -> 其他費用 | G84: =IFERROR(__xludf.DUMMYFUNCTION("""COMPUTED_VALUE"""),"辦公軟體") -> 辦公軟體 | H84: =IFERROR(__xludf.DUMMYFUNCTION("""COMPUTED_VALUE"""),"通用軟體 Asana") -> 通用軟體 Asana | I84: =IFERROR(__xludf.DUMMYFUNCTION("""COMPUTED_VALUE"""),830.0) -> 830 | J84: =IFERROR(__xludf.DUMMYFUNCTION("""COMPUTED_VALUE"""),9960.0) -> 9960 | K84: =IFERROR(__xludf.DUMMYFUNCTION("""COMPUTED_VALUE"""),"各專業中心") -> 各專業中心 | L84: =IFERROR(__xludf.DUMMYFUNCTION("""COMPUTED_VALUE"""),"各專業中心") -> 各專業中心 | M84: =IFERROR(__xludf.DUMMYFUNCTION("""COMPUTED_VALUE"""),"新項目, 通用軟體單獨計算") -> 新項目, 通用軟體單獨計算
B85: =IFERROR(__xludf.DUMMYFUNCTION("""COMPUTED_VALUE"""),84.0) -> 84 | C85: =IFERROR(__xludf.DUMMYFUNCTION("""COMPUTED_VALUE"""),"非人事費用") -> 非人事費用 | D85: =IFERROR(__xludf.DUMMYFUNCTION("""COMPUTED_VALUE"""),"iCHEF") -> iCHEF | E85: =IFERROR(__xludf.DUMMYFUNCTION("""COMPUTED_VALUE"""),"6x3201") -> 6x3201 | F85: =IFERROR(__xludf.DUMMYFUNCTION("""COMPUTED_VALUE"""),"其他費用") -> 其他費用 | G85: =IFERROR(__xludf.DUMMYFUNCTION("""COMPUTED_VALUE"""),"辦公軟體") -> 辦公軟體 | H85: =IFERROR(__xludf.DUMMYFUNCTION("""COMPUTED_VALUE"""),"通用軟體 Notion") -> 通用軟體 Notion | I85: =IFERROR(__xludf.DUMMYFUNCTION("""COMPUTED_VALUE"""),300.0) -> 300 | J85: =IFERROR(__xludf.DUMMYFUNCTION("""COMPUTED_VALUE"""),3600.0) -> 3600 | K85: =IFERROR(__xludf.DUMMYFUNCTION("""COMPUTED_VALUE"""),"各專業中心") -> 各專業中心 | L85: =IFERROR(__xludf.DUMMYFUNCTION("""COMPUTED_VALUE"""),"各專業中心") -> 各專業中心 | M85: =IFERROR(__xludf.DUMMYFUNCTION("""COMPUTED_VALUE"""),"新項目, 通用軟體單獨計算") -> 新項目, 通用軟體單獨計算
B86: =IFERROR(__xludf.DUMMYFUNCTION("""COMPUTED_VALUE"""),85.0) -> 85 | C86: =IFERROR(__xludf.DUMMYFUNCTION("""COMPUTED_VALUE"""),"非人事費用") -> 非人事費用 | D86: =IFERROR(__xludf.DUMMYFUNCTION("""COMPUTED_VALUE"""),"iCHEF") -> iCHEF | E86: =IFERROR(__xludf.DUMMYFUNCTION("""COMPUTED_VALUE"""),"6x3201") -> 6x3201 | F86: =IFERROR(__xludf.DUMMYFUNCTION("""COMPUTED_VALUE"""),"其他費用") -> 其他費用 | G86: =IFERROR(__xludf.DUMMYFUNCTION("""COMPUTED_VALUE"""),"辦公軟體") -> 辦公軟體 | H86: =IFERROR(__xludf.DUMMYFUNCTION("""COMPUTED_VALUE"""),"通用軟體 Slack") -> 通用軟體 Slack | I86: =IFERROR(__xludf.DUMMYFUNCTION("""COMPUTED_VALUE"""),218.0) -> 218 | J86: =IFERROR(__xludf.DUMMYFUNCTION("""COMPUTED_VALUE"""),2616.0) -> 2616 | K86: =IFERROR(__xludf.DUMMYFUNCTION("""COMPUTED_VALUE"""),"各專業中心") -> 各專業中心 | L86: =IFERROR(__xludf.DUMMYFUNCTION("""COMPUTED_VALUE"""),"各專業中心") -> 各專業中心 | M86: =IFERROR(__xludf.DUMMYFUNCTION("""COMPUTED_VALUE"""),"新項目, 通用軟體單獨計算") -> 新項目, 通用軟體單獨計算
B87: =IFERROR(__xludf.DUMMYFUNCTION("""COMPUTED_VALUE"""),86.0) -> 86 | C87: =IFERROR(__xludf.DUMMYFUNCTION("""COMPUTED_VALUE"""),"非人事費用") -> 非人事費用 | D87: =IFERROR(__xludf.DUMMYFUNCTION("""COMPUTED_VALUE"""),"iCHEF") -> iCHEF | E87: =IFERROR(__xludf.DUMMYFUNCTION("""COMPUTED_VALUE"""),"6x3201") -> 6x3201 | F87: =IFERROR(__xludf.DUMMYFUNCTION("""COMPUTED_VALUE"""),"其他費用") -> 其他費用 | G87: =IFERROR(__xludf.DUMMYFUNCTION("""COMPUTED_VALUE"""),"辦公軟體") -> 辦公軟體 | H87: =IFERROR(__xludf.DUMMYFUNCTION("""COMPUTED_VALUE"""),"辦公室VPN") -> 辦公室VPN | I87: =IFERROR(__xludf.DUMMYFUNCTION("""COMPUTED_VALUE"""),100.0) -> 100 | J87: =IFERROR(__xludf.DUMMYFUNCTION("""COMPUTED_VALUE"""),1200.0) -> 1200 | K87: =IFERROR(__xludf.DUMMYFUNCTION("""COMPUTED_VALUE"""),"各專業中心") -> 各專業中心 | L87: =IFERROR(__xludf.DUMMYFUNCTION("""COMPUTED_VALUE"""),"各專業中心") -> 各專業中心 | M87: =IFERROR(__xludf.DUMMYFUNCTION("""COMPUTED_VALUE"""),"新項目, 2025 沒攤給各中心, 2026 攤給各中心") -> 新項目, 2025 沒攤給各中心, 2026 攤給各中心
B88: =IFERROR(__xludf.DUMMYFUNCTION("""COMPUTED_VALUE"""),87.0) -> 87 | C88: =IFERROR(__xludf.DUMMYFUNCTION("""COMPUTED_VALUE"""),"非人事費用") -> 非人事費用 | D88: =IFERROR(__xludf.DUMMYFUNCTION("""COMPUTED_VALUE"""),"iCHEF") -> iCHEF | E88: =IFERROR(__xludf.DUMMYFUNCTION("""COMPUTED_VALUE"""),"6x3201") -> 6x3201 | F88: =IFERROR(__xludf.DUMMYFUNCTION("""COMPUTED_VALUE"""),"其他費用") -> 其他費用 | G88: =IFERROR(__xludf.DUMMYFUNCTION("""COMPUTED_VALUE"""),"辦公軟體") -> 辦公軟體 | H88: =IFERROR(__xludf.DUMMYFUNCTION("""COMPUTED_VALUE"""),"點點簽") -> 點點簽 | I88: =IFERROR(__xludf.DUMMYFUNCTION("""COMPUTED_VALUE"""),450.0) -> 450 | J88: =IFERROR(__xludf.DUMMYFUNCTION("""COMPUTED_VALUE"""),5400.0) -> 5400 | K88: =IFERROR(__xludf.DUMMYFUNCTION("""COMPUTED_VALUE"""),"各專業中心") -> 各專業中心 | L88: =IFERROR(__xludf.DUMMYFUNCTION("""COMPUTED_VALUE"""),"各專業中心") -> 各專業中心 | M88: =IFERROR(__xludf.DUMMYFUNCTION("""COMPUTED_VALUE"""),"新項目, 2025 轉給資訊管理") -> 新項目, 2025 轉給資訊管理
B89: =IFERROR(__xludf.DUMMYFUNCTION("""COMPUTED_VALUE"""),88.0) -> 88 | C89: =IFERROR(__xludf.DUMMYFUNCTION("""COMPUTED_VALUE"""),"非人事費用") -> 非人事費用 | D89: =IFERROR(__xludf.DUMMYFUNCTION("""COMPUTED_VALUE"""),"QLR") -> QLR | E89: =IFERROR(__xludf.DUMMYFUNCTION("""COMPUTED_VALUE"""),"6x3201") -> 6x3201 | F89: =IFERROR(__xludf.DUMMYFUNCTION("""COMPUTED_VALUE"""),"其他費用") -> 其他費用 | G89: =IFERROR(__xludf.DUMMYFUNCTION("""COMPUTED_VALUE"""),"辦公軟體") -> 辦公軟體 | H89: =IFERROR(__xludf.DUMMYFUNCTION("""COMPUTED_VALUE"""),"通用軟體 GWS") -> 通用軟體 GWS | I89: =IFERROR(__xludf.DUMMYFUNCTION("""COMPUTED_VALUE"""),180.0) -> 180 | J89: =IFERROR(__xludf.DUMMYFUNCTION("""COMPUTED_VALUE"""),2160.0) -> 2160 | K89: =IFERROR(__xludf.DUMMYFUNCTION("""COMPUTED_VALUE"""),"各專業中心") -> 各專業中心 | L89: =IFERROR(__xludf.DUMMYFUNCTION("""COMPUTED_VALUE"""),"各專業中心") -> 各專業中心 | M89: =IFERROR(__xludf.DUMMYFUNCTION("""COMPUTED_VALUE"""),"新項目, 通用軟體單獨計算") -> 新項目, 通用軟體單獨計算
B90: =IFERROR(__xludf.DUMMYFUNCTION("""COMPUTED_VALUE"""),89.0) -> 89 | C90: =IFERROR(__xludf.DUMMYFUNCTION("""COMPUTED_VALUE"""),"非人事費用") -> 非人事費用 | D90: =IFERROR(__xludf.DUMMYFUNCTION("""COMPUTED_VALUE"""),"QLR") -> QLR | E90: =IFERROR(__xludf.DUMMYFUNCTION("""COMPUTED_VALUE"""),"6x3201") -> 6x3201 | F90: =IFERROR(__xludf.DUMMYFUNCTION("""COMPUTED_VALUE"""),"其他費用") -> 其他費用 | G90: =IFERROR(__xludf.DUMMYFUNCTION("""COMPUTED_VALUE"""),"辦公軟體") -> 辦公軟體 | H90: =IFERROR(__xludf.DUMMYFUNCTION("""COMPUTED_VALUE"""),"專用軟體 Netsuite 主管/看管報帳號") -> 專用軟體 Netsuite 主管/看管報帳號 | I90: =IFERROR(__xludf.DUMMYFUNCTION("""COMPUTED_VALUE"""),1384.0) -> 1384 | J90: =IFERROR(__xludf.DUMMYFUNCTION("""COMPUTED_VALUE"""),16608.0) -> 16608 | K90: =IFERROR(__xludf.DUMMYFUNCTION("""COMPUTED_VALUE"""),"各專業中心") -> 各專業中心 | L90: =IFERROR(__xludf.DUMMYFUNCTION("""COMPUTED_VALUE"""),"各專業中心") -> 各專業中心 | M90: =IFERROR(__xludf.DUMMYFUNCTION("""COMPUTED_VALUE"""),"新項目, 通用軟體單獨計算") -> 新項目, 通用軟體單獨計算
B91: =IFERROR(__xludf.DUMMYFUNCTION("""COMPUTED_VALUE"""),90.0) -> 90 | C91: =IFERROR(__xludf.DUMMYFUNCTION("""COMPUTED_VALUE"""),"非人事費用") -> 非人事費用 | D91: =IFERROR(__xludf.DUMMYFUNCTION("""COMPUTED_VALUE"""),"QLR") -> QLR | E91: =IFERROR(__xludf.DUMMYFUNCTION("""COMPUTED_VALUE"""),"6x3201") -> 6x3201 | F91: =IFERROR(__xludf.DUMMYFUNCTION("""COMPUTED_VALUE"""),"其他費用") -> 其他費用 | G91: =IFERROR(__xludf.DUMMYFUNCTION("""COMPUTED_VALUE"""),"辦公軟體") -> 辦公軟體 | H91: =IFERROR(__xludf.DUMMYFUNCTION("""COMPUTED_VALUE"""),"專用軟體 Netsuite 員工帳號") -> 專用軟體 Netsuite 員工帳號 | I91: =IFERROR(__xludf.DUMMYFUNCTION("""COMPUTED_VALUE"""),229.0) -> 229 | J91: =IFERROR(__xludf.DUMMYFUNCTION("""COMPUTED_VALUE"""),2748.0) -> 2748 | K91: =IFERROR(__xludf.DUMMYFUNCTION("""COMPUTED_VALUE"""),"各專業中心") -> 各專業中心 | L91: =IFERROR(__xludf.DUMMYFUNCTION("""COMPUTED_VALUE"""),"各專業中心") -> 各專業中心 | M91: =IFERROR(__xludf.DUMMYFUNCTION("""COMPUTED_VALUE"""),"新項目, 通用軟體單獨計算") -> 新項目, 通用軟體單獨計算
B92: =IFERROR(__xludf.DUMMYFUNCTION("""COMPUTED_VALUE"""),91.0) -> 91 | C92: =IFERROR(__xludf.DUMMYFUNCTION("""COMPUTED_VALUE"""),"非人事費用") -> 非人事費用 | D92: =IFERROR(__xludf.DUMMYFUNCTION("""COMPUTED_VALUE"""),"QLR") -> QLR | E92: =IFERROR(__xludf.DUMMYFUNCTION("""COMPUTED_VALUE"""),"6x3201") -> 6x3201 | F92: =IFERROR(__xludf.DUMMYFUNCTION("""COMPUTED_VALUE"""),"其他費用") -> 其他費用 | G92: =IFERROR(__xludf.DUMMYFUNCTION("""COMPUTED_VALUE"""),"辦公軟體") -> 辦公軟體 | H92: =IFERROR(__xludf.DUMMYFUNCTION("""COMPUTED_VALUE"""),"通用軟體 Asana") -> 通用軟體 Asana | I92: =IFERROR(__xludf.DUMMYFUNCTION("""COMPUTED_VALUE"""),750.0) -> 750 | J92: =IFERROR(__xludf.DUMMYFUNCTION("""COMPUTED_VALUE"""),9000.0) -> 9000 | K92: =IFERROR(__xludf.DUMMYFUNCTION("""COMPUTED_VALUE"""),"各專業中心") -> 各專業中心 | L92: =IFERROR(__xludf.DUMMYFUNCTION("""COMPUTED_VALUE"""),"各專業中心") -> 各專業中心 | M92: =IFERROR(__xludf.DUMMYFUNCTION("""COMPUTED_VALUE"""),"新項目, 通用軟體單獨計算") -> 新項目, 通用軟體單獨計算
B93: =IFERROR(__xludf.DUMMYFUNCTION("""COMPUTED_VALUE"""),92.0) -> 92 | C93: =IFERROR(__xludf.DUMMYFUNCTION("""COMPUTED_VALUE"""),"非人事費用") -> 非人事費用 | D93: =IFERROR(__xludf.DUMMYFUNCTION("""COMPUTED_VALUE"""),"QLR") -> QLR | E93: =IFERROR(__xludf.DUMMYFUNCTION("""COMPUTED_VALUE"""),"6x3201") -> 6x3201 | F93: =IFERROR(__xludf.DUMMYFUNCTION("""COMPUTED_VALUE"""),"其他費用") -> 其他費用 | G93: =IFERROR(__xludf.DUMMYFUNCTION("""COMPUTED_VALUE"""),"辦公軟體") -> 辦公軟體 | H93: =IFERROR(__xludf.DUMMYFUNCTION("""COMPUTED_VALUE"""),"通用軟體 Notion") -> 通用軟體 Notion | I93: =IFERROR(__xludf.DUMMYFUNCTION("""COMPUTED_VALUE"""),300.0) -> 300 | J93: =IFERROR(__xludf.DUMMYFUNCTION("""COMPUTED_VALUE"""),3600.0) -> 3600 | K93: =IFERROR(__xludf.DUMMYFUNCTION("""COMPUTED_VALUE"""),"各專業中心") -> 各專業中心 | L93: =IFERROR(__xludf.DUMMYFUNCTION("""COMPUTED_VALUE"""),"各專業中心") -> 各專業中心 | M93: =IFERROR(__xludf.DUMMYFUNCTION("""COMPUTED_VALUE"""),"新項目, 通用軟體單獨計算") -> 新項目, 通用軟體單獨計算
B94: =IFERROR(__xludf.DUMMYFUNCTION("""COMPUTED_VALUE"""),93.0) -> 93 | C94: =IFERROR(__xludf.DUMMYFUNCTION("""COMPUTED_VALUE"""),"非人事費用") -> 非人事費用 | D94: =IFERROR(__xludf.DUMMYFUNCTION("""COMPUTED_VALUE"""),"QLR") -> QLR | E94: =IFERROR(__xludf.DUMMYFUNCTION("""COMPUTED_VALUE"""),"6x3201") -> 6x3201 | F94: =IFERROR(__xludf.DUMMYFUNCTION("""COMPUTED_VALUE"""),"其他費用") -> 其他費用 | G94: =IFERROR(__xludf.DUMMYFUNCTION("""COMPUTED_VALUE"""),"辦公軟體") -> 辦公軟體 | H94: =IFERROR(__xludf.DUMMYFUNCTION("""COMPUTED_VALUE"""),"通用軟體 Slack") -> 通用軟體 Slack | I94: =IFERROR(__xludf.DUMMYFUNCTION("""COMPUTED_VALUE"""),203.0) -> 203 | J94: =IFERROR(__xludf.DUMMYFUNCTION("""COMPUTED_VALUE"""),2436.0) -> 2436 | K94: =IFERROR(__xludf.DUMMYFUNCTION("""COMPUTED_VALUE"""),"各專業中心") -> 各專業中心 | L94: =IFERROR(__xludf.DUMMYFUNCTION("""COMPUTED_VALUE"""),"各專業中心") -> 各專業中心 | M94: =IFERROR(__xludf.DUMMYFUNCTION("""COMPUTED_VALUE"""),"新項目, 通用軟體單獨計算") -> 新項目, 通用軟體單獨計算

Sheet 中心專用帳號盤點
B1: =IFERROR(__xludf.DUMMYFUNCTION("IMPORTRANGE(""https://docs.google.com/spreadsheets/d/1gsXoI5zM-IbJ26IzdPrtU33yQaJeMN9ebORVtKwXYdI/edit?gid=613934984#gid=613934984"",""2026 各中心需求匯總!A1:z"")"),"子公司") -> 子公司 | C1: =IFERROR(__xludf.DUMMYFUNCTION("""COMPUTED_VALUE"""),"事業單位") -> 事業單位 | D1: =IFERROR(__xludf.DUMMYFUNCTION("""COMPUTED_VALUE"""),"Si 編號") -> Si 編號 | E1: =IFERROR(__xludf.DUMMYFUNCTION("""COMPUTED_VALUE"""),"TA 編號") -> TA 編號 | F1: =IFERROR(__xludf.DUMMYFUNCTION("""COMPUTED_VALUE"""),"費用單位") -> 費用單位 | G1: =IFERROR(__xludf.DUMMYFUNCTION("""COMPUTED_VALUE"""),"費用項目") -> 費用項目 | H1: =IFERROR(__xludf.DUMMYFUNCTION("""COMPUTED_VALUE"""),"單價") -> 單價 | I1: =IFERROR(__xludf.DUMMYFUNCTION("""COMPUTED_VALUE"""),"現有帳號數量") -> 現有帳號數量 | J1: =IFERROR(__xludf.DUMMYFUNCTION("""COMPUTED_VALUE"""),"現有每月費用") -> 現有每月費用 | K1: =IFERROR(__xludf.DUMMYFUNCTION("""COMPUTED_VALUE"""),"預計新人帳號數量") -> 預計新人帳號數量 | L1: =IFERROR(__xludf.DUMMYFUNCTION("""COMPUTED_VALUE"""),"預計新人費用") -> 預計新人費用
B2: =IFERROR(__xludf.DUMMYFUNCTION("""COMPUTED_VALUE"""),"歸屬子公司，例如:TW、QLR") -> 歸屬子公司，例如:TW、QLR | C2: =IFERROR(__xludf.DUMMYFUNCTION("""COMPUTED_VALUE"""),"不需填寫") -> 不需填寫 | D2: =IFERROR(__xludf.DUMMYFUNCTION("""COMPUTED_VALUE"""),"不需填寫") -> 不需填寫 | E2: =IFERROR(__xludf.DUMMYFUNCTION("""COMPUTED_VALUE"""),"不需填寫") -> 不需填寫 | F2: =IFERROR(__xludf.DUMMYFUNCTION("""COMPUTED_VALUE"""),"需按中心/部門/團隊規格，例如：行銷營運中心:銷售營運部:導入教練團隊") -> 需按中心/部門/團隊規格，例如：行銷營運中心:銷售營運部:導入教練團隊 | G2: =IFERROR(__xludf.DUMMYFUNCTION("""COMPUTED_VALUE"""),"請填寫工具名稱與品項，例如：Tableau Viewer 帳號") -> 請填寫工具名稱與品項，例如：Tableau Viewer 帳號 | H2: =IFERROR(__xludf.DUMMYFUNCTION("""COMPUTED_VALUE"""),"填品項金額，例如 300") -> 填品項金額，例如 300 | I2: =IFERROR(__xludf.DUMMYFUNCTION("""COMPUTED_VALUE"""),"填寫現有員工帳號數，例如：3") -> 填寫現有員工帳號數，例如：3 | J2: =IFERROR(__xludf.DUMMYFUNCTION("""COMPUTED_VALUE"""),"公式：單價 x 現有帳號數量") -> 公式：單價 x 現有帳號數量 | K2: =IFERROR(__xludf.DUMMYFUNCTION("""COMPUTED_VALUE"""),"填寫新員工帳號數，例如：3") -> 填寫新員工帳號數，例如：3 | L2: =IFERROR(__xludf.DUMMYFUNCTION("""COMPUTED_VALUE"""),"公式：單價 x 預計新人帳號數量") -> 公式：單價 x 預計新人帳號數量
B3: =IFERROR(__xludf.DUMMYFUNCTION("""COMPUTED_VALUE"""),"TW") -> TW | F3: =IFERROR(__xludf.DUMMYFUNCTION("""COMPUTED_VALUE"""),"行銷營運中心") -> 行銷營運中心 | G3: =IFERROR(__xludf.DUMMYFUNCTION("""COMPUTED_VALUE"""),"VPN (辦公室網路)") -> VPN (辦公室網路) | H3: =IFERROR(__xludf.DUMMYFUNCTION("""COMPUTED_VALUE"""),100.0) -> 100 | I3: =IFERROR(__xludf.DUMMYFUNCTION("""COMPUTED_VALUE"""),26.0) -> 26 | J3: =IFERROR(__xludf.DUMMYFUNCTION("""COMPUTED_VALUE"""),2600.0) -> 2600
B4: =IFERROR(__xludf.DUMMYFUNCTION("""COMPUTED_VALUE"""),"TW") -> TW | F4: =IFERROR(__xludf.DUMMYFUNCTION("""COMPUTED_VALUE"""),"研發中心") -> 研發中心 | G4: =IFERROR(__xludf.DUMMYFUNCTION("""COMPUTED_VALUE"""),"VPN (辦公室網路)") -> VPN (辦公室網路) | H4: =IFERROR(__xludf.DUMMYFUNCTION("""COMPUTED_VALUE"""),100.0) -> 100 | I4: =IFERROR(__xludf.DUMMYFUNCTION("""COMPUTED_VALUE"""),31.0) -> 31 | J4: =IFERROR(__xludf.DUMMYFUNCTION("""COMPUTED_VALUE"""),3100.0) -> 3100
B5: =IFERROR(__xludf.DUMMYFUNCTION("""COMPUTED_VALUE"""),"TW") -> TW | F5: =IFERROR(__xludf.DUMMYFUNCTION("""COMPUTED_VALUE"""),"客戶價值中心") -> 客戶價值中心 | G5: =IFERROR(__xludf.DUMMYFUNCTION("""COMPUTED_VALUE"""),"VPN (辦公室網路)") -> VPN (辦公室網路) | H5: =IFERROR(__xludf.DUMMYFUNCTION("""COMPUTED_VALUE"""),100.0) -> 100 | I5: =IFERROR(__xludf.DUMMYFUNCTION("""COMPUTED_VALUE"""),27.0) -> 27 | J5: =IFERROR(__xludf.DUMMYFUNCTION("""COMPUTED_VALUE"""),2700.0) -> 2700
B6: =IFERROR(__xludf.DUMMYFUNCTION("""COMPUTED_VALUE"""),"TW") -> TW | F6: =IFERROR(__xludf.DUMMYFUNCTION("""COMPUTED_VALUE"""),"管理中心") -> 管理中心 | G6: =IFERROR(__xludf.DUMMYFUNCTION("""COMPUTED_VALUE"""),"VPN (辦公室網路)") -> VPN (辦公室網路) | H6: =IFERROR(__xludf.DUMMYFUNCTION("""COMPUTED_VALUE"""),100.0) -> 100 | I6: =IFERROR(__xludf.DUMMYFUNCTION("""COMPUTED_VALUE"""),0.0) -> 0 | J6: =IFERROR(__xludf.DUMMYFUNCTION("""COMPUTED_VALUE"""),0.0) -> 0
B7: =IFERROR(__xludf.DUMMYFUNCTION("""COMPUTED_VALUE"""),"TW") -> TW | F7: =IFERROR(__xludf.DUMMYFUNCTION("""COMPUTED_VALUE"""),"執行長室") -> 執行長室 | G7: =IFERROR(__xludf.DUMMYFUNCTION("""COMPUTED_VALUE"""),"VPN (辦公室網路)") -> VPN (辦公室網路) | H7: =IFERROR(__xludf.DUMMYFUNCTION("""COMPUTED_VALUE"""),100.0) -> 100 | I7: =IFERROR(__xludf.DUMMYFUNCTION("""COMPUTED_VALUE"""),0.0) -> 0 | J7: =IFERROR(__xludf.DUMMYFUNCTION("""COMPUTED_VALUE"""),0.0) -> 0
B8: =IFERROR(__xludf.DUMMYFUNCTION("""COMPUTED_VALUE"""),"TW") -> TW | F8: =IFERROR(__xludf.DUMMYFUNCTION("""COMPUTED_VALUE"""),"財務中心") -> 財務中心 | G8: =IFERROR(__xludf.DUMMYFUNCTION("""COMPUTED_VALUE"""),"VPN (辦公室網路)") -> VPN (辦公室網路) | H8: =IFERROR(__xludf.DUMMYFUNCTION("""COMPUTED_VALUE"""),100.0) -> 100 | I8: =IFERROR(__xludf.DUMMYFUNCTION("""COMPUTED_VALUE"""),0.0) -> 0 | J8: =IFERROR(__xludf.DUMMYFUNCTION("""COMPUTED_VALUE"""),0.0) -> 0
B9: =IFERROR(__xludf.DUMMYFUNCTION("""COMPUTED_VALUE"""),"QLR") -> QLR | F9: =IFERROR(__xludf.DUMMYFUNCTION("""COMPUTED_VALUE"""),"Qlieer") -> Qlieer | G9: =IFERROR(__xludf.DUMMYFUNCTION("""COMPUTED_VALUE"""),"VPN (辦公室網路)") -> VPN (辦公室網路) | H9: =IFERROR(__xludf.DUMMYFUNCTION("""COMPUTED_VALUE"""),100.0) -> 100 | I9: =IFERROR(__xludf.DUMMYFUNCTION("""COMPUTED_VALUE"""),0.0) -> 0 | J9: =IFERROR(__xludf.DUMMYFUNCTION("""COMPUTED_VALUE"""),0.0) -> 0
B10: =IFERROR(__xludf.DUMMYFUNCTION("""COMPUTED_VALUE"""),"TW") -> TW | F10: =IFERROR(__xludf.DUMMYFUNCTION("""COMPUTED_VALUE"""),"策略資料中心") -> 策略資料中心 | G10: =IFERROR(__xludf.DUMMYFUNCTION("""COMPUTED_VALUE"""),"VPN (辦公室網路)") -> VPN (辦公室網路) | H10: =IFERROR(__xludf.DUMMYFUNCTION("""COMPUTED_VALUE"""),100.0) -> 100 | I10: =IFERROR(__xludf.DUMMYFUNCTION("""COMPUTED_VALUE"""),0.0) -> 0 | J10: =IFERROR(__xludf.DUMMYFUNCTION("""COMPUTED_VALUE"""),0.0) -> 0
B11: =IFERROR(__xludf.DUMMYFUNCTION("""COMPUTED_VALUE"""),"HK") -> HK | F11: =IFERROR(__xludf.DUMMYFUNCTION("""COMPUTED_VALUE"""),"海外執行長室") -> 海外執行長室 | G11: =IFERROR(__xludf.DUMMYFUNCTION("""COMPUTED_VALUE"""),"VPN (辦公室網路)") -> VPN (辦公室網路) | H11: =IFERROR(__xludf.DUMMYFUNCTION("""COMPUTED_VALUE"""),100.0) -> 100 | I11: =IFERROR(__xludf.DUMMYFUNCTION("""COMPUTED_VALUE"""),0.0) -> 0 | J11: =IFERROR(__xludf.DUMMYFUNCTION("""COMPUTED_VALUE"""),0.0) -> 0
B12: =IFERROR(__xludf.DUMMYFUNCTION("""COMPUTED_VALUE"""),"TW") -> TW | F12: =IFERROR(__xludf.DUMMYFUNCTION("""COMPUTED_VALUE"""),"行銷營運中心") -> 行銷營運中心 | G12: =IFERROR(__xludf.DUMMYFUNCTION("""COMPUTED_VALUE"""),"Tableau (Creator)") -> Tableau (Creator) | H12: =IFERROR(__xludf.DUMMYFUNCTION("""COMPUTED_VALUE"""),2354.0) -> 2354 | I12: =IFERROR(__xludf.DUMMYFUNCTION("""COMPUTED_VALUE"""),3.0) -> 3 | J12: =IFERROR(__xludf.DUMMYFUNCTION("""COMPUTED_VALUE"""),7062.0) -> 7062
B13: =IFERROR(__xludf.DUMMYFUNCTION("""COMPUTED_VALUE"""),"TW") -> TW | F13: =IFERROR(__xludf.DUMMYFUNCTION("""COMPUTED_VALUE"""),"研發中心") -> 研發中心 | G13: =IFERROR(__xludf.DUMMYFUNCTION("""COMPUTED_VALUE"""),"Tableau (Creator)") -> Tableau (Creator) | H13: =IFERROR(__xludf.DUMMYFUNCTION("""COMPUTED_VALUE"""),2354.0) -> 2354 | I13: =IFERROR(__xludf.DUMMYFUNCTION("""COMPUTED_VALUE"""),6.0) -> 6 | J13: =IFERROR(__xludf.DUMMYFUNCTION("""COMPUTED_VALUE"""),14124.0) -> 14124
B14: =IFERROR(__xludf.DUMMYFUNCTION("""COMPUTED_VALUE"""),"TW") -> TW | F14: =IFERROR(__xludf.DUMMYFUNCTION("""COMPUTED_VALUE"""),"客戶價值中心") -> 客戶價值中心 | G14: =IFERROR(__xludf.DUMMYFUNCTION("""COMPUTED_VALUE"""),"Tableau (Creator)") -> Tableau (Creator) | H14: =IFERROR(__xludf.DUMMYFUNCTION("""COMPUTED_VALUE"""),2354.0) -> 2354 | I14: =IFERROR(__xludf.DUMMYFUNCTION("""COMPUTED_VALUE"""),1.0) -> 1 | J14: =IFERROR(__xludf.DUMMYFUNCTION("""COMPUTED_VALUE"""),2354.0) -> 2354
B15: =IFERROR(__xludf.DUMMYFUNCTION("""COMPUTED_VALUE"""),"TW") -> TW | F15: =IFERROR(__xludf.DUMMYFUNCTION("""COMPUTED_VALUE"""),"管理中心") -> 管理中心 | G15: =IFERROR(__xludf.DUMMYFUNCTION("""COMPUTED_VALUE"""),"Tableau (Creator)") -> Tableau (Creator) | H15: =IFERROR(__xludf.DUMMYFUNCTION("""COMPUTED_VALUE"""),2354.0) -> 2354 | I15: =IFERROR(__xludf.DUMMYFUNCTION("""COMPUTED_VALUE"""),0.0) -> 0 | J15: =IFERROR(__xludf.DUMMYFUNCTION("""COMPUTED_VALUE"""),0.0) -> 0
B16: =IFERROR(__xludf.DUMMYFUNCTION("""COMPUTED_VALUE"""),"TW") -> TW | F16: =IFERROR(__xludf.DUMMYFUNCTION("""COMPUTED_VALUE"""),"執行長室") -> 執行長室 | G16: =IFERROR(__xludf.DUMMYFUNCTION("""COMPUTED_VALUE"""),"Tableau (Creator)") -> Tableau (Creator) | H16: =IFERROR(__xludf.DUMMYFUNCTION("""COMPUTED_VALUE"""),2354.0) -> 2354 | I16: =IFERROR(__xludf.DUMMYFUNCTION("""COMPUTED_VALUE"""),0.0) -> 0 | J16: =IFERROR(__xludf.DUMMYFUNCTION("""COMPUTED_VALUE"""),0.0) -> 0
B17: =IFERROR(__xludf.DUMMYFUNCTION("""COMPUTED_VALUE"""),"TW") -> TW | F17: =IFERROR(__xludf.DUMMYFUNCTION("""COMPUTED_VALUE"""),"財務中心") -> 財務中心 | G17: =IFERROR(__xludf.DUMMYFUNCTION("""COMPUTED_VALUE"""),"Tableau (Creator)") -> Tableau (Creator) | H17: =IFERROR(__xludf.DUMMYFUNCTION("""COMPUTED_VALUE"""),2354.0) -> 2354 | I17: =IFERROR(__xludf.DUMMYFUNCTION("""COMPUTED_VALUE"""),0.0) -> 0 | J17: =IFERROR(__xludf.DUMMYFUNCTION("""COMPUTED_VALUE"""),0.0) -> 0
B18: =IFERROR(__xludf.DUMMYFUNCTION("""COMPUTED_VALUE"""),"QLR") -> QLR | F18: =IFERROR(__xludf.DUMMYFUNCTION("""COMPUTED_VALUE"""),"Qlieer") -> Qlieer | G18: =IFERROR(__xludf.DUMMYFUNCTION("""COMPUTED_VALUE"""),"Tableau (Creator)") -> Tableau (Creator) | H18: =IFERROR(__xludf.DUMMYFUNCTION("""COMPUTED_VALUE"""),2354.0) -> 2354 | I18: =IFERROR(__xludf.DUMMYFUNCTION("""COMPUTED_VALUE"""),0.0) -> 0 | J18: =IFERROR(__xludf.DUMMYFUNCTION("""COMPUTED_VALUE"""),0.0) -> 0
B19: =IFERROR(__xludf.DUMMYFUNCTION("""COMPUTED_VALUE"""),"TW") -> TW | F19: =IFERROR(__xludf.DUMMYFUNCTION("""COMPUTED_VALUE"""),"策略資料中心") -> 策略資料中心 | G19: =IFERROR(__xludf.DUMMYFUNCTION("""COMPUTED_VALUE"""),"Tableau (Creator)") -> Tableau (Creator) | H19: =IFERROR(__xludf.DUMMYFUNCTION("""COMPUTED_VALUE"""),2354.0) -> 2354 | I19: =IFERROR(__xludf.DUMMYFUNCTION("""COMPUTED_VALUE"""),4.0) -> 4 | J19: =IFERROR(__xludf.DUMMYFUNCTION("""COMPUTED_VALUE"""),9416.0) -> 9416
B20: =IFERROR(__xludf.DUMMYFUNCTION("""COMPUTED_VALUE"""),"HK") -> HK | F20: =IFERROR(__xludf.DUMMYFUNCTION("""COMPUTED_VALUE"""),"海外執行長室") -> 海外執行長室 | G20: =IFERROR(__xludf.DUMMYFUNCTION("""COMPUTED_VALUE"""),"Tableau (Creator)") -> Tableau (Creator) | H20: =IFERROR(__xludf.DUMMYFUNCTION("""COMPUTED_VALUE"""),2354.0) -> 2354 | I20: =IFERROR(__xludf.DUMMYFUNCTION("""COMPUTED_VALUE"""),0.0) -> 0 | J20: =IFERROR(__xludf.DUMMYFUNCTION("""COMPUTED_VALUE"""),0.0) -> 0
B21: =IFERROR(__xludf.DUMMYFUNCTION("""COMPUTED_VALUE"""),"TW") -> TW | F21: =IFERROR(__xludf.DUMMYFUNCTION("""COMPUTED_VALUE"""),"行銷營運中心") -> 行銷營運中心 | G21: =IFERROR(__xludf.DUMMYFUNCTION("""COMPUTED_VALUE"""),"Tableau (Viewer)") -> Tableau (Viewer) | H21: =IFERROR(__xludf.DUMMYFUNCTION("""COMPUTED_VALUE"""),352.0) -> 352 | I21: =IFERROR(__xludf.DUMMYFUNCTION("""COMPUTED_VALUE"""),13.0) -> 13 | J21: =IFERROR(__xludf.DUMMYFUNCTION("""COMPUTED_VALUE"""),4576.0) -> 4576
B22: =IFERROR(__xludf.DUMMYFUNCTION("""COMPUTED_VALUE"""),"TW") -> TW | F22: =IFERROR(__xludf.DUMMYFUNCTION("""COMPUTED_VALUE"""),"研發中心") -> 研發中心 | G22: =IFERROR(__xludf.DUMMYFUNCTION("""COMPUTED_VALUE"""),"Tableau (Viewer)") -> Tableau (Viewer) | H22: =IFERROR(__xludf.DUMMYFUNCTION("""COMPUTED_VALUE"""),352.0) -> 352 | I22: =IFERROR(__xludf.DUMMYFUNCTION("""COMPUTED_VALUE"""),2.0) -> 2 | J22: =IFERROR(__xludf.DUMMYFUNCTION("""COMPUTED_VALUE"""),704.0) -> 704
B23: =IFERROR(__xludf.DUMMYFUNCTION("""COMPUTED_VALUE"""),"TW") -> TW | F23: =IFERROR(__xludf.DUMMYFUNCTION("""COMPUTED_VALUE"""),"客戶價值中心") -> 客戶價值中心 | G23: =IFERROR(__xludf.DUMMYFUNCTION("""COMPUTED_VALUE"""),"Tableau (Viewer)") -> Tableau (Viewer) | H23: =IFERROR(__xludf.DUMMYFUNCTION("""COMPUTED_VALUE"""),352.0) -> 352 | I23: =IFERROR(__xludf.DUMMYFUNCTION("""COMPUTED_VALUE"""),2.0) -> 2 | J23: =IFERROR(__xludf.DUMMYFUNCTION("""COMPUTED_VALUE"""),704.0) -> 704
B24: =IFERROR(__xludf.DUMMYFUNCTION("""COMPUTED_VALUE"""),"TW") -> TW | F24: =IFERROR(__xludf.DUMMYFUNCTION("""COMPUTED_VALUE"""),"管理中心") -> 管理中心 | G24: =IFERROR(__xludf.DUMMYFUNCTION("""COMPUTED_VALUE"""),"Tableau (Viewer)") -> Tableau (Viewer) | H24: =IFERROR(__xludf.DUMMYFUNCTION("""COMPUTED_VALUE"""),352.0) -> 352 | I24: =IFERROR(__xludf.DUMMYFUNCTION("""COMPUTED_VALUE"""),0.0) -> 0 | J24: =IFERROR(__xludf.DUMMYFUNCTION("""COMPUTED_VALUE"""),0.0) -> 0
B25: =IFERROR(__xludf.DUMMYFUNCTION("""COMPUTED_VALUE"""),"TW") -> TW | F25: =IFERROR(__xludf.DUMMYFUNCTION("""COMPUTED_VALUE"""),"執行長室") -> 執行長室 | G25: =IFERROR(__xludf.DUMMYFUNCTION("""COMPUTED_VALUE"""),"Tableau (Viewer)") -> Tableau (Viewer) | H25: =IFERROR(__xludf.DUMMYFUNCTION("""COMPUTED_VALUE"""),352.0) -> 352 | I25: =IFERROR(__xludf.DUMMYFUNCTION("""COMPUTED_VALUE"""),2.0) -> 2 | J25: =IFERROR(__xludf.DUMMYFUNCTION("""COMPUTED_VALUE"""),704.0) -> 704
B26: =IFERROR(__xludf.DUMMYFUNCTION("""COMPUTED_VALUE"""),"TW") -> TW | F26: =IFERROR(__xludf.DUMMYFUNCTION("""COMPUTED_VALUE"""),"財務中心") -> 財務中心 | G26: =IFERROR(__xludf.DUMMYFUNCTION("""COMPUTED_VALUE"""),"Tableau (Viewer)") -> Tableau (Viewer) | H26: =IFERROR(__xludf.DUMMYFUNCTION("""COMPUTED_VALUE"""),352.0) -> 352 | I26: =IFERROR(__xludf.DUMMYFUNCTION("""COMPUTED_VALUE"""),5.0) -> 5 | J26: =IFERROR(__xludf.DUMMYFUNCTION("""COMPUTED_VALUE"""),1760.0) -> 1760
B27: =IFERROR(__xludf.DUMMYFUNCTION("""COMPUTED_VALUE"""),"QLR") -> QLR | F27: =IFERROR(__xludf.DUMMYFUNCTION("""COMPUTED_VALUE"""),"Qlieer") -> Qlieer | G27: =IFERROR(__xludf.DUMMYFUNCTION("""COMPUTED_VALUE"""),"Tableau (Viewer)") -> Tableau (Viewer) | H27: =IFERROR(__xludf.DUMMYFUNCTION("""COMPUTED_VALUE"""),352.0) -> 352 | I27: =IFERROR(__xludf.DUMMYFUNCTION("""COMPUTED_VALUE"""),1.0) -> 1 | J27: =IFERROR(__xludf.DUMMYFUNCTION("""COMPUTED_VALUE"""),352.0) -> 352
B28: =IFERROR(__xludf.DUMMYFUNCTION("""COMPUTED_VALUE"""),"TW") -> TW | F28: =IFERROR(__xludf.DUMMYFUNCTION("""COMPUTED_VALUE"""),"策略資料中心") -> 策略資料中心 | G28: =IFERROR(__xludf.DUMMYFUNCTION("""COMPUTED_VALUE"""),"Tableau (Viewer)") -> Tableau (Viewer) | H28: =IFERROR(__xludf.DUMMYFUNCTION("""COMPUTED_VALUE"""),352.0) -> 352 | I28: =IFERROR(__xludf.DUMMYFUNCTION("""COMPUTED_VALUE"""),0.0) -> 0 | J28: =IFERROR(__xludf.DUMMYFUNCTION("""COMPUTED_VALUE"""),0.0) -> 0
B29: =IFERROR(__xludf.DUMMYFUNCTION("""COMPUTED_VALUE"""),"HK") -> HK | F29: =IFERROR(__xludf.DUMMYFUNCTION("""COMPUTED_VALUE"""),"海外執行長室") -> 海外執行長室 | G29: =IFERROR(__xludf.DUMMYFUNCTION("""COMPUTED_VALUE"""),"Tableau (Viewer)") -> Tableau (Viewer) | H29: =IFERROR(__xludf.DUMMYFUNCTION("""COMPUTED_VALUE"""),352.0) -> 352 | I29: =IFERROR(__xludf.DUMMYFUNCTION("""COMPUTED_VALUE"""),0.0) -> 0 | J29: =IFERROR(__xludf.DUMMYFUNCTION("""COMPUTED_VALUE"""),0.0) -> 0
B30: =IFERROR(__xludf.DUMMYFUNCTION("""COMPUTED_VALUE"""),"TW") -> TW | F30: =IFERROR(__xludf.DUMMYFUNCTION("""COMPUTED_VALUE"""),"行銷營運中心") -> 行銷營運中心 | G30: =IFERROR(__xludf.DUMMYFUNCTION("""COMPUTED_VALUE"""),"Office") -> Office | H30: =IFERROR(__xludf.DUMMYFUNCTION("""COMPUTED_VALUE"""),254.0) -> 254 | I30: =IFERROR(__xludf.DUMMYFUNCTION("""COMPUTED_VALUE"""),18.0) -> 18 | J30: =IFERROR(__xludf.DUMMYFUNCTION("""COMPUTED_VALUE"""),4572.0) -> 4572
B31: =IFERROR(__xludf.DUMMYFUNCTION("""COMPUTED_VALUE"""),"TW") -> TW | F31: =IFERROR(__xludf.DUMMYFUNCTION("""COMPUTED_VALUE"""),"研發中心") -> 研發中心 | G31: =IFERROR(__xludf.DUMMYFUNCTION("""COMPUTED_VALUE"""),"Office") -> Office | H31: =IFERROR(__xludf.DUMMYFUNCTION("""COMPUTED_VALUE"""),254.0) -> 254 | I31: =IFERROR(__xludf.DUMMYFUNCTION("""COMPUTED_VALUE"""),0.0) -> 0 | J31: =IFERROR(__xludf.DUMMYFUNCTION("""COMPUTED_VALUE"""),0.0) -> 0
B32: =IFERROR(__xludf.DUMMYFUNCTION("""COMPUTED_VALUE"""),"TW") -> TW | F32: =IFERROR(__xludf.DUMMYFUNCTION("""COMPUTED_VALUE"""),"客戶價值中心") -> 客戶價值中心 | G32: =IFERROR(__xludf.DUMMYFUNCTION("""COMPUTED_VALUE"""),"Office") -> Office | H32: =IFERROR(__xludf.DUMMYFUNCTION("""COMPUTED_VALUE"""),254.0) -> 254 | I32: =IFERROR(__xludf.DUMMYFUNCTION("""COMPUTED_VALUE"""),9.0) -> 9 | J32: =IFERROR(__xludf.DUMMYFUNCTION("""COMPUTED_VALUE"""),2286.0) -> 2286
B33: =IFERROR(__xludf.DUMMYFUNCTION("""COMPUTED_VALUE"""),"TW") -> TW | F33: =IFERROR(__xludf.DUMMYFUNCTION("""COMPUTED_VALUE"""),"管理中心") -> 管理中心 | G33: =IFERROR(__xludf.DUMMYFUNCTION("""COMPUTED_VALUE"""),"Office") -> Office | H33: =IFERROR(__xludf.DUMMYFUNCTION("""COMPUTED_VALUE"""),254.0) -> 254 | I33: =IFERROR(__xludf.DUMMYFUNCTION("""COMPUTED_VALUE"""),6.0) -> 6 | J33: =IFERROR(__xludf.DUMMYFUNCTION("""COMPUTED_VALUE"""),1524.0) -> 1524
B34: =IFERROR(__xludf.DUMMYFUNCTION("""COMPUTED_VALUE"""),"TW") -> TW | F34: =IFERROR(__xludf.DUMMYFUNCTION("""COMPUTED_VALUE"""),"執行長室") -> 執行長室 | G34: =IFERROR(__xludf.DUMMYFUNCTION("""COMPUTED_VALUE"""),"Office") -> Office | H34: =IFERROR(__xludf.DUMMYFUNCTION("""COMPUTED_VALUE"""),254.0) -> 254 | I34: =IFERROR(__xludf.DUMMYFUNCTION("""COMPUTED_VALUE"""),1.0) -> 1 | J34: =IFERROR(__xludf.DUMMYFUNCTION("""COMPUTED_VALUE"""),254.0) -> 254
B35: =IFERROR(__xludf.DUMMYFUNCTION("""COMPUTED_VALUE"""),"TW") -> TW | F35: =IFERROR(__xludf.DUMMYFUNCTION("""COMPUTED_VALUE"""),"財務中心") -> 財務中心 | G35: =IFERROR(__xludf.DUMMYFUNCTION("""COMPUTED_VALUE"""),"Office") -> Office | H35: =IFERROR(__xludf.DUMMYFUNCTION("""COMPUTED_VALUE"""),254.0) -> 254 | I35: =IFERROR(__xludf.DUMMYFUNCTION("""COMPUTED_VALUE"""),3.0) -> 3 | J35: =IFERROR(__xludf.DUMMYFUNCTION("""COMPUTED_VALUE"""),762.0) -> 762
B36: =IFERROR(__xludf.DUMMYFUNCTION("""COMPUTED_VALUE"""),"QLR") -> QLR | F36: =IFERROR(__xludf.DUMMYFUNCTION("""COMPUTED_VALUE"""),"Qlieer") -> Qlieer | G36: =IFERROR(__xludf.DUMMYFUNCTION("""COMPUTED_VALUE"""),"Office") -> Office | H36: =IFERROR(__xludf.DUMMYFUNCTION("""COMPUTED_VALUE"""),254.0) -> 254 | I36: =IFERROR(__xludf.DUMMYFUNCTION("""COMPUTED_VALUE"""),0.0) -> 0 | J36: =IFERROR(__xludf.DUMMYFUNCTION("""COMPUTED_VALUE"""),0.0) -> 0
B37: =IFERROR(__xludf.DUMMYFUNCTION("""COMPUTED_VALUE"""),"TW") -> TW | F37: =IFERROR(__xludf.DUMMYFUNCTION("""COMPUTED_VALUE"""),"策略資料中心") -> 策略資料中心 | G37: =IFERROR(__xludf.DUMMYFUNCTION("""COMPUTED_VALUE"""),"Office") -> Office | H37: =IFERROR(__xludf.DUMMYFUNCTION("""COMPUTED_VALUE"""),254.0) -> 254 | I37: =IFERROR(__xludf.DUMMYFUNCTION("""COMPUTED_VALUE"""),1.0) -> 1 | J37: =IFERROR(__xludf.DUMMYFUNCTION("""COMPUTED_VALUE"""),254.0) -> 254
B38: =IFERROR(__xludf.DUMMYFUNCTION("""COMPUTED_VALUE"""),"HK") -> HK | F38: =IFERROR(__xludf.DUMMYFUNCTION("""COMPUTED_VALUE"""),"海外執行長室") -> 海外執行長室 | G38: =IFERROR(__xludf.DUMMYFUNCTION("""COMPUTED_VALUE"""),"Office") -> Office | H38: =IFERROR(__xludf.DUMMYFUNCTION("""COMPUTED_VALUE"""),254.0) -> 254 | I38: =IFERROR(__xludf.DUMMYFUNCTION("""COMPUTED_VALUE"""),0.0) -> 0 | J38: =IFERROR(__xludf.DUMMYFUNCTION("""COMPUTED_VALUE"""),0.0) -> 0
B39: =IFERROR(__xludf.DUMMYFUNCTION("""COMPUTED_VALUE"""),"TW") -> TW | F39: =IFERROR(__xludf.DUMMYFUNCTION("""COMPUTED_VALUE"""),"行銷營運中心") -> 行銷營運中心 | G39: =IFERROR(__xludf.DUMMYFUNCTION("""COMPUTED_VALUE"""),"Adobe Creative Cloud") -> Adobe Creative Cloud | H39: =IFERROR(__xludf.DUMMYFUNCTION("""COMPUTED_VALUE"""),3000.0) -> 3000 | I39: =IFERROR(__xludf.DUMMYFUNCTION("""COMPUTED_VALUE"""),4.0) -> 4 | J39: =IFERROR(__xludf.DUMMYFUNCTION("""COMPUTED_VALUE"""),12000.0) -> 12000
B40: =IFERROR(__xludf.DUMMYFUNCTION("""COMPUTED_VALUE"""),"TW") -> TW | F40: =IFERROR(__xludf.DUMMYFUNCTION("""COMPUTED_VALUE"""),"研發中心") -> 研發中心 | G40: =IFERROR(__xludf.DUMMYFUNCTION("""COMPUTED_VALUE"""),"Adobe Creative Cloud") -> Adobe Creative Cloud | H40: =IFERROR(__xludf.DUMMYFUNCTION("""COMPUTED_VALUE"""),3000.0) -> 3000 | I40: =IFERROR(__xludf.DUMMYFUNCTION("""COMPUTED_VALUE"""),0.0) -> 0 | J40: =IFERROR(__xludf.DUMMYFUNCTION("""COMPUTED_VALUE"""),0.0) -> 0
B41: =IFERROR(__xludf.DUMMYFUNCTION("""COMPUTED_VALUE"""),"TW") -> TW | F41: =IFERROR(__xludf.DUMMYFUNCTION("""COMPUTED_VALUE"""),"客戶價值中心") -> 客戶價值中心 | G41: =IFERROR(__xludf.DUMMYFUNCTION("""COMPUTED_VALUE"""),"Adobe Creative Cloud") -> Adobe Creative Cloud | H41: =IFERROR(__xludf.DUMMYFUNCTION("""COMPUTED_VALUE"""),3000.0) -> 3000 | I41: =IFERROR(__xludf.DUMMYFUNCTION("""COMPUTED_VALUE"""),0.0) -> 0 | J41: =IFERROR(__xludf.DUMMYFUNCTION("""COMPUTED_VALUE"""),0.0) -> 0
B42: =IFERROR(__xludf.DUMMYFUNCTION("""COMPUTED_VALUE"""),"TW") -> TW | F42: =IFERROR(__xludf.DUMMYFUNCTION("""COMPUTED_VALUE"""),"管理中心") -> 管理中心 | G42: =IFERROR(__xludf.DUMMYFUNCTION("""COMPUTED_VALUE"""),"Adobe Creative Cloud") -> Adobe Creative Cloud | H42: =IFERROR(__xludf.DUMMYFUNCTION("""COMPUTED_VALUE"""),3000.0) -> 3000 | I42: =IFERROR(__xludf.DUMMYFUNCTION("""COMPUTED_VALUE"""),0.0) -> 0 | J42: =IFERROR(__xludf.DUMMYFUNCTION("""COMPUTED_VALUE"""),0.0) -> 0
B43: =IFERROR(__xludf.DUMMYFUNCTION("""COMPUTED_VALUE"""),"TW") -> TW | F43: =IFERROR(__xludf.DUMMYFUNCTION("""COMPUTED_VALUE"""),"執行長室") -> 執行長室 | G43: =IFERROR(__xludf.DUMMYFUNCTION("""COMPUTED_VALUE"""),"Adobe Creative Cloud") -> Adobe Creative Cloud | H43: =IFERROR(__xludf.DUMMYFUNCTION("""COMPUTED_VALUE"""),3000.0) -> 3000 | I43: =IFERROR(__xludf.DUMMYFUNCTION("""COMPUTED_VALUE"""),0.0) -> 0 | J43: =IFERROR(__xludf.DUMMYFUNCTION("""COMPUTED_VALUE"""),0.0) -> 0
B44: =IFERROR(__xludf.DUMMYFUNCTION("""COMPUTED_VALUE"""),"TW") -> TW | F44: =IFERROR(__xludf.DUMMYFUNCTION("""COMPUTED_VALUE"""),"財務中心") -> 財務中心 | G44: =IFERROR(__xludf.DUMMYFUNCTION("""COMPUTED_VALUE"""),"Adobe Creative Cloud") -> Adobe Creative Cloud | H44: =IFERROR(__xludf.DUMMYFUNCTION("""COMPUTED_VALUE"""),3000.0) -> 3000 | I44: =IFERROR(__xludf.DUMMYFUNCTION("""COMPUTED_VALUE"""),0.0) -> 0 | J44: =IFERROR(__xludf.DUMMYFUNCTION("""COMPUTED_VALUE"""),0.0) -> 0
B45: =IFERROR(__xludf.DUMMYFUNCTION("""COMPUTED_VALUE"""),"QLR") -> QLR | F45: =IFERROR(__xludf.DUMMYFUNCTION("""COMPUTED_VALUE"""),"Qlieer") -> Qlieer | G45: =IFERROR(__xludf.DUMMYFUNCTION("""COMPUTED_VALUE"""),"Adobe Creative Cloud") -> Adobe Creative Cloud | H45: =IFERROR(__xludf.DUMMYFUNCTION("""COMPUTED_VALUE"""),3000.0) -> 3000 | I45: =IFERROR(__xludf.DUMMYFUNCTION("""COMPUTED_VALUE"""),0.0) -> 0 | J45: =IFERROR(__xludf.DUMMYFUNCTION("""COMPUTED_VALUE"""),0.0) -> 0
B46: =IFERROR(__xludf.DUMMYFUNCTION("""COMPUTED_VALUE"""),"TW") -> TW | F46: =IFERROR(__xludf.DUMMYFUNCTION("""COMPUTED_VALUE"""),"策略資料中心") -> 策略資料中心 | G46: =IFERROR(__xludf.DUMMYFUNCTION("""COMPUTED_VALUE"""),"Adobe Creative Cloud") -> Adobe Creative Cloud | H46: =IFERROR(__xludf.DUMMYFUNCTION("""COMPUTED_VALUE"""),3000.0) -> 3000 | I46: =IFERROR(__xludf.DUMMYFUNCTION("""COMPUTED_VALUE"""),0.0) -> 0 | J46: =IFERROR(__xludf.DUMMYFUNCTION("""COMPUTED_VALUE"""),0.0) -> 0
B47: =IFERROR(__xludf.DUMMYFUNCTION("""COMPUTED_VALUE"""),"HK") -> HK | F47: =IFERROR(__xludf.DUMMYFUNCTION("""COMPUTED_VALUE"""),"海外執行長室") -> 海外執行長室 | G47: =IFERROR(__xludf.DUMMYFUNCTION("""COMPUTED_VALUE"""),"Adobe Creative Cloud") -> Adobe Creative Cloud | H47: =IFERROR(__xludf.DUMMYFUNCTION("""COMPUTED_VALUE"""),3000.0) -> 3000 | I47: =IFERROR(__xludf.DUMMYFUNCTION("""COMPUTED_VALUE"""),0.0) -> 0 | J47: =IFERROR(__xludf.DUMMYFUNCTION("""COMPUTED_VALUE"""),0.0) -> 0
B48: =IFERROR(__xludf.DUMMYFUNCTION("""COMPUTED_VALUE"""),"TW") -> TW | F48: =IFERROR(__xludf.DUMMYFUNCTION("""COMPUTED_VALUE"""),"行銷營運中心") -> 行銷營運中心 | G48: =IFERROR(__xludf.DUMMYFUNCTION("""COMPUTED_VALUE"""),"Adobe Arcobat") -> Adobe Arcobat | H48: =IFERROR(__xludf.DUMMYFUNCTION("""COMPUTED_VALUE"""),510.0) -> 510 | I48: =IFERROR(__xludf.DUMMYFUNCTION("""COMPUTED_VALUE"""),0.0) -> 0 | J48: =IFERROR(__xludf.DUMMYFUNCTION("""COMPUTED_VALUE"""),0.0) -> 0
B49: =IFERROR(__xludf.DUMMYFUNCTION("""COMPUTED_VALUE"""),"TW") -> TW | F49: =IFERROR(__xludf.DUMMYFUNCTION("""COMPUTED_VALUE"""),"研發中心") -> 研發中心 | G49: =IFERROR(__xludf.DUMMYFUNCTION("""COMPUTED_VALUE"""),"Adobe Arcobat") -> Adobe Arcobat | H49: =IFERROR(__xludf.DUMMYFUNCTION("""COMPUTED_VALUE"""),510.0) -> 510 | I49: =IFERROR(__xludf.DUMMYFUNCTION("""COMPUTED_VALUE"""),0.0) -> 0 | J49: =IFERROR(__xludf.DUMMYFUNCTION("""COMPUTED_VALUE"""),0.0) -> 0
B50: =IFERROR(__xludf.DUMMYFUNCTION("""COMPUTED_VALUE"""),"TW") -> TW | F50: =IFERROR(__xludf.DUMMYFUNCTION("""COMPUTED_VALUE"""),"客戶價值中心") -> 客戶價值中心 | G50: =IFERROR(__xludf.DUMMYFUNCTION("""COMPUTED_VALUE"""),"Adobe Arcobat") -> Adobe Arcobat | H50: =IFERROR(__xludf.DUMMYFUNCTION("""COMPUTED_VALUE"""),510.0) -> 510 | I50: =IFERROR(__xludf.DUMMYFUNCTION("""COMPUTED_VALUE"""),0.0) -> 0 | J50: =IFERROR(__xludf.DUMMYFUNCTION("""COMPUTED_VALUE"""),0.0) -> 0
B51: =IFERROR(__xludf.DUMMYFUNCTION("""COMPUTED_VALUE"""),"TW") -> TW | F51: =IFERROR(__xludf.DUMMYFUNCTION("""COMPUTED_VALUE"""),"管理中心") -> 管理中心 | G51: =IFERROR(__xludf.DUMMYFUNCTION("""COMPUTED_VALUE"""),"Adobe Arcobat") -> Adobe Arcobat | H51: =IFERROR(__xludf.DUMMYFUNCTION("""COMPUTED_VALUE"""),510.0) -> 510 | I51: =IFERROR(__xludf.DUMMYFUNCTION("""COMPUTED_VALUE"""),0.0) -> 0 | J51: =IFERROR(__xludf.DUMMYFUNCTION("""COMPUTED_VALUE"""),0.0) -> 0
B52: =IFERROR(__xludf.DUMMYFUNCTION("""COMPUTED_VALUE"""),"TW") -> TW | F52: =IFERROR(__xludf.DUMMYFUNCTION("""COMPUTED_VALUE"""),"執行長室") -> 執行長室 | G52: =IFERROR(__xludf.DUMMYFUNCTION("""COMPUTED_VALUE"""),"Adobe Arcobat") -> Adobe Arcobat | H52: =IFERROR(__xludf.DUMMYFUNCTION("""COMPUTED_VALUE"""),510.0) -> 510 | I52: =IFERROR(__xludf.DUMMYFUNCTION("""COMPUTED_VALUE"""),1.0) -> 1 | J52: =IFERROR(__xludf.DUMMYFUNCTION("""COMPUTED_VALUE"""),510.0) -> 510
B53: =IFERROR(__xludf.DUMMYFUNCTION("""COMPUTED_VALUE"""),"TW") -> TW | F53: =IFERROR(__xludf.DUMMYFUNCTION("""COMPUTED_VALUE"""),"財務中心") -> 財務中心 | G53: =IFERROR(__xludf.DUMMYFUNCTION("""COMPUTED_VALUE"""),"Adobe Arcobat") -> Adobe Arcobat | H53: =IFERROR(__xludf.DUMMYFUNCTION("""COMPUTED_VALUE"""),510.0) -> 510 | I53: =IFERROR(__xludf.DUMMYFUNCTION("""COMPUTED_VALUE"""),1.0) -> 1 | J53: =IFERROR(__xludf.DUMMYFUNCTION("""COMPUTED_VALUE"""),510.0) -> 510
B54: =IFERROR(__xludf.DUMMYFUNCTION("""COMPUTED_VALUE"""),"QLR") -> QLR | F54: =IFERROR(__xludf.DUMMYFUNCTION("""COMPUTED_VALUE"""),"Qlieer") -> Qlieer | G54: =IFERROR(__xludf.DUMMYFUNCTION("""COMPUTED_VALUE"""),"Adobe Arcobat") -> Adobe Arcobat | H54: =IFERROR(__xludf.DUMMYFUNCTION("""COMPUTED_VALUE"""),510.0) -> 510 | I54: =IFERROR(__xludf.DUMMYFUNCTION("""COMPUTED_VALUE"""),0.0) -> 0 | J54: =IFERROR(__xludf.DUMMYFUNCTION("""COMPUTED_VALUE"""),0.0) -> 0
B55: =IFERROR(__xludf.DUMMYFUNCTION("""COMPUTED_VALUE"""),"TW") -> TW | F55: =IFERROR(__xludf.DUMMYFUNCTION("""COMPUTED_VALUE"""),"策略資料中心") -> 策略資料中心 | G55: =IFERROR(__xludf.DUMMYFUNCTION("""COMPUTED_VALUE"""),"Adobe Arcobat") -> Adobe Arcobat | H55: =IFERROR(__xludf.DUMMYFUNCTION("""COMPUTED_VALUE"""),510.0) -> 510 | I55: =IFERROR(__xludf.DUMMYFUNCTION("""COMPUTED_VALUE"""),0.0) -> 0 | J55: =IFERROR(__xludf.DUMMYFUNCTION("""COMPUTED_VALUE"""),0.0) -> 0
B56: =IFERROR(__xludf.DUMMYFUNCTION("""COMPUTED_VALUE"""),"HK") -> HK | F56: =IFERROR(__xludf.DUMMYFUNCTION("""COMPUTED_VALUE"""),"海外執行長室") -> 海外執行長室 | G56: =IFERROR(__xludf.DUMMYFUNCTION("""COMPUTED_VALUE"""),"Adobe Arcobat") -> Adobe Arcobat | H56: =IFERROR(__xludf.DUMMYFUNCTION("""COMPUTED_VALUE"""),510.0) -> 510 | I56: =IFERROR(__xludf.DUMMYFUNCTION("""COMPUTED_VALUE"""),0.0) -> 0 | J56: =IFERROR(__xludf.DUMMYFUNCTION("""COMPUTED_VALUE"""),0.0) -> 0
B57: =IFERROR(__xludf.DUMMYFUNCTION("""COMPUTED_VALUE"""),"TW") -> TW | F57: =IFERROR(__xludf.DUMMYFUNCTION("""COMPUTED_VALUE"""),"行銷營運中心") -> 行銷營運中心 | G57: =IFERROR(__xludf.DUMMYFUNCTION("""COMPUTED_VALUE"""),"Salesforce Sales Cloud") -> Salesforce Sales Cloud | H57: =IFERROR(__xludf.DUMMYFUNCTION("""COMPUTED_VALUE"""),3728.0) -> 3728 | I57: =IFERROR(__xludf.DUMMYFUNCTION("""COMPUTED_VALUE"""),40.0) -> 40 | J57: =IFERROR(__xludf.DUMMYFUNCTION("""COMPUTED_VALUE"""),149120.0) -> 149120
B58: =IFERROR(__xludf.DUMMYFUNCTION("""COMPUTED_VALUE"""),"TW") -> TW | F58: =IFERROR(__xludf.DUMMYFUNCTION("""COMPUTED_VALUE"""),"研發中心") -> 研發中心 | G58: =IFERROR(__xludf.DUMMYFUNCTION("""COMPUTED_VALUE"""),"Salesforce Sales Cloud") -> Salesforce Sales Cloud | H58: =IFERROR(__xludf.DUMMYFUNCTION("""COMPUTED_VALUE"""),3728.0) -> 3728 | I58: =IFERROR(__xludf.DUMMYFUNCTION("""COMPUTED_VALUE"""),2.0) -> 2 | J58: =IFERROR(__xludf.DUMMYFUNCTION("""COMPUTED_VALUE"""),7456.0) -> 7456
B59: =IFERROR(__xludf.DUMMYFUNCTION("""COMPUTED_VALUE"""),"TW") -> TW | F59: =IFERROR(__xludf.DUMMYFUNCTION("""COMPUTED_VALUE"""),"客戶價值中心") -> 客戶價值中心 | G59: =IFERROR(__xludf.DUMMYFUNCTION("""COMPUTED_VALUE"""),"Salesforce Sales Cloud") -> Salesforce Sales Cloud | H59: =IFERROR(__xludf.DUMMYFUNCTION("""COMPUTED_VALUE"""),3728.0) -> 3728 | I59: =IFERROR(__xludf.DUMMYFUNCTION("""COMPUTED_VALUE"""),0.0) -> 0 | J59: =IFERROR(__xludf.DUMMYFUNCTION("""COMPUTED_VALUE"""),0.0) -> 0
B60: =IFERROR(__xludf.DUMMYFUNCTION("""COMPUTED_VALUE"""),"TW") -> TW | F60: =IFERROR(__xludf.DUMMYFUNCTION("""COMPUTED_VALUE"""),"管理中心") -> 管理中心 | G60: =IFERROR(__xludf.DUMMYFUNCTION("""COMPUTED_VALUE"""),"Salesforce Sales Cloud") -> Salesforce Sales Cloud | H60: =IFERROR(__xludf.DUMMYFUNCTION("""COMPUTED_VALUE"""),3728.0) -> 3728 | I60: =IFERROR(__xludf.DUMMYFUNCTION("""COMPUTED_VALUE"""),2.0) -> 2 | J60: =IFERROR(__xludf.DUMMYFUNCTION("""COMPUTED_VALUE"""),7456.0) -> 7456
B61: =IFERROR(__xludf.DUMMYFUNCTION("""COMPUTED_VALUE"""),"TW") -> TW | F61: =IFERROR(__xludf.DUMMYFUNCTION("""COMPUTED_VALUE"""),"執行長室") -> 執行長室 | G61: =IFERROR(__xludf.DUMMYFUNCTION("""COMPUTED_VALUE"""),"Salesforce Sales Cloud") -> Salesforce Sales Cloud | H61: =IFERROR(__xludf.DUMMYFUNCTION("""COMPUTED_VALUE"""),3728.0) -> 3728 | I61: =IFERROR(__xludf.DUMMYFUNCTION("""COMPUTED_VALUE"""),2.0) -> 2 | J61: =IFERROR(__xludf.DUMMYFUNCTION("""COMPUTED_VALUE"""),7456.0) -> 7456
B62: =IFERROR(__xludf.DUMMYFUNCTION("""COMPUTED_VALUE"""),"TW") -> TW | F62: =IFERROR(__xludf.DUMMYFUNCTION("""COMPUTED_VALUE"""),"財務中心") -> 財務中心 | G62: =IFERROR(__xludf.DUMMYFUNCTION("""COMPUTED_VALUE"""),"Salesforce Sales Cloud") -> Salesforce Sales Cloud | H62: =IFERROR(__xludf.DUMMYFUNCTION("""COMPUTED_VALUE"""),3728.0) -> 3728 | I62: =IFERROR(__xludf.DUMMYFUNCTION("""COMPUTED_VALUE"""),0.0) -> 0 | J62: =IFERROR(__xludf.DUMMYFUNCTION("""COMPUTED_VALUE"""),0.0) -> 0
B63: =IFERROR(__xludf.DUMMYFUNCTION("""COMPUTED_VALUE"""),"QLR") -> QLR | F63: =IFERROR(__xludf.DUMMYFUNCTION("""COMPUTED_VALUE"""),"Qlieer") -> Qlieer | G63: =IFERROR(__xludf.DUMMYFUNCTION("""COMPUTED_VALUE"""),"Salesforce Sales Cloud") -> Salesforce Sales Cloud | H63: =IFERROR(__xludf.DUMMYFUNCTION("""COMPUTED_VALUE"""),3728.0) -> 3728 | I63: =IFERROR(__xludf.DUMMYFUNCTION("""COMPUTED_VALUE"""),0.0) -> 0 | J63: =IFERROR(__xludf.DUMMYFUNCTION("""COMPUTED_VALUE"""),0.0) -> 0
B64: =IFERROR(__xludf.DUMMYFUNCTION("""COMPUTED_VALUE"""),"TW") -> TW | F64: =IFERROR(__xludf.DUMMYFUNCTION("""COMPUTED_VALUE"""),"策略資料中心") -> 策略資料中心 | G64: =IFERROR(__xludf.DUMMYFUNCTION("""COMPUTED_VALUE"""),"Salesforce Sales Cloud") -> Salesforce Sales Cloud | H64: =IFERROR(__xludf.DUMMYFUNCTION("""COMPUTED_VALUE"""),3728.0) -> 3728 | I64: =IFERROR(__xludf.DUMMYFUNCTION("""COMPUTED_VALUE"""),2.0) -> 2 | J64: =IFERROR(__xludf.DUMMYFUNCTION("""COMPUTED_VALUE"""),7456.0) -> 7456
B65: =IFERROR(__xludf.DUMMYFUNCTION("""COMPUTED_VALUE"""),"HK") -> HK | F65: =IFERROR(__xludf.DUMMYFUNCTION("""COMPUTED_VALUE"""),"海外執行長室") -> 海外執行長室 | G65: =IFERROR(__xludf.DUMMYFUNCTION("""COMPUTED_VALUE"""),"Salesforce Sales Cloud") -> Salesforce Sales Cloud | H65: =IFERROR(__xludf.DUMMYFUNCTION("""COMPUTED_VALUE"""),3728.0) -> 3728 | I65: =IFERROR(__xludf.DUMMYFUNCTION("""COMPUTED_VALUE"""),0.0) -> 0 | J65: =IFERROR(__xludf.DUMMYFUNCTION("""COMPUTED_VALUE"""),0.0) -> 0
B66: =IFERROR(__xludf.DUMMYFUNCTION("""COMPUTED_VALUE"""),"TW") -> TW | F66: =IFERROR(__xludf.DUMMYFUNCTION("""COMPUTED_VALUE"""),"行銷營運中心") -> 行銷營運中心 | G66: =IFERROR(__xludf.DUMMYFUNCTION("""COMPUTED_VALUE"""),"Salesforce Service Cloud") -> Salesforce Service Cloud | H66: =IFERROR(__xludf.DUMMYFUNCTION("""COMPUTED_VALUE"""),3728.0) -> 3728 | I66: =IFERROR(__xludf.DUMMYFUNCTION("""COMPUTED_VALUE"""),0.0) -> 0 | J66: =IFERROR(__xludf.DUMMYFUNCTION("""COMPUTED_VALUE"""),0.0) -> 0
B67: =IFERROR(__xludf.DUMMYFUNCTION("""COMPUTED_VALUE"""),"TW") -> TW | F67: =IFERROR(__xludf.DUMMYFUNCTION("""COMPUTED_VALUE"""),"研發中心") -> 研發中心 | G67: =IFERROR(__xludf.DUMMYFUNCTION("""COMPUTED_VALUE"""),"Salesforce Service Cloud") -> Salesforce Service Cloud | H67: =IFERROR(__xludf.DUMMYFUNCTION("""COMPUTED_VALUE"""),3728.0) -> 3728 | I67: =IFERROR(__xludf.DUMMYFUNCTION("""COMPUTED_VALUE"""),0.0) -> 0 | J67: =IFERROR(__xludf.DUMMYFUNCTION("""COMPUTED_VALUE"""),0.0) -> 0
B68: =IFERROR(__xludf.DUMMYFUNCTION("""COMPUTED_VALUE"""),"TW") -> TW | F68: =IFERROR(__xludf.DUMMYFUNCTION("""COMPUTED_VALUE"""),"客戶價值中心") -> 客戶價值中心 | G68: =IFERROR(__xludf.DUMMYFUNCTION("""COMPUTED_VALUE"""),"Salesforce Service Cloud") -> Salesforce Service Cloud | H68: =IFERROR(__xludf.DUMMYFUNCTION("""COMPUTED_VALUE"""),3728.0) -> 3728 | I68: =IFERROR(__xludf.DUMMYFUNCTION("""COMPUTED_VALUE"""),28.0) -> 28 | J68: =IFERROR(__xludf.DUMMYFUNCTION("""COMPUTED_VALUE"""),104384.0) -> 104384
B69: =IFERROR(__xludf.DUMMYFUNCTION("""COMPUTED_VALUE"""),"TW") -> TW | F69: =IFERROR(__xludf.DUMMYFUNCTION("""COMPUTED_VALUE"""),"管理中心") -> 管理中心 | G69: =IFERROR(__xludf.DUMMYFUNCTION("""COMPUTED_VALUE"""),"Salesforce Service Cloud") -> Salesforce Service Cloud | H69: =IFERROR(__xludf.DUMMYFUNCTION("""COMPUTED_VALUE"""),3728.0) -> 3728 | I69: =IFERROR(__xludf.DUMMYFUNCTION("""COMPUTED_VALUE"""),4.0) -> 4 | J69: =IFERROR(__xludf.DUMMYFUNCTION("""COMPUTED_VALUE"""),14912.0) -> 14912
B70: =IFERROR(__xludf.DUMMYFUNCTION("""COMPUTED_VALUE"""),"TW") -> TW | F70: =IFERROR(__xludf.DUMMYFUNCTION("""COMPUTED_VALUE"""),"執行長室") -> 執行長室 | G70: =IFERROR(__xludf.DUMMYFUNCTION("""COMPUTED_VALUE"""),"Salesforce Service Cloud") -> Salesforce Service Cloud | H70: =IFERROR(__xludf.DUMMYFUNCTION("""COMPUTED_VALUE"""),3728.0) -> 3728 | I70: =IFERROR(__xludf.DUMMYFUNCTION("""COMPUTED_VALUE"""),0.0) -> 0 | J70: =IFERROR(__xludf.DUMMYFUNCTION("""COMPUTED_VALUE"""),0.0) -> 0
B71: =IFERROR(__xludf.DUMMYFUNCTION("""COMPUTED_VALUE"""),"TW") -> TW | F71: =IFERROR(__xludf.DUMMYFUNCTION("""COMPUTED_VALUE"""),"財務中心") -> 財務中心 | G71: =IFERROR(__xludf.DUMMYFUNCTION("""COMPUTED_VALUE"""),"Salesforce Service Cloud") -> Salesforce Service Cloud | H71: =IFERROR(__xludf.DUMMYFUNCTION("""COMPUTED_VALUE"""),3728.0) -> 3728 | I71: =IFERROR(__xludf.DUMMYFUNCTION("""COMPUTED_VALUE"""),0.0) -> 0 | J71: =IFERROR(__xludf.DUMMYFUNCTION("""COMPUTED_VALUE"""),0.0) -> 0
B72: =IFERROR(__xludf.DUMMYFUNCTION("""COMPUTED_VALUE"""),"QLR") -> QLR | F72: =IFERROR(__xludf.DUMMYFUNCTION("""COMPUTED_VALUE"""),"Qlieer") -> Qlieer | G72: =IFERROR(__xludf.DUMMYFUNCTION("""COMPUTED_VALUE"""),"Salesforce Service Cloud") -> Salesforce Service Cloud | H72: =IFERROR(__xludf.DUMMYFUNCTION("""COMPUTED_VALUE"""),3728.0) -> 3728 | I72: =IFERROR(__xludf.DUMMYFUNCTION("""COMPUTED_VALUE"""),0.0) -> 0 | J72: =IFERROR(__xludf.DUMMYFUNCTION("""COMPUTED_VALUE"""),0.0) -> 0
B73: =IFERROR(__xludf.DUMMYFUNCTION("""COMPUTED_VALUE"""),"TW") -> TW | F73: =IFERROR(__xludf.DUMMYFUNCTION("""COMPUTED_VALUE"""),"策略資料中心") -> 策略資料中心 | G73: =IFERROR(__xludf.DUMMYFUNCTION("""COMPUTED_VALUE"""),"Salesforce Service Cloud") -> Salesforce Service Cloud | H73: =IFERROR(__xludf.DUMMYFUNCTION("""COMPUTED_VALUE"""),3728.0) -> 3728 | I73: =IFERROR(__xludf.DUMMYFUNCTION("""COMPUTED_VALUE"""),0.0) -> 0 | J73: =IFERROR(__xludf.DUMMYFUNCTION("""COMPUTED_VALUE"""),0.0) -> 0
B74: =IFERROR(__xludf.DUMMYFUNCTION("""COMPUTED_VALUE"""),"HK") -> HK | F74: =IFERROR(__xludf.DUMMYFUNCTION("""COMPUTED_VALUE"""),"海外執行長室") -> 海外執行長室 | G74: =IFERROR(__xludf.DUMMYFUNCTION("""COMPUTED_VALUE"""),"Salesforce Service Cloud") -> Salesforce Service Cloud | H74: =IFERROR(__xludf.DUMMYFUNCTION("""COMPUTED_VALUE"""),3728.0) -> 3728 | I74: =IFERROR(__xludf.DUMMYFUNCTION("""COMPUTED_VALUE"""),0.0) -> 0 | J74: =IFERROR(__xludf.DUMMYFUNCTION("""COMPUTED_VALUE"""),0.0) -> 0
B75: =IFERROR(__xludf.DUMMYFUNCTION("""COMPUTED_VALUE"""),"TW") -> TW | F75: =IFERROR(__xludf.DUMMYFUNCTION("""COMPUTED_VALUE"""),"行銷營運中心") -> 行銷營運中心 | G75: =IFERROR(__xludf.DUMMYFUNCTION("""COMPUTED_VALUE"""),"Salesforce Sales+Service Cloud") -> Salesforce Sales+Service Cloud | H75: =IFERROR(__xludf.DUMMYFUNCTION("""COMPUTED_VALUE"""),4680.0) -> 4680 | I75: =IFERROR(__xludf.DUMMYFUNCTION("""COMPUTED_VALUE"""),0.0) -> 0 | J75: =IFERROR(__xludf.DUMMYFUNCTION("""COMPUTED_VALUE"""),0.0) -> 0
B76: =IFERROR(__xludf.DUMMYFUNCTION("""COMPUTED_VALUE"""),"TW") -> TW | F76: =IFERROR(__xludf.DUMMYFUNCTION("""COMPUTED_VALUE"""),"研發中心") -> 研發中心 | G76: =IFERROR(__xludf.DUMMYFUNCTION("""COMPUTED_VALUE"""),"Salesforce Sales+Service Cloud") -> Salesforce Sales+Service Cloud | H76: =IFERROR(__xludf.DUMMYFUNCTION("""COMPUTED_VALUE"""),4680.0) -> 4680 | I76: =IFERROR(__xludf.DUMMYFUNCTION("""COMPUTED_VALUE"""),0.0) -> 0 | J76: =IFERROR(__xludf.DUMMYFUNCTION("""COMPUTED_VALUE"""),0.0) -> 0
B77: =IFERROR(__xludf.DUMMYFUNCTION("""COMPUTED_VALUE"""),"TW") -> TW | F77: =IFERROR(__xludf.DUMMYFUNCTION("""COMPUTED_VALUE"""),"客戶價值中心") -> 客戶價值中心 | G77: =IFERROR(__xludf.DUMMYFUNCTION("""COMPUTED_VALUE"""),"Salesforce Sales+Service Cloud") -> Salesforce Sales+Service Cloud | H77: =IFERROR(__xludf.DUMMYFUNCTION("""COMPUTED_VALUE"""),4680.0) -> 4680 | I77: =IFERROR(__xludf.DUMMYFUNCTION("""COMPUTED_VALUE"""),0.0) -> 0 | J77: =IFERROR(__xludf.DUMMYFUNCTION("""COMPUTED_VALUE"""),0.0) -> 0
B78: =IFERROR(__xludf.DUMMYFUNCTION("""COMPUTED_VALUE"""),"TW") -> TW | F78: =IFERROR(__xludf.DUMMYFUNCTION("""COMPUTED_VALUE"""),"管理中心") -> 管理中心 | G78: =IFERROR(__xludf.DUMMYFUNCTION("""COMPUTED_VALUE"""),"Salesforce Sales+Service Cloud") -> Salesforce Sales+Service Cloud | H78: =IFERROR(__xludf.DUMMYFUNCTION("""COMPUTED_VALUE"""),4680.0) -> 4680 | I78: =IFERROR(__xludf.DUMMYFUNCTION("""COMPUTED_VALUE"""),2.0) -> 2 | J78: =IFERROR(__xludf.DUMMYFUNCTION("""COMPUTED_VALUE"""),9360.0) -> 9360
B79: =IFERROR(__xludf.DUMMYFUNCTION("""COMPUTED_VALUE"""),"TW") -> TW | F79: =IFERROR(__xludf.DUMMYFUNCTION("""COMPUTED_VALUE"""),"執行長室") -> 執行長室 | G79: =IFERROR(__xludf.DUMMYFUNCTION("""COMPUTED_VALUE"""),"Salesforce Sales+Service Cloud") -> Salesforce Sales+Service Cloud | H79: =IFERROR(__xludf.DUMMYFUNCTION("""COMPUTED_VALUE"""),4680.0) -> 4680 | I79: =IFERROR(__xludf.DUMMYFUNCTION("""COMPUTED_VALUE"""),0.0) -> 0 | J79: =IFERROR(__xludf.DUMMYFUNCTION("""COMPUTED_VALUE"""),0.0) -> 0
B80: =IFERROR(__xludf.DUMMYFUNCTION("""COMPUTED_VALUE"""),"TW") -> TW | F80: =IFERROR(__xludf.DUMMYFUNCTION("""COMPUTED_VALUE"""),"財務中心") -> 財務中心 | G80: =IFERROR(__xludf.DUMMYFUNCTION("""COMPUTED_VALUE"""),"Salesforce Sales+Service Cloud") -> Salesforce Sales+Service Cloud | H80: =IFERROR(__xludf.DUMMYFUNCTION("""COMPUTED_VALUE"""),4680.0) -> 4680 | I80: =IFERROR(__xludf.DUMMYFUNCTION("""COMPUTED_VALUE"""),0.0) -> 0 | J80: =IFERROR(__xludf.DUMMYFUNCTION("""COMPUTED_VALUE"""),0.0) -> 0
B81: =IFERROR(__xludf.DUMMYFUNCTION("""COMPUTED_VALUE"""),"QLR") -> QLR | F81: =IFERROR(__xludf.DUMMYFUNCTION("""COMPUTED_VALUE"""),"Qlieer") -> Qlieer | G81: =IFERROR(__xludf.DUMMYFUNCTION("""COMPUTED_VALUE"""),"Salesforce Sales+Service Cloud") -> Salesforce Sales+Service Cloud | H81: =IFERROR(__xludf.DUMMYFUNCTION("""COMPUTED_VALUE"""),4680.0) -> 4680 | I81: =IFERROR(__xludf.DUMMYFUNCTION("""COMPUTED_VALUE"""),0.0) -> 0 | J81: =IFERROR(__xludf.DUMMYFUNCTION("""COMPUTED_VALUE"""),0.0) -> 0
B82: =IFERROR(__xludf.DUMMYFUNCTION("""COMPUTED_VALUE"""),"TW") -> TW | F82: =IFERROR(__xludf.DUMMYFUNCTION("""COMPUTED_VALUE"""),"策略資料中心") -> 策略資料中心 | G82: =IFERROR(__xludf.DUMMYFUNCTION("""COMPUTED_VALUE"""),"Salesforce Sales+Service Cloud") -> Salesforce Sales+Service Cloud | H82: =IFERROR(__xludf.DUMMYFUNCTION("""COMPUTED_VALUE"""),4680.0) -> 4680 | I82: =IFERROR(__xludf.DUMMYFUNCTION("""COMPUTED_VALUE"""),0.0) -> 0 | J82: =IFERROR(__xludf.DUMMYFUNCTION("""COMPUTED_VALUE"""),0.0) -> 0
B83: =IFERROR(__xludf.DUMMYFUNCTION("""COMPUTED_VALUE"""),"HK") -> HK | F83: =IFERROR(__xludf.DUMMYFUNCTION("""COMPUTED_VALUE"""),"海外執行長室") -> 海外執行長室 | G83: =IFERROR(__xludf.DUMMYFUNCTION("""COMPUTED_VALUE"""),"Salesforce Sales+Service Cloud") -> Salesforce Sales+Service Cloud | H83: =IFERROR(__xludf.DUMMYFUNCTION("""COMPUTED_VALUE"""),4680.0) -> 4680 | I83: =IFERROR(__xludf.DUMMYFUNCTION("""COMPUTED_VALUE"""),0.0) -> 0 | J83: =IFERROR(__xludf.DUMMYFUNCTION("""COMPUTED_VALUE"""),0.0) -> 0
B84: =IFERROR(__xludf.DUMMYFUNCTION("""COMPUTED_VALUE"""),"TW") -> TW | F84: =IFERROR(__xludf.DUMMYFUNCTION("""COMPUTED_VALUE"""),"行銷營運中心") -> 行銷營運中心 | G84: =IFERROR(__xludf.DUMMYFUNCTION("""COMPUTED_VALUE"""),"點點簽") -> 點點簽 | H84: =IFERROR(__xludf.DUMMYFUNCTION("""COMPUTED_VALUE"""),450.0) -> 450 | I84: =IFERROR(__xludf.DUMMYFUNCTION("""COMPUTED_VALUE"""),3.0) -> 3 | J84: =IFERROR(__xludf.DUMMYFUNCTION("""COMPUTED_VALUE"""),1350.0) -> 1350
B85: =IFERROR(__xludf.DUMMYFUNCTION("""COMPUTED_VALUE"""),"TW") -> TW | F85: =IFERROR(__xludf.DUMMYFUNCTION("""COMPUTED_VALUE"""),"研發中心") -> 研發中心 | G85: =IFERROR(__xludf.DUMMYFUNCTION("""COMPUTED_VALUE"""),"點點簽") -> 點點簽 | H85: =IFERROR(__xludf.DUMMYFUNCTION("""COMPUTED_VALUE"""),450.0) -> 450 | I85: =IFERROR(__xludf.DUMMYFUNCTION("""COMPUTED_VALUE"""),0.0) -> 0 | J85: =IFERROR(__xludf.DUMMYFUNCTION("""COMPUTED_VALUE"""),0.0) -> 0
B86: =IFERROR(__xludf.DUMMYFUNCTION("""COMPUTED_VALUE"""),"TW") -> TW | F86: =IFERROR(__xludf.DUMMYFUNCTION("""COMPUTED_VALUE"""),"客戶價值中心") -> 客戶價值中心 | G86: =IFERROR(__xludf.DUMMYFUNCTION("""COMPUTED_VALUE"""),"點點簽") -> 點點簽 | H86: =IFERROR(__xludf.DUMMYFUNCTION("""COMPUTED_VALUE"""),450.0) -> 450 | I86: =IFERROR(__xludf.DUMMYFUNCTION("""COMPUTED_VALUE"""),1.0) -> 1 | J86: =IFERROR(__xludf.DUMMYFUNCTION("""COMPUTED_VALUE"""),450.0) -> 450
B87: =IFERROR(__xludf.DUMMYFUNCTION("""COMPUTED_VALUE"""),"TW") -> TW | F87: =IFERROR(__xludf.DUMMYFUNCTION("""COMPUTED_VALUE"""),"管理中心") -> 管理中心 | G87: =IFERROR(__xludf.DUMMYFUNCTION("""COMPUTED_VALUE"""),"點點簽") -> 點點簽 | H87: =IFERROR(__xludf.DUMMYFUNCTION("""COMPUTED_VALUE"""),450.0) -> 450 | I87: =IFERROR(__xludf.DUMMYFUNCTION("""COMPUTED_VALUE"""),2.0) -> 2 | J87: =IFERROR(__xludf.DUMMYFUNCTION("""COMPUTED_VALUE"""),900.0) -> 900
B88: =IFERROR(__xludf.DUMMYFUNCTION("""COMPUTED_VALUE"""),"TW") -> TW | F88: =IFERROR(__xludf.DUMMYFUNCTION("""COMPUTED_VALUE"""),"執行長室") -> 執行長室 | G88: =IFERROR(__xludf.DUMMYFUNCTION("""COMPUTED_VALUE"""),"點點簽") -> 點點簽 | H88: =IFERROR(__xludf.DUMMYFUNCTION("""COMPUTED_VALUE"""),450.0) -> 450 | I88: =IFERROR(__xludf.DUMMYFUNCTION("""COMPUTED_VALUE"""),0.0) -> 0 | J88: =IFERROR(__xludf.DUMMYFUNCTION("""COMPUTED_VALUE"""),0.0) -> 0
B89: =IFERROR(__xludf.DUMMYFUNCTION("""COMPUTED_VALUE"""),"TW") -> TW | F89: =IFERROR(__xludf.DUMMYFUNCTION("""COMPUTED_VALUE"""),"財務中心") -> 財務中心 | G89: =IFERROR(__xludf.DUMMYFUNCTION("""COMPUTED_VALUE"""),"點點簽") -> 點點簽 | H89: =IFERROR(__xludf.DUMMYFUNCTION("""COMPUTED_VALUE"""),450.0) -> 450 | I89: =IFERROR(__xludf.DUMMYFUNCTION("""COMPUTED_VALUE"""),0.0) -> 0 | J89: =IFERROR(__xludf.DUMMYFUNCTION("""COMPUTED_VALUE"""),0.0) -> 0
B90: =IFERROR(__xludf.DUMMYFUNCTION("""COMPUTED_VALUE"""),"QLR") -> QLR | F90: =IFERROR(__xludf.DUMMYFUNCTION("""COMPUTED_VALUE"""),"Qlieer") -> Qlieer | G90: =IFERROR(__xludf.DUMMYFUNCTION("""COMPUTED_VALUE"""),"點點簽") -> 點點簽 | H90: =IFERROR(__xludf.DUMMYFUNCTION("""COMPUTED_VALUE"""),450.0) -> 450 | I90: =IFERROR(__xludf.DUMMYFUNCTION("""COMPUTED_VALUE"""),0.0) -> 0 | J90: =IFERROR(__xludf.DUMMYFUNCTION("""COMPUTED_VALUE"""),0.0) -> 0
B91: =IFERROR(__xludf.DUMMYFUNCTION("""COMPUTED_VALUE"""),"TW") -> TW | F91: =IFERROR(__xludf.DUMMYFUNCTION("""COMPUTED_VALUE"""),"策略資料中心") -> 策略資料中心 | G91: =IFERROR(__xludf.DUMMYFUNCTION("""COMPUTED_VALUE"""),"點點簽") -> 點點簽 | H91: =IFERROR(__xludf.DUMMYFUNCTION("""COMPUTED_VALUE"""),450.0) -> 450 | I91: =IFERROR(__xludf.DUMMYFUNCTION("""COMPUTED_VALUE"""),0.0) -> 0 | J91: =IFERROR(__xludf.DUMMYFUNCTION("""COMPUTED_VALUE"""),0.0) -> 0
B92: =IFERROR(__xludf.DUMMYFUNCTION("""COMPUTED_VALUE"""),"HK") -> HK | F92: =IFERROR(__xludf.DUMMYFUNCTION("""COMPUTED_VALUE"""),"海外執行長室") -> 海外執行長室 | G92: =IFERROR(__xludf.DUMMYFUNCTION("""COMPUTED_VALUE"""),"點點簽") -> 點點簽 | H92: =IFERROR(__xludf.DUMMYFUNCTION("""COMPUTED_VALUE"""),450.0) -> 450 | I92: =IFERROR(__xludf.DUMMYFUNCTION("""COMPUTED_VALUE"""),0.0) -> 0 | J92: =IFERROR(__xludf.DUMMYFUNCTION("""COMPUTED_VALUE"""),0.0) -> 0
B93: =IFERROR(__xludf.DUMMYFUNCTION("""COMPUTED_VALUE"""),"TW") -> TW | F93: =IFERROR(__xludf.DUMMYFUNCTION("""COMPUTED_VALUE"""),"行銷營運中心") -> 行銷營運中心 | G93: =IFERROR(__xludf.DUMMYFUNCTION("""COMPUTED_VALUE"""),"JAMF ") -> JAMF | H93: =IFERROR(__xludf.DUMMYFUNCTION("""COMPUTED_VALUE"""),300.0) -> 300 | J93: =IFERROR(__xludf.DUMMYFUNCTION("""COMPUTED_VALUE"""),0.0) -> 0
B94: =IFERROR(__xludf.DUMMYFUNCTION("""COMPUTED_VALUE"""),"TW") -> TW | F94: =IFERROR(__xludf.DUMMYFUNCTION("""COMPUTED_VALUE"""),"研發中心") -> 研發中心 | G94: =IFERROR(__xludf.DUMMYFUNCTION("""COMPUTED_VALUE"""),"JAMF ") -> JAMF | H94: =IFERROR(__xludf.DUMMYFUNCTION("""COMPUTED_VALUE"""),300.0) -> 300 | J94: =IFERROR(__xludf.DUMMYFUNCTION("""COMPUTED_VALUE"""),0.0) -> 0
B95: =IFERROR(__xludf.DUMMYFUNCTION("""COMPUTED_VALUE"""),"TW") -> TW | F95: =IFERROR(__xludf.DUMMYFUNCTION("""COMPUTED_VALUE"""),"客戶價值中心") -> 客戶價值中心 | G95: =IFERROR(__xludf.DUMMYFUNCTION("""COMPUTED_VALUE"""),"JAMF ") -> JAMF | H95: =IFERROR(__xludf.DUMMYFUNCTION("""COMPUTED_VALUE"""),300.0) -> 300 | J95: =IFERROR(__xludf.DUMMYFUNCTION("""COMPUTED_VALUE"""),0.0) -> 0
B96: =IFERROR(__xludf.DUMMYFUNCTION("""COMPUTED_VALUE"""),"TW") -> TW | F96: =IFERROR(__xludf.DUMMYFUNCTION("""COMPUTED_VALUE"""),"管理中心") -> 管理中心 | G96: =IFERROR(__xludf.DUMMYFUNCTION("""COMPUTED_VALUE"""),"JAMF ") -> JAMF | H96: =IFERROR(__xludf.DUMMYFUNCTION("""COMPUTED_VALUE"""),300.0) -> 300 | J96: =IFERROR(__xludf.DUMMYFUNCTION("""COMPUTED_VALUE"""),0.0) -> 0
B97: =IFERROR(__xludf.DUMMYFUNCTION("""COMPUTED_VALUE"""),"TW") -> TW | F97: =IFERROR(__xludf.DUMMYFUNCTION("""COMPUTED_VALUE"""),"執行長室") -> 執行長室 | G97: =IFERROR(__xludf.DUMMYFUNCTION("""COMPUTED_VALUE"""),"JAMF ") -> JAMF | H97: =IFERROR(__xludf.DUMMYFUNCTION("""COMPUTED_VALUE"""),300.0) -> 300 | J97: =IFERROR(__xludf.DUMMYFUNCTION("""COMPUTED_VALUE"""),0.0) -> 0
B98: =IFERROR(__xludf.DUMMYFUNCTION("""COMPUTED_VALUE"""),"TW") -> TW | F98: =IFERROR(__xludf.DUMMYFUNCTION("""COMPUTED_VALUE"""),"財務中心") -> 財務中心 | G98: =IFERROR(__xludf.DUMMYFUNCTION("""COMPUTED_VALUE"""),"JAMF ") -> JAMF | H98: =IFERROR(__xludf.DUMMYFUNCTION("""COMPUTED_VALUE"""),300.0) -> 300 | J98: =IFERROR(__xludf.DUMMYFUNCTION("""COMPUTED_VALUE"""),0.0) -> 0
B99: =IFERROR(__xludf.DUMMYFUNCTION("""COMPUTED_VALUE"""),"QLR") -> QLR | F99: =IFERROR(__xludf.DUMMYFUNCTION("""COMPUTED_VALUE"""),"Qlieer") -> Qlieer | G99: =IFERROR(__xludf.DUMMYFUNCTION("""COMPUTED_VALUE"""),"JAMF ") -> JAMF | H99: =IFERROR(__xludf.DUMMYFUNCTION("""COMPUTED_VALUE"""),300.0) -> 300 | J99: =IFERROR(__xludf.DUMMYFUNCTION("""COMPUTED_VALUE"""),0.0) -> 0
B100: =IFERROR(__xludf.DUMMYFUNCTION("""COMPUTED_VALUE"""),"TW") -> TW | F100: =IFERROR(__xludf.DUMMYFUNCTION("""COMPUTED_VALUE"""),"策略資料中心") -> 策略資料中心 | G100: =IFERROR(__xludf.DUMMYFUNCTION("""COMPUTED_VALUE"""),"JAMF ") -> JAMF | H100: =IFERROR(__xludf.DUMMYFUNCTION("""COMPUTED_VALUE"""),300.0) -> 300 | J100: =IFERROR(__xludf.DUMMYFUNCTION("""COMPUTED_VALUE"""),0.0) -> 0
...

Sheet 中心通用帳號盤點
B1: =IFERROR(__xludf.DUMMYFUNCTION("IMPORTRANGE(""https://docs.google.com/spreadsheets/d/1cg3_Ki8lTqFvPzESMZ9gT2Ca86Cm7f89AKRurSr-zVk/edit?gid=0#gid=0"",""2026 各中心共通帳號費用!A1:z"")"),"子公司") -> 子公司 | C1: =IFERROR(__xludf.DUMMYFUNCTION("""COMPUTED_VALUE"""),"事業單位") -> 事業單位 | D1: =IFERROR(__xludf.DUMMYFUNCTION("""COMPUTED_VALUE"""),"Si 編號") -> Si 編號 | E1: =IFERROR(__xludf.DUMMYFUNCTION("""COMPUTED_VALUE"""),"TA 編號") -> TA 編號 | F1: =IFERROR(__xludf.DUMMYFUNCTION("""COMPUTED_VALUE"""),"費用單位 (Netsuite Department)") -> 費用單位 (Netsuite Department) | G1: =IFERROR(__xludf.DUMMYFUNCTION("""COMPUTED_VALUE"""),"費用項目") -> 費用項目 | H1: =IFERROR(__xludf.DUMMYFUNCTION("""COMPUTED_VALUE"""),"單價") -> 單價 | I1: =IFERROR(__xludf.DUMMYFUNCTION("""COMPUTED_VALUE"""),"現有帳號數量") -> 現有帳號數量 | J1: =IFERROR(__xludf.DUMMYFUNCTION("""COMPUTED_VALUE"""),"現有每月費用") -> 現有每月費用 | K1: =IFERROR(__xludf.DUMMYFUNCTION("""COMPUTED_VALUE"""),"預計新人帳號數量") -> 預計新人帳號數量 | L1: =IFERROR(__xludf.DUMMYFUNCTION("""COMPUTED_VALUE"""),"預計新人費用") -> 預計新人費用
B2: =IFERROR(__xludf.DUMMYFUNCTION("""COMPUTED_VALUE"""),"歸屬子公司，例如:TW、QLR") -> 歸屬子公司，例如:TW、QLR | C2: =IFERROR(__xludf.DUMMYFUNCTION("""COMPUTED_VALUE"""),"不需填寫") -> 不需填寫 | D2: =IFERROR(__xludf.DUMMYFUNCTION("""COMPUTED_VALUE"""),"不需填寫") -> 不需填寫 | E2: =IFERROR(__xludf.DUMMYFUNCTION("""COMPUTED_VALUE"""),"不需填寫") -> 不需填寫 | F2: =IFERROR(__xludf.DUMMYFUNCTION("""COMPUTED_VALUE"""),"需按中心/部門/團隊規格，例如：行銷營運中心:銷售營運部:導入教練團隊") -> 需按中心/部門/團隊規格，例如：行銷營運中心:銷售營運部:導入教練團隊 | G2: =IFERROR(__xludf.DUMMYFUNCTION("""COMPUTED_VALUE"""),"請填寫工具名稱與品項，例如：Tableau Viewer 帳號") -> 請填寫工具名稱與品項，例如：Tableau Viewer 帳號 | H2: =IFERROR(__xludf.DUMMYFUNCTION("""COMPUTED_VALUE"""),"填品項金額，例如 300") -> 填品項金額，例如 300 | I2: =IFERROR(__xludf.DUMMYFUNCTION("""COMPUTED_VALUE"""),"填寫現有員工帳號數，例如：3") -> 填寫現有員工帳號數，例如：3 | J2: =IFERROR(__xludf.DUMMYFUNCTION("""COMPUTED_VALUE"""),"公式：單價 x 現有帳號數量") -> 公式：單價 x 現有帳號數量 | K2: =IFERROR(__xludf.DUMMYFUNCTION("""COMPUTED_VALUE"""),"填寫新員工帳號數，例如：3") -> 填寫新員工帳號數，例如：3 | L2: =IFERROR(__xludf.DUMMYFUNCTION("""COMPUTED_VALUE"""),"公式：單價 x 預計新人帳號數量") -> 公式：單價 x 預計新人帳號數量
B3: =IFERROR(__xludf.DUMMYFUNCTION("""COMPUTED_VALUE"""),"TW") -> TW | F3: =IFERROR(__xludf.DUMMYFUNCTION("""COMPUTED_VALUE"""),"行銷營運中心") -> 行銷營運中心 | G3: =IFERROR(__xludf.DUMMYFUNCTION("""COMPUTED_VALUE"""),"GWS") -> GWS | H3: =IFERROR(__xludf.DUMMYFUNCTION("""COMPUTED_VALUE"""),412.0) -> 412 | I3: =IFERROR(__xludf.DUMMYFUNCTION("""COMPUTED_VALUE"""),56.0) -> 56 | J3: =IFERROR(__xludf.DUMMYFUNCTION("""COMPUTED_VALUE"""),23072.0) -> 23072
B4: =IFERROR(__xludf.DUMMYFUNCTION("""COMPUTED_VALUE"""),"TW") -> TW | F4: =IFERROR(__xludf.DUMMYFUNCTION("""COMPUTED_VALUE"""),"研發中心") -> 研發中心 | G4: =IFERROR(__xludf.DUMMYFUNCTION("""COMPUTED_VALUE"""),"GWS") -> GWS | H4: =IFERROR(__xludf.DUMMYFUNCTION("""COMPUTED_VALUE"""),412.0) -> 412 | I4: =IFERROR(__xludf.DUMMYFUNCTION("""COMPUTED_VALUE"""),54.0) -> 54 | J4: =IFERROR(__xludf.DUMMYFUNCTION("""COMPUTED_VALUE"""),22248.0) -> 22248
B5: =IFERROR(__xludf.DUMMYFUNCTION("""COMPUTED_VALUE"""),"TW") -> TW | F5: =IFERROR(__xludf.DUMMYFUNCTION("""COMPUTED_VALUE"""),"客戶價值中心") -> 客戶價值中心 | G5: =IFERROR(__xludf.DUMMYFUNCTION("""COMPUTED_VALUE"""),"GWS") -> GWS | H5: =IFERROR(__xludf.DUMMYFUNCTION("""COMPUTED_VALUE"""),412.0) -> 412 | I5: =IFERROR(__xludf.DUMMYFUNCTION("""COMPUTED_VALUE"""),33.0) -> 33 | J5: =IFERROR(__xludf.DUMMYFUNCTION("""COMPUTED_VALUE"""),13596.0) -> 13596
B6: =IFERROR(__xludf.DUMMYFUNCTION("""COMPUTED_VALUE"""),"TW") -> TW | F6: =IFERROR(__xludf.DUMMYFUNCTION("""COMPUTED_VALUE"""),"管理中心") -> 管理中心 | G6: =IFERROR(__xludf.DUMMYFUNCTION("""COMPUTED_VALUE"""),"GWS") -> GWS | H6: =IFERROR(__xludf.DUMMYFUNCTION("""COMPUTED_VALUE"""),412.0) -> 412 | I6: =IFERROR(__xludf.DUMMYFUNCTION("""COMPUTED_VALUE"""),14.0) -> 14 | J6: =IFERROR(__xludf.DUMMYFUNCTION("""COMPUTED_VALUE"""),5768.0) -> 5768
B7: =IFERROR(__xludf.DUMMYFUNCTION("""COMPUTED_VALUE"""),"TW") -> TW | F7: =IFERROR(__xludf.DUMMYFUNCTION("""COMPUTED_VALUE"""),"執行長室") -> 執行長室 | G7: =IFERROR(__xludf.DUMMYFUNCTION("""COMPUTED_VALUE"""),"GWS") -> GWS | H7: =IFERROR(__xludf.DUMMYFUNCTION("""COMPUTED_VALUE"""),412.0) -> 412 | I7: =IFERROR(__xludf.DUMMYFUNCTION("""COMPUTED_VALUE"""),4.0) -> 4 | J7: =IFERROR(__xludf.DUMMYFUNCTION("""COMPUTED_VALUE"""),1648.0) -> 1648
B8: =IFERROR(__xludf.DUMMYFUNCTION("""COMPUTED_VALUE"""),"TW") -> TW | F8: =IFERROR(__xludf.DUMMYFUNCTION("""COMPUTED_VALUE"""),"財務中心") -> 財務中心 | G8: =IFERROR(__xludf.DUMMYFUNCTION("""COMPUTED_VALUE"""),"GWS") -> GWS | H8: =IFERROR(__xludf.DUMMYFUNCTION("""COMPUTED_VALUE"""),412.0) -> 412 | I8: =IFERROR(__xludf.DUMMYFUNCTION("""COMPUTED_VALUE"""),6.0) -> 6 | J8: =IFERROR(__xludf.DUMMYFUNCTION("""COMPUTED_VALUE"""),2472.0) -> 2472
